Workbook

Sheet P&L
A1: alche — 24-Month P&L
A2: Pre-Seed | EUR 500K @ EUR 2.5M Cap | All decisions applied | Formula-based
A3: All amounts in EUR. Click any cell to see the formula.
A4: Budget P&L (EUR) | B4: M1 | C4: M2 | D4: M3 | E4: M4 | F4: M5 | G4: M6 | H4: M7 | I4: M8 | J4: M9 | K4: M10 | L4: M11 | M4: M12 | N4: M13 | O4: M14 | P4: M15 | Q4: M16 | R4: M17 | S4: M18 | T4: M19 | U4: M20 | V4: M21 | W4: M22 | X4: M23 | Y4: M24 | Z4: TOTAL
A5: SUBSCRIBER METRICS
A6: New Subs Added | B6: ='Growth Curves'!B14 | C6: ='Growth Curves'!C14 | D6: ='Growth Curves'!D14 | E6: ='Growth Curves'!E14 | F6: ='Growth Curves'!F14 | G6: ='Growth Curves'!G14 | H6: ='Growth Curves'!H14 | I6: ='Growth Curves'!I14 | ... Y6: ='Growth Curves'!Y14 | Z6: =SUM(B6:Y6)
A7: Churned Subs | B7: ='Growth Curves'!B15 | C7: ='Growth Curves'!C15 | D7: ='Growth Curves'!D15 | E7: ='Growth Curves'!E15 | F7: ='Growth Curves'!F15 | G7: ='Growth Curves'!G15 | H7: ='Growth Curves'!H15 | I7: ='Growth Curves'!I15 | ... Y7: ='Growth Curves'!Y15 | Z7: =SUM(B7:Y7)
A8: Total Subscribers | B8: ='Growth Curves'!B16 | C8: ='Growth Curves'!C16 | D8: ='Growth Curves'!D16 | E8: ='Growth Curves'!E16 | F8: ='Growth Curves'!F16 | G8: ='Growth Curves'!G16 | H8: ='Growth Curves'!H16 | I8: ='Growth Curves'!I16 | ... Y8: ='Growth Curves'!Y16 | Z8: =SUM(B8:Y8)
A9: Core (52%) | B9: ='Growth Curves'!B17 | C9: ='Growth Curves'!C17 | D9: ='Growth Curves'!D17 | E9: ='Growth Curves'!E17 | F9: ='Growth Curves'!F17 | G9: ='Growth Curves'!G17 | H9: ='Growth Curves'!H17 | I9: ='Growth Curves'!I17 | ... Y9: ='Growth Curves'!Y17 | Z9: =SUM(B9:Y9)
A10: Pro (38%) | B10: ='Growth Curves'!B18 | C10: ='Growth Curves'!C18 | D10: ='Growth Curves'!D18 | E10: ='Growth Curves'!E18 | F10: ='Growth Curves'!F18 | G10: ='Growth Curves'!G18 | H10: ='Growth Curves'!H18 | I10: ='Growth Curves'!I18 | ... Y10: ='Growth Curves'!Y18 | Z10: =SUM(B10:Y10)
A11: Premium (10%) | B11: ='Growth Curves'!B19 | C11: ='Growth Curves'!C19 | D11: ='Growth Curves'!D19 | E11: ='Growth Curves'!E19 | F11: ='Growth Curves'!F19 | G11: ='Growth Curves'!G19 | H11: ='Growth Curves'!H19 | I11: ='Growth Curves'!I19 | ... Y11: ='Growth Curves'!Y19 | Z11: =SUM(B11:Y11)
A13: INCOME
A14: Potions
A15: Units shipped | B15: ='Growth Curves'!B4 | C15: ='Growth Curves'!C4 | D15: ='Growth Curves'!D4 | E15: ='Growth Curves'!E4 | F15: ='Growth Curves'!F4 | G15: ='Growth Curves'!G4 | H15: ='Growth Curves'!H4 | I15: ='Growth Curves'!I4 | ... Y15: ='Growth Curves'!Y4 | Z15: =SUM(B15:Y15)
A16: Price/unit | B16: =Assumptions!B22 | C16: =Assumptions!B22 | D16: =Assumptions!B22 | E16: =Assumptions!B22 | F16: =Assumptions!B22 | G16: =Assumptions!B22 | H16: =Assumptions!B22 | I16: =Assumptions!B22 | J16: =Assumptions!B22 | K16: =Assumptions!B22 | L16: =Assumptions!B22 | M16: =Assumptions!B22 | N16: =Assumptions!B22 | O16: =Assumptions!B22 | P16: =Assumptions!B22 | Q16: =Assumptions!B22 | R16: =Assumptions!B22 | S16: =Assumptions!B22 | T16: =Assumptions!B22 | U16: =Assumptions!B22 | V16: =Assumptions!B22 | W16: =Assumptions!B22 | X16: =Assumptions!B22 | Y16: =Assumptions!B22 | Z16: =SUM(B16:Y16)
A17: Revenue | B17: =B15*Assumptions!B22 | C17: =C15*Assumptions!B22 | D17: =D15*Assumptions!B22 | E17: =E15*Assumptions!B22 | F17: =F15*Assumptions!B22 | G17: =G15*Assumptions!B22 | H17: =H15*Assumptions!B22 | I17: =I15*Assumptions!B22 | J17: =J15*Assumptions!B22 | K17: =K15*Assumptions!B22 | L17: =L15*Assumptions!B22 | M17: =M15*Assumptions!B22 | N17: =N15*Assumptions!B22 | O17: =O15*Assumptions!B22 | P17: =P15*Assumptions!B22 | Q17: =Q15*Assumptions!B22 | R17: =R15*Assumptions!B22 | S17: =S15*Assumptions!B22 | T17: =T15*Assumptions!B22 | U17: =U15*Assumptions!B22 | V17: =V15*Assumptions!B22 | W17: =W15*Assumptions!B22 | X17: =X15*Assumptions!B22 | Y17: =Y15*Assumptions!B22 | Z17: =SUM(B17:Y17)
A18: LED Therapy
A19: Sessions | B19: ='Growth Curves'!B5 | C19: ='Growth Curves'!C5 | D19: ='Growth Curves'!D5 | E19: ='Growth Curves'!E5 | F19: ='Growth Curves'!F5 | G19: ='Growth Curves'!G5 | H19: ='Growth Curves'!H5 | I19: ='Growth Curves'!I5 | ... Y19: ='Growth Curves'!Y5 | Z19: =SUM(B19:Y19)
A20: Price/session | B20: =Assumptions!B24 | C20: =Assumptions!B24 | D20: =Assumptions!B24 | E20: =Assumptions!B24 | F20: =Assumptions!B24 | G20: =Assumptions!B24 | H20: =Assumptions!B24 | I20: =Assumptions!B24 | J20: =Assumptions!B24 | K20: =Assumptions!B24 | L20: =Assumptions!B24 | M20: =Assumptions!B24 | N20: =Assumptions!B24 | O20: =Assumptions!B24 | P20: =Assumptions!B24 | Q20: =Assumptions!B24 | R20: =Assumptions!B24 | S20: =Assumptions!B24 | T20: =Assumptions!B24 | U20: =Assumptions!B24 | V20: =Assumptions!B24 | W20: =Assumptions!B24 | X20: =Assumptions!B24 | Y20: =Assumptions!B24 | Z20: =SUM(B20:Y20)
A21: Revenue | B21: =B19*Assumptions!B24 | C21: =C19*Assumptions!B24 | D21: =D19*Assumptions!B24 | E21: =E19*Assumptions!B24 | F21: =F19*Assumptions!B24 | G21: =G19*Assumptions!B24 | H21: =H19*Assumptions!B24 | I21: =I19*Assumptions!B24 | J21: =J19*Assumptions!B24 | K21: =K19*Assumptions!B24 | L21: =L19*Assumptions!B24 | M21: =M19*Assumptions!B24 | N21: =N19*Assumptions!B24 | O21: =O19*Assumptions!B24 | P21: =P19*Assumptions!B24 | Q21: =Q19*Assumptions!B24 | R21: =R19*Assumptions!B24 | S21: =S19*Assumptions!B24 | T21: =T19*Assumptions!B24 | U21: =U19*Assumptions!B24 | V21: =V19*Assumptions!B24 | W21: =W19*Assumptions!B24 | X21: =X19*Assumptions!B24 | Y21: =Y19*Assumptions!B24 | Z21: =SUM(B21:Y21)
A22: Smoothie Bar
A23: Units sold | B23: ='Growth Curves'!B6 | C23: ='Growth Curves'!C6 | D23: ='Growth Curves'!D6 | E23: ='Growth Curves'!E6 | F23: ='Growth Curves'!F6 | G23: ='Growth Curves'!G6 | H23: ='Growth Curves'!H6 | I23: ='Growth Curves'!I6 | ... Y23: ='Growth Curves'!Y6 | Z23: =SUM(B23:Y23)
A24: Price/smoothie | B24: =Assumptions!B26 | C24: =Assumptions!B26 | D24: =Assumptions!B26 | E24: =Assumptions!B26 | F24: =Assumptions!B26 | G24: =Assumptions!B26 | H24: =Assumptions!B26 | I24: =Assumptions!B26 | J24: =Assumptions!B26 | K24: =Assumptions!B26 | L24: =Assumptions!B26 | M24: =Assumptions!B26 | N24: =Assumptions!B26 | O24: =Assumptions!B26 | P24: =Assumptions!B26 | Q24: =Assumptions!B26 | R24: =Assumptions!B26 | S24: =Assumptions!B26 | T24: =Assumptions!B26 | U24: =Assumptions!B26 | V24: =Assumptions!B26 | W24: =Assumptions!B26 | X24: =Assumptions!B26 | Y24: =Assumptions!B26 | Z24: =SUM(B24:Y24)
A25: Revenue | B25: =ROUND(B23*Assumptions!B26,0) | C25: =ROUND(C23*Assumptions!B26,0) | D25: =ROUND(D23*Assumptions!B26,0) | E25: =ROUND(E23*Assumptions!B26,0) | F25: =ROUND(F23*Assumptions!B26,0) | G25: =ROUND(G23*Assumptions!B26,0) | H25: =ROUND(H23*Assumptions!B26,0) | I25: =ROUND(I23*Assumptions!B26,0) | J25: =ROUND(J23*Assumptions!B26,0) | K25: =ROUND(K23*Assumptions!B26,0) | L25: =ROUND(L23*Assumptions!B26,0) | M25: =ROUND(M23*Assumptions!B26,0) | N25: =ROUND(N23*Assumptions!B26,0) | O25: =ROUND(O23*Assumptions!B26,0) | P25: =ROUND(P23*Assumptions!B26,0) | Q25: =ROUND(Q23*Assumptions!B26,0) | R25: =ROUND(R23*Assumptions!B26,0) | S25: =ROUND(S23*Assumptions!B26,0) | T25: =ROUND(T23*Assumptions!B26,0) | U25: =ROUND(U23*Assumptions!B26,0) | V25: =ROUND(V23*Assumptions!B26,0) | W25: =ROUND(W23*Assumptions!B26,0) | X25: =ROUND(X23*Assumptions!B26,0) | Y25: =ROUND(Y23*Assumptions!B26,0) | Z25: =SUM(B25:Y25)
A26: Community Events
A27: Event count | B27: ='Growth Curves'!B7 | C27: ='Growth Curves'!C7 | D27: ='Growth Curves'!D7 | E27: ='Growth Curves'!E7 | F27: ='Growth Curves'!F7 | G27: ='Growth Curves'!G7 | H27: ='Growth Curves'!H7 | I27: ='Growth Curves'!I7 | ... Y27: ='Growth Curves'!Y7 | Z27: =SUM(B27:Y27)
A28: Avg attendees/event | B28: ='Growth Curves'!B8 | C28: ='Growth Curves'!C8 | D28: ='Growth Curves'!D8 | E28: ='Growth Curves'!E8 | F28: ='Growth Curves'!F8 | G28: ='Growth Curves'!G8 | H28: ='Growth Curves'!H8 | I28: ='Growth Curves'!I8 | ... Y28: ='Growth Curves'!Y8 | Z28: =SUM(B28:Y28)
A29: Total attendees | B29: =B27*B28 | C29: =C27*C28 | D29: =D27*D28 | E29: =E27*E28 | F29: =F27*F28 | G29: =G27*G28 | H29: =H27*H28 | I29: =I27*I28 | ... Y29: =Y27*Y28 | Z29: =SUM(B29:Y29)
A30: Price/ticket | B30: =Assumptions!B28 | C30: =Assumptions!B28 | D30: =Assumptions!B28 | E30: =Assumptions!B28 | F30: =Assumptions!B28 | G30: =Assumptions!B28 | H30: =Assumptions!B28 | I30: =Assumptions!B28 | J30: =Assumptions!B28 | K30: =Assumptions!B28 | L30: =Assumptions!B28 | M30: =Assumptions!B28 | N30: =Assumptions!B28 | O30: =Assumptions!B28 | P30: =Assumptions!B28 | Q30: =Assumptions!B28 | R30: =Assumptions!B28 | S30: =Assumptions!B28 | T30: =Assumptions!B28 | U30: =Assumptions!B28 | V30: =Assumptions!B28 | W30: =Assumptions!B28 | X30: =Assumptions!B28 | Y30: =Assumptions!B28 | Z30: =SUM(B30:Y30)
A31: Revenue | B31: =B29*Assumptions!B28 | C31: =C29*Assumptions!B28 | D31: =D29*Assumptions!B28 | E31: =E29*Assumptions!B28 | F31: =F29*Assumptions!B28 | G31: =G29*Assumptions!B28 | H31: =H29*Assumptions!B28 | I31: =I29*Assumptions!B28 | J31: =J29*Assumptions!B28 | K31: =K29*Assumptions!B28 | L31: =L29*Assumptions!B28 | M31: =M29*Assumptions!B28 | N31: =N29*Assumptions!B28 | O31: =O29*Assumptions!B28 | P31: =P29*Assumptions!B28 | Q31: =Q29*Assumptions!B28 | R31: =R29*Assumptions!B28 | S31: =S29*Assumptions!B28 | T31: =T29*Assumptions!B28 | U31: =U29*Assumptions!B28 | V31: =V29*Assumptions!B28 | W31: =W29*Assumptions!B28 | X31: =X29*Assumptions!B28 | Y31: =Y29*Assumptions!B28 | Z31: =SUM(B31:Y31)
A32: Doctor SaaS (D1: EUR 99/mo)
A33: Clinics listed | B33: ='Growth Curves'!B9 | C33: ='Growth Curves'!C9 | D33: ='Growth Curves'!D9 | E33: ='Growth Curves'!E9 | F33: ='Growth Curves'!F9 | G33: ='Growth Curves'!G9 | H33: ='Growth Curves'!H9 | I33: ='Growth Curves'!I9 | ... Y33: ='Growth Curves'!Y9 | Z33: =SUM(B33:Y33)
A34: Fee/month | B34: =Assumptions!B31 | C34: =Assumptions!B31 | D34: =Assumptions!B31 | E34: =Assumptions!B31 | F34: =Assumptions!B31 | G34: =Assumptions!B31 | H34: =Assumptions!B31 | I34: =Assumptions!B31 | J34: =Assumptions!B31 | K34: =Assumptions!B31 | L34: =Assumptions!B31 | M34: =Assumptions!B31 | N34: =Assumptions!B31 | O34: =Assumptions!B31 | P34: =Assumptions!B31 | Q34: =Assumptions!B31 | R34: =Assumptions!B31 | S34: =Assumptions!B31 | T34: =Assumptions!B31 | U34: =Assumptions!B31 | V34: =Assumptions!B31 | W34: =Assumptions!B31 | X34: =Assumptions!B31 | Y34: =Assumptions!B31 | Z34: =SUM(B34:Y34)
A35: Revenue | B35: =B33*Assumptions!B31 | C35: =C33*Assumptions!B31 | D35: =D33*Assumptions!B31 | E35: =E33*Assumptions!B31 | F35: =F33*Assumptions!B31 | G35: =G33*Assumptions!B31 | H35: =H33*Assumptions!B31 | I35: =I33*Assumptions!B31 | J35: =J33*Assumptions!B31 | K35: =K33*Assumptions!B31 | L35: =L33*Assumptions!B31 | M35: =M33*Assumptions!B31 | N35: =N33*Assumptions!B31 | O35: =O33*Assumptions!B31 | P35: =P33*Assumptions!B31 | Q35: =Q33*Assumptions!B31 | R35: =R33*Assumptions!B31 | S35: =S33*Assumptions!B31 | T35: =T33*Assumptions!B31 | U35: =U33*Assumptions!B31 | V35: =V33*Assumptions!B31 | W35: =W33*Assumptions!B31 | X35: =X33*Assumptions!B31 | Y35: =Y33*Assumptions!B31 | Z35: =SUM(B35:Y35)
A36: Restaurant (Phase 2 — EUR 0) | B36: 0 | C36: 0 | D36: 0 | E36: 0 | F36: 0 | G36: 0 | H36: 0 | I36: 0 | J36: 0 | K36: 0 | L36: 0 | M36: 0 | N36: 0 | O36: 0 | P36: 0 | Q36: 0 | R36: 0 | S36: 0 | T36: 0 | U36: 0 | V36: 0 | W36: 0 | X36: 0 | Y36: 0 | Z36: =SUM(B36:Y36)
A37: Subscriptions
A38: Core (EUR 19/mo) | B38: ='Growth Curves'!B17*Assumptions!B5 | C38: ='Growth Curves'!C17*Assumptions!B5 | D38: ='Growth Curves'!D17*Assumptions!B5 | E38: ='Growth Curves'!E17*Assumptions!B5 | F38: ='Growth Curves'!F17*Assumptions!B5 | G38: ='Growth Curves'!G17*Assumptions!B5 | H38: ='Growth Curves'!H17*Assumptions!B5 | I38: ='Growth Curves'!I17*Assumptions!B5 | J38: ='Growth Curves'!J17*Assumptions!B5 | K38: ='Growth Curves'!K17*Assumptions!B5 | L38: ='Growth Curves'!L17*Assumptions!B5 | M38: ='Growth Curves'!M17*Assumptions!B5 | N38: ='Growth Curves'!N17*Assumptions!B5 | O38: ='Growth Curves'!O17*Assumptions!B5 | P38: ='Growth Curves'!P17*Assumptions!B5 | Q38: ='Growth Curves'!Q17*Assumptions!B5 | R38: ='Growth Curves'!R17*Assumptions!B5 | S38: ='Growth Curves'!S17*Assumptions!B5 | T38: ='Growth Curves'!T17*Assumptions!B5 | U38: ='Growth Curves'!U17*Assumptions!B5 | V38: ='Growth Curves'!V17*Assumptions!B5 | W38: ='Growth Curves'!W17*Assumptions!B5 | X38: ='Growth Curves'!X17*Assumptions!B5 | Y38: ='Growth Curves'!Y17*Assumptions!B5 | Z38: =SUM(B38:Y38)
A39: Pro (EUR 49/mo) | B39: ='Growth Curves'!B18*Assumptions!B6 | C39: ='Growth Curves'!C18*Assumptions!B6 | D39: ='Growth Curves'!D18*Assumptions!B6 | E39: ='Growth Curves'!E18*Assumptions!B6 | F39: ='Growth Curves'!F18*Assumptions!B6 | G39: ='Growth Curves'!G18*Assumptions!B6 | H39: ='Growth Curves'!H18*Assumptions!B6 | I39: ='Growth Curves'!I18*Assumptions!B6 | J39: ='Growth Curves'!J18*Assumptions!B6 | K39: ='Growth Curves'!K18*Assumptions!B6 | L39: ='Growth Curves'!L18*Assumptions!B6 | M39: ='Growth Curves'!M18*Assumptions!B6 | N39: ='Growth Curves'!N18*Assumptions!B6 | O39: ='Growth Curves'!O18*Assumptions!B6 | P39: ='Growth Curves'!P18*Assumptions!B6 | Q39: ='Growth Curves'!Q18*Assumptions!B6 | R39: ='Growth Curves'!R18*Assumptions!B6 | S39: ='Growth Curves'!S18*Assumptions!B6 | T39: ='Growth Curves'!T18*Assumptions!B6 | U39: ='Growth Curves'!U18*Assumptions!B6 | V39: ='Growth Curves'!V18*Assumptions!B6 | W39: ='Growth Curves'!W18*Assumptions!B6 | X39: ='Growth Curves'!X18*Assumptions!B6 | Y39: ='Growth Curves'!Y18*Assumptions!B6 | Z39: =SUM(B39:Y39)
A40: Premium (EUR 99/mo) | B40: ='Growth Curves'!B19*Assumptions!B7 | C40: ='Growth Curves'!C19*Assumptions!B7 | D40: ='Growth Curves'!D19*Assumptions!B7 | E40: ='Growth Curves'!E19*Assumptions!B7 | F40: ='Growth Curves'!F19*Assumptions!B7 | G40: ='Growth Curves'!G19*Assumptions!B7 | H40: ='Growth Curves'!H19*Assumptions!B7 | I40: ='Growth Curves'!I19*Assumptions!B7 | J40: ='Growth Curves'!J19*Assumptions!B7 | K40: ='Growth Curves'!K19*Assumptions!B7 | L40: ='Growth Curves'!L19*Assumptions!B7 | M40: ='Growth Curves'!M19*Assumptions!B7 | N40: ='Growth Curves'!N19*Assumptions!B7 | O40: ='Growth Curves'!O19*Assumptions!B7 | P40: ='Growth Curves'!P19*Assumptions!B7 | Q40: ='Growth Curves'!Q19*Assumptions!B7 | R40: ='Growth Curves'!R19*Assumptions!B7 | S40: ='Growth Curves'!S19*Assumptions!B7 | T40: ='Growth Curves'!T19*Assumptions!B7 | U40: ='Growth Curves'!U19*Assumptions!B7 | V40: ='Growth Curves'!V19*Assumptions!B7 | W40: ='Growth Curves'!W19*Assumptions!B7 | X40: ='Growth Curves'!X19*Assumptions!B7 | Y40: ='Growth Curves'!Y19*Assumptions!B7 | Z40: =SUM(B40:Y40)
A41: Subscription MRR | B41: =B38+B39+B40 | C41: =C38+C39+C40 | D41: =D38+D39+D40 | E41: =E38+E39+E40 | F41: =F38+F39+F40 | G41: =G38+G39+G40 | H41: =H38+H39+H40 | I41: =I38+I39+I40 | ... Y41: =Y38+Y39+Y40 | Z41: =SUM(B41:Y41)
A43: TOTAL INCOME | B43: =B17+B21+B25+B31+B35+B36+B41 | C43: =C17+C21+C25+C31+C35+C36+C41 | D43: =D17+D21+D25+D31+D35+D36+D41 | E43: =E17+E21+E25+E31+E35+E36+E41 | F43: =F17+F21+F25+F31+F35+F36+F41 | G43: =G17+G21+G25+G31+G35+G36+G41 | H43: =H17+H21+H25+H31+H35+H36+H41 | I43: =I17+I21+I25+I31+I35+I36+I41 | ... Y43: =Y17+Y21+Y25+Y31+Y35+Y36+Y41 | Z43: =SUM(B43:Y43)
A45: COST OF GOODS SOLD (COGS)
A46: Potions COGS
A47: Product cost (EUR 23.50/unit) | B47: =ROUND(B15*Assumptions!B23,0) | C47: =ROUND(C15*Assumptions!B23,0) | D47: =ROUND(D15*Assumptions!B23,0) | E47: =ROUND(E15*Assumptions!B23,0) | F47: =ROUND(F15*Assumptions!B23,0) | G47: =ROUND(G15*Assumptions!B23,0) | H47: =ROUND(H15*Assumptions!B23,0) | I47: =ROUND(I15*Assumptions!B23,0) | J47: =ROUND(J15*Assumptions!B23,0) | K47: =ROUND(K15*Assumptions!B23,0) | L47: =ROUND(L15*Assumptions!B23,0) | M47: =ROUND(M15*Assumptions!B23,0) | N47: =ROUND(N15*Assumptions!B23,0) | O47: =ROUND(O15*Assumptions!B23,0) | P47: =ROUND(P15*Assumptions!B23,0) | Q47: =ROUND(Q15*Assumptions!B23,0) | R47: =ROUND(R15*Assumptions!B23,0) | S47: =ROUND(S15*Assumptions!B23,0) | T47: =ROUND(T15*Assumptions!B23,0) | U47: =ROUND(U15*Assumptions!B23,0) | V47: =ROUND(V15*Assumptions!B23,0) | W47: =ROUND(W15*Assumptions!B23,0) | X47: =ROUND(X15*Assumptions!B23,0) | Y47: =ROUND(Y15*Assumptions!B23,0) | Z47: =SUM(B47:Y47)
A48: Waste/spoilage (5.5%) | B48: =ROUND(B17*Assumptions!B36,0) | C48: =ROUND(C17*Assumptions!B36,0) | D48: =ROUND(D17*Assumptions!B36,0) | E48: =ROUND(E17*Assumptions!B36,0) | F48: =ROUND(F17*Assumptions!B36,0) | G48: =ROUND(G17*Assumptions!B36,0) | H48: =ROUND(H17*Assumptions!B36,0) | I48: =ROUND(I17*Assumptions!B36,0) | J48: =ROUND(J17*Assumptions!B36,0) | K48: =ROUND(K17*Assumptions!B36,0) | L48: =ROUND(L17*Assumptions!B36,0) | M48: =ROUND(M17*Assumptions!B36,0) | N48: =ROUND(N17*Assumptions!B36,0) | O48: =ROUND(O17*Assumptions!B36,0) | P48: =ROUND(P17*Assumptions!B36,0) | Q48: =ROUND(Q17*Assumptions!B36,0) | R48: =ROUND(R17*Assumptions!B36,0) | S48: =ROUND(S17*Assumptions!B36,0) | T48: =ROUND(T17*Assumptions!B36,0) | U48: =ROUND(U17*Assumptions!B36,0) | V48: =ROUND(V17*Assumptions!B36,0) | W48: =ROUND(W17*Assumptions!B36,0) | X48: =ROUND(X17*Assumptions!B36,0) | Y48: =ROUND(Y17*Assumptions!B36,0) | Z48: =SUM(B48:Y48)
A49: 3PL fulfillment (EUR 2.50/unit) | B49: =IF(1>=4,ROUND(B15*Assumptions!B37,0),0) | C49: =IF(2>=4,ROUND(C15*Assumptions!B37,0),0) | D49: =IF(3>=4,ROUND(D15*Assumptions!B37,0),0) | E49: =IF(4>=4,ROUND(E15*Assumptions!B37,0),0) | F49: =IF(5>=4,ROUND(F15*Assumptions!B37,0),0) | G49: =IF(6>=4,ROUND(G15*Assumptions!B37,0),0) | H49: =IF(7>=4,ROUND(H15*Assumptions!B37,0),0) | I49: =IF(8>=4,ROUND(I15*Assumptions!B37,0),0) | J49: =IF(9>=4,ROUND(J15*Assumptions!B37,0),0) | K49: =IF(10>=4,ROUND(K15*Assumptions!B37,0),0) | L49: =IF(11>=4,ROUND(L15*Assumptions!B37,0),0) | M49: =IF(12>=4,ROUND(M15*Assumptions!B37,0),0) | N49: =IF(13>=4,ROUND(N15*Assumptions!B37,0),0) | O49: =IF(14>=4,ROUND(O15*Assumptions!B37,0),0) | P49: =IF(15>=4,ROUND(P15*Assumptions!B37,0),0) | Q49: =IF(16>=4,ROUND(Q15*Assumptions!B37,0),0) | R49: =IF(17>=4,ROUND(R15*Assumptions!B37,0),0) | S49: =IF(18>=4,ROUND(S15*Assumptions!B37,0),0) | T49: =IF(19>=4,ROUND(T15*Assumptions!B37,0),0) | U49: =IF(20>=4,ROUND(U15*Assumptions!B37,0),0) | V49: =IF(21>=4,ROUND(V15*Assumptions!B37,0),0) | W49: =IF(22>=4,ROUND(W15*Assumptions!B37,0),0) | X49: =IF(23>=4,ROUND(X15*Assumptions!B37,0),0) | Y49: =IF(24>=4,ROUND(Y15*Assumptions!B37,0),0) | Z49: =SUM(B49:Y49)
A50: LED Practitioner (EUR 25/session) | B50: =ROUND(B19*Assumptions!B25,0) | C50: =ROUND(C19*Assumptions!B25,0) | D50: =ROUND(D19*Assumptions!B25,0) | E50: =ROUND(E19*Assumptions!B25,0) | F50: =ROUND(F19*Assumptions!B25,0) | G50: =ROUND(G19*Assumptions!B25,0) | H50: =ROUND(H19*Assumptions!B25,0) | I50: =ROUND(I19*Assumptions!B25,0) | J50: =ROUND(J19*Assumptions!B25,0) | K50: =ROUND(K19*Assumptions!B25,0) | L50: =ROUND(L19*Assumptions!B25,0) | M50: =ROUND(M19*Assumptions!B25,0) | N50: =ROUND(N19*Assumptions!B25,0) | O50: =ROUND(O19*Assumptions!B25,0) | P50: =ROUND(P19*Assumptions!B25,0) | Q50: =ROUND(Q19*Assumptions!B25,0) | R50: =ROUND(R19*Assumptions!B25,0) | S50: =ROUND(S19*Assumptions!B25,0) | T50: =ROUND(T19*Assumptions!B25,0) | U50: =ROUND(U19*Assumptions!B25,0) | V50: =ROUND(V19*Assumptions!B25,0) | W50: =ROUND(W19*Assumptions!B25,0) | X50: =ROUND(X19*Assumptions!B25,0) | Y50: =ROUND(Y19*Assumptions!B25,0) | Z50: =SUM(B50:Y50)
A51: Smoothie Bar COGS
A52: Ingredients + packaging (35%) | B52: =ROUND(B25*Assumptions!B27,0) | C52: =ROUND(C25*Assumptions!B27,0) | D52: =ROUND(D25*Assumptions!B27,0) | E52: =ROUND(E25*Assumptions!B27,0) | F52: =ROUND(F25*Assumptions!B27,0) | G52: =ROUND(G25*Assumptions!B27,0) | H52: =ROUND(H25*Assumptions!B27,0) | I52: =ROUND(I25*Assumptions!B27,0) | J52: =ROUND(J25*Assumptions!B27,0) | K52: =ROUND(K25*Assumptions!B27,0) | L52: =ROUND(L25*Assumptions!B27,0) | M52: =ROUND(M25*Assumptions!B27,0) | N52: =ROUND(N25*Assumptions!B27,0) | O52: =ROUND(O25*Assumptions!B27,0) | P52: =ROUND(P25*Assumptions!B27,0) | Q52: =ROUND(Q25*Assumptions!B27,0) | R52: =ROUND(R25*Assumptions!B27,0) | S52: =ROUND(S25*Assumptions!B27,0) | T52: =ROUND(T25*Assumptions!B27,0) | U52: =ROUND(U25*Assumptions!B27,0) | V52: =ROUND(V25*Assumptions!B27,0) | W52: =ROUND(W25*Assumptions!B27,0) | X52: =ROUND(X25*Assumptions!B27,0) | Y52: =ROUND(Y25*Assumptions!B27,0) | Z52: =SUM(B52:Y52)
A53: Events & Ticketing | B53: =ROUND(B27*Assumptions!B29+B31*Assumptions!B30,0) | C53: =ROUND(C27*Assumptions!B29+C31*Assumptions!B30,0) | D53: =ROUND(D27*Assumptions!B29+D31*Assumptions!B30,0) | E53: =ROUND(E27*Assumptions!B29+E31*Assumptions!B30,0) | F53: =ROUND(F27*Assumptions!B29+F31*Assumptions!B30,0) | G53: =ROUND(G27*Assumptions!B29+G31*Assumptions!B30,0) | H53: =ROUND(H27*Assumptions!B29+H31*Assumptions!B30,0) | I53: =ROUND(I27*Assumptions!B29+I31*Assumptions!B30,0) | J53: =ROUND(J27*Assumptions!B29+J31*Assumptions!B30,0) | K53: =ROUND(K27*Assumptions!B29+K31*Assumptions!B30,0) | L53: =ROUND(L27*Assumptions!B29+L31*Assumptions!B30,0) | M53: =ROUND(M27*Assumptions!B29+M31*Assumptions!B30,0) | N53: =ROUND(N27*Assumptions!B29+N31*Assumptions!B30,0) | O53: =ROUND(O27*Assumptions!B29+O31*Assumptions!B30,0) | P53: =ROUND(P27*Assumptions!B29+P31*Assumptions!B30,0) | Q53: =ROUND(Q27*Assumptions!B29+Q31*Assumptions!B30,0) | R53: =ROUND(R27*Assumptions!B29+R31*Assumptions!B30,0) | S53: =ROUND(S27*Assumptions!B29+S31*Assumptions!B30,0) | T53: =ROUND(T27*Assumptions!B29+T31*Assumptions!B30,0) | U53: =ROUND(U27*Assumptions!B29+U31*Assumptions!B30,0) | V53: =ROUND(V27*Assumptions!B29+V31*Assumptions!B30,0) | W53: =ROUND(W27*Assumptions!B29+W31*Assumptions!B30,0) | X53: =ROUND(X27*Assumptions!B29+X31*Assumptions!B30,0) | Y53: =ROUND(Y27*Assumptions!B29+Y31*Assumptions!B30,0) | Z53: =SUM(B53:Y53)
A54: Doctor Verification (EUR 25/new) | B54: =ROUND('Growth Curves'!B11*Assumptions!B32,0) | C54: =ROUND('Growth Curves'!C11*Assumptions!B32,0) | D54: =ROUND('Growth Curves'!D11*Assumptions!B32,0) | E54: =ROUND('Growth Curves'!E11*Assumptions!B32,0) | F54: =ROUND('Growth Curves'!F11*Assumptions!B32,0) | G54: =ROUND('Growth Curves'!G11*Assumptions!B32,0) | H54: =ROUND('Growth Curves'!H11*Assumptions!B32,0) | I54: =ROUND('Growth Curves'!I11*Assumptions!B32,0) | J54: =ROUND('Growth Curves'!J11*Assumptions!B32,0) | K54: =ROUND('Growth Curves'!K11*Assumptions!B32,0) | L54: =ROUND('Growth Curves'!L11*Assumptions!B32,0) | M54: =ROUND('Growth Curves'!M11*Assumptions!B32,0) | N54: =ROUND('Growth Curves'!N11*Assumptions!B32,0) | O54: =ROUND('Growth Curves'!O11*Assumptions!B32,0) | P54: =ROUND('Growth Curves'!P11*Assumptions!B32,0) | Q54: =ROUND('Growth Curves'!Q11*Assumptions!B32,0) | R54: =ROUND('Growth Curves'!R11*Assumptions!B32,0) | S54: =ROUND('Growth Curves'!S11*Assumptions!B32,0) | T54: =ROUND('Growth Curves'!T11*Assumptions!B32,0) | U54: =ROUND('Growth Curves'!U11*Assumptions!B32,0) | V54: =ROUND('Growth Curves'!V11*Assumptions!B32,0) | W54: =ROUND('Growth Curves'!W11*Assumptions!B32,0) | X54: =ROUND('Growth Curves'!X11*Assumptions!B32,0) | Y54: =ROUND('Growth Curves'!Y11*Assumptions!B32,0) | Z54: =SUM(B54:Y54)
A55: AI API — User-Facing (EUR 0.35/sub) | B55: =ROUND('Growth Curves'!B16*Assumptions!B39,0) | C55: =ROUND('Growth Curves'!C16*Assumptions!B39,0) | D55: =ROUND('Growth Curves'!D16*Assumptions!B39,0) | E55: =ROUND('Growth Curves'!E16*Assumptions!B39,0) | F55: =ROUND('Growth Curves'!F16*Assumptions!B39,0) | G55: =ROUND('Growth Curves'!G16*Assumptions!B39,0) | H55: =ROUND('Growth Curves'!H16*Assumptions!B39,0) | I55: =ROUND('Growth Curves'!I16*Assumptions!B39,0) | J55: =ROUND('Growth Curves'!J16*Assumptions!B39,0) | K55: =ROUND('Growth Curves'!K16*Assumptions!B39,0) | L55: =ROUND('Growth Curves'!L16*Assumptions!B39,0) | M55: =ROUND('Growth Curves'!M16*Assumptions!B39,0) | N55: =ROUND('Growth Curves'!N16*Assumptions!B39,0) | O55: =ROUND('Growth Curves'!O16*Assumptions!B39,0) | P55: =ROUND('Growth Curves'!P16*Assumptions!B39,0) | Q55: =ROUND('Growth Curves'!Q16*Assumptions!B39,0) | R55: =ROUND('Growth Curves'!R16*Assumptions!B39,0) | S55: =ROUND('Growth Curves'!S16*Assumptions!B39,0) | T55: =ROUND('Growth Curves'!T16*Assumptions!B39,0) | U55: =ROUND('Growth Curves'!U16*Assumptions!B39,0) | V55: =ROUND('Growth Curves'!V16*Assumptions!B39,0) | W55: =ROUND('Growth Curves'!W16*Assumptions!B39,0) | X55: =ROUND('Growth Curves'!X16*Assumptions!B39,0) | Y55: =ROUND('Growth Curves'!Y16*Assumptions!B39,0) | Z55: =SUM(B55:Y55)
A56: Refund/Returns Reserve (1.5%) | B56: =ROUND((B17+B25+B31)*Assumptions!B40,0) | C56: =ROUND((C17+C25+C31)*Assumptions!B40,0) | D56: =ROUND((D17+D25+D31)*Assumptions!B40,0) | E56: =ROUND((E17+E25+E31)*Assumptions!B40,0) | F56: =ROUND((F17+F25+F31)*Assumptions!B40,0) | G56: =ROUND((G17+G25+G31)*Assumptions!B40,0) | H56: =ROUND((H17+H25+H31)*Assumptions!B40,0) | I56: =ROUND((I17+I25+I31)*Assumptions!B40,0) | J56: =ROUND((J17+J25+J31)*Assumptions!B40,0) | K56: =ROUND((K17+K25+K31)*Assumptions!B40,0) | L56: =ROUND((L17+L25+L31)*Assumptions!B40,0) | M56: =ROUND((M17+M25+M31)*Assumptions!B40,0) | N56: =ROUND((N17+N25+N31)*Assumptions!B40,0) | O56: =ROUND((O17+O25+O31)*Assumptions!B40,0) | P56: =ROUND((P17+P25+P31)*Assumptions!B40,0) | Q56: =ROUND((Q17+Q25+Q31)*Assumptions!B40,0) | R56: =ROUND((R17+R25+R31)*Assumptions!B40,0) | S56: =ROUND((S17+S25+S31)*Assumptions!B40,0) | T56: =ROUND((T17+T25+T31)*Assumptions!B40,0) | U56: =ROUND((U17+U25+U31)*Assumptions!B40,0) | V56: =ROUND((V17+V25+V31)*Assumptions!B40,0) | W56: =ROUND((W17+W25+W31)*Assumptions!B40,0) | X56: =ROUND((X17+X25+X31)*Assumptions!B40,0) | Y56: =ROUND((Y17+Y25+Y31)*Assumptions!B40,0) | Z56: =SUM(B56:Y56)
A57: Stripe Processing (2.9%) | B57: =ROUND(B43*Assumptions!B38,0) | C57: =ROUND(C43*Assumptions!B38,0) | D57: =ROUND(D43*Assumptions!B38,0) | E57: =ROUND(E43*Assumptions!B38,0) | F57: =ROUND(F43*Assumptions!B38,0) | G57: =ROUND(G43*Assumptions!B38,0) | H57: =ROUND(H43*Assumptions!B38,0) | I57: =ROUND(I43*Assumptions!B38,0) | J57: =ROUND(J43*Assumptions!B38,0) | K57: =ROUND(K43*Assumptions!B38,0) | L57: =ROUND(L43*Assumptions!B38,0) | M57: =ROUND(M43*Assumptions!B38,0) | N57: =ROUND(N43*Assumptions!B38,0) | O57: =ROUND(O43*Assumptions!B38,0) | P57: =ROUND(P43*Assumptions!B38,0) | Q57: =ROUND(Q43*Assumptions!B38,0) | R57: =ROUND(R43*Assumptions!B38,0) | S57: =ROUND(S43*Assumptions!B38,0) | T57: =ROUND(T43*Assumptions!B38,0) | U57: =ROUND(U43*Assumptions!B38,0) | V57: =ROUND(V43*Assumptions!B38,0) | W57: =ROUND(W43*Assumptions!B38,0) | X57: =ROUND(X43*Assumptions!B38,0) | Y57: =ROUND(Y43*Assumptions!B38,0) | Z57: =SUM(B57:Y57)
A59: TOTAL COGS | B59: =B47+B48+B49+B50+B52+B53+B54+B55+B56+B57 | C59: =C47+C48+C49+C50+C52+C53+C54+C55+C56+C57 | D59: =D47+D48+D49+D50+D52+D53+D54+D55+D56+D57 | E59: =E47+E48+E49+E50+E52+E53+E54+E55+E56+E57 | F59: =F47+F48+F49+F50+F52+F53+F54+F55+F56+F57 | G59: =G47+G48+G49+G50+G52+G53+G54+G55+G56+G57 | H59: =H47+H48+H49+H50+H52+H53+H54+H55+H56+H57 | I59: =I47+I48+I49+I50+I52+I53+I54+I55+I56+I57 | ... Y59: =Y47+Y48+Y49+Y50+Y52+Y53+Y54+Y55+Y56+Y57 | Z59: =SUM(B59:Y59)
A61: GROSS PROFIT | B61: =B43-B59 | C61: =C43-C59 | D61: =D43-D59 | E61: =E43-E59 | F61: =F43-F59 | G61: =G43-G59 | H61: =H43-H59 | I61: =I43-I59 | ... Y61: =Y43-Y59 | Z61: =SUM(B61:Y61)
A62: Gross Margin % | B62: =IF(B43>0,B61/B43,0) | C62: =IF(C43>0,C61/C43,0) | D62: =IF(D43>0,D61/D43,0) | E62: =IF(E43>0,E61/E43,0) | F62: =IF(F43>0,F61/F43,0) | G62: =IF(G43>0,G61/G43,0) | H62: =IF(H43>0,H61/H43,0) | I62: =IF(I43>0,I61/I43,0) | ... Z62: =IF(Z43>0,Z61/Z43,0)
A64: OPERATING EXPENSES
A65: Payroll
A66: Timu (CEO) | B66: =ROUND(Assumptions!B43*Assumptions!B44,0) | C66: =ROUND(Assumptions!B43*Assumptions!B44,0) | D66: =ROUND(Assumptions!B43*Assumptions!B44,0) | E66: =ROUND(Assumptions!B43*Assumptions!B44,0) | F66: =ROUND(Assumptions!B43*Assumptions!B44,0) | G66: =ROUND(Assumptions!B43*Assumptions!B44,0) | H66: =ROUND(Assumptions!B43*Assumptions!B44,0) | I66: =ROUND(Assumptions!B43*Assumptions!B44,0) | J66: =ROUND(Assumptions!B43*Assumptions!B44,0) | K66: =ROUND(Assumptions!B43*Assumptions!B44,0) | L66: =ROUND(Assumptions!B43*Assumptions!B44,0) | M66: =ROUND(Assumptions!B43*Assumptions!B44,0) | N66: =ROUND(Assumptions!B43*Assumptions!B44,0) | O66: =ROUND(Assumptions!B43*Assumptions!B44,0) | P66: =ROUND(Assumptions!B43*Assumptions!B44,0) | Q66: =ROUND(Assumptions!B43*Assumptions!B44,0) | R66: =ROUND(Assumptions!B43*Assumptions!B44,0) | S66: =ROUND(Assumptions!B43*Assumptions!B44,0) | T66: =ROUND(Assumptions!B43*Assumptions!B44,0) | U66: =ROUND(Assumptions!B43*Assumptions!B44,0) | V66: =ROUND(Assumptions!B43*Assumptions!B44,0) | W66: =ROUND(Assumptions!B43*Assumptions!B44,0) | X66: =ROUND(Assumptions!B43*Assumptions!B44,0) | Y66: =ROUND(Assumptions!B43*Assumptions!B44,0) | Z66: =SUM(B66:Y66)
A67: Daria (COO) | B67: =ROUND(Assumptions!B43*Assumptions!B44,0) | C67: =ROUND(Assumptions!B43*Assumptions!B44,0) | D67: =ROUND(Assumptions!B43*Assumptions!B44,0) | E67: =ROUND(Assumptions!B43*Assumptions!B44,0) | F67: =ROUND(Assumptions!B43*Assumptions!B44,0) | G67: =ROUND(Assumptions!B43*Assumptions!B44,0) | H67: =ROUND(Assumptions!B43*Assumptions!B44,0) | I67: =ROUND(Assumptions!B43*Assumptions!B44,0) | J67: =ROUND(Assumptions!B43*Assumptions!B44,0) | K67: =ROUND(Assumptions!B43*Assumptions!B44,0) | L67: =ROUND(Assumptions!B43*Assumptions!B44,0) | M67: =ROUND(Assumptions!B43*Assumptions!B44,0) | N67: =ROUND(Assumptions!B43*Assumptions!B44,0) | O67: =ROUND(Assumptions!B43*Assumptions!B44,0) | P67: =ROUND(Assumptions!B43*Assumptions!B44,0) | Q67: =ROUND(Assumptions!B43*Assumptions!B44,0) | R67: =ROUND(Assumptions!B43*Assumptions!B44,0) | S67: =ROUND(Assumptions!B43*Assumptions!B44,0) | T67: =ROUND(Assumptions!B43*Assumptions!B44,0) | U67: =ROUND(Assumptions!B43*Assumptions!B44,0) | V67: =ROUND(Assumptions!B43*Assumptions!B44,0) | W67: =ROUND(Assumptions!B43*Assumptions!B44,0) | X67: =ROUND(Assumptions!B43*Assumptions!B44,0) | Y67: =ROUND(Assumptions!B43*Assumptions!B44,0) | Z67: =SUM(B67:Y67)
A68: Space Staff (M4+) | B68: =IF(1>=4,ROUND(Assumptions!B45*Assumptions!B44,0),0) | C68: =IF(2>=4,ROUND(Assumptions!B45*Assumptions!B44,0),0) | D68: =IF(3>=4,ROUND(Assumptions!B45*Assumptions!B44,0),0) | E68: =IF(4>=4,ROUND(Assumptions!B45*Assumptions!B44,0),0) | F68: =IF(5>=4,ROUND(Assumptions!B45*Assumptions!B44,0),0) | G68: =IF(6>=4,ROUND(Assumptions!B45*Assumptions!B44,0),0) | H68: =IF(7>=4,ROUND(Assumptions!B45*Assumptions!B44,0),0) | I68: =IF(8>=4,ROUND(Assumptions!B45*Assumptions!B44,0),0) | J68: =IF(9>=4,ROUND(Assumptions!B45*Assumptions!B44,0),0) | K68: =IF(10>=4,ROUND(Assumptions!B45*Assumptions!B44,0),0) | L68: =IF(11>=4,ROUND(Assumptions!B45*Assumptions!B44,0),0) | M68: =IF(12>=4,ROUND(Assumptions!B45*Assumptions!B44,0),0) | N68: =IF(13>=4,ROUND(Assumptions!B45*Assumptions!B44,0),0) | O68: =IF(14>=4,ROUND(Assumptions!B45*Assumptions!B44,0),0) | P68: =IF(15>=4,ROUND(Assumptions!B45*Assumptions!B44,0),0) | Q68: =IF(16>=4,ROUND(Assumptions!B45*Assumptions!B44,0),0) | R68: =IF(17>=4,ROUND(Assumptions!B45*Assumptions!B44,0),0) | S68: =IF(18>=4,ROUND(Assumptions!B45*Assumptions!B44,0),0) | T68: =IF(19>=4,ROUND(Assumptions!B45*Assumptions!B44,0),0) | U68: =IF(20>=4,ROUND(Assumptions!B45*Assumptions!B44,0),0) | V68: =IF(21>=4,ROUND(Assumptions!B45*Assumptions!B44,0),0) | W68: =IF(22>=4,ROUND(Assumptions!B45*Assumptions!B44,0),0) | X68: =IF(23>=4,ROUND(Assumptions!B45*Assumptions!B44,0),0) | Y68: =IF(24>=4,ROUND(Assumptions!B45*Assumptions!B44,0),0) | Z68: =SUM(B68:Y68)
A69: Partner Mgr (M6+) | B69: =IF(1>=6,ROUND(Assumptions!B46*Assumptions!B44,0),0) | C69: =IF(2>=6,ROUND(Assumptions!B46*Assumptions!B44,0),0) | D69: =IF(3>=6,ROUND(Assumptions!B46*Assumptions!B44,0),0) | E69: =IF(4>=6,ROUND(Assumptions!B46*Assumptions!B44,0),0) | F69: =IF(5>=6,ROUND(Assumptions!B46*Assumptions!B44,0),0) | G69: =IF(6>=6,ROUND(Assumptions!B46*Assumptions!B44,0),0) | H69: =IF(7>=6,ROUND(Assumptions!B46*Assumptions!B44,0),0) | I69: =IF(8>=6,ROUND(Assumptions!B46*Assumptions!B44,0),0) | J69: =IF(9>=6,ROUND(Assumptions!B46*Assumptions!B44,0),0) | K69: =IF(10>=6,ROUND(Assumptions!B46*Assumptions!B44,0),0) | L69: =IF(11>=6,ROUND(Assumptions!B46*Assumptions!B44,0),0) | M69: =IF(12>=6,ROUND(Assumptions!B46*Assumptions!B44,0),0) | N69: =IF(13>=6,ROUND(Assumptions!B46*Assumptions!B44,0),0) | O69: =IF(14>=6,ROUND(Assumptions!B46*Assumptions!B44,0),0) | P69: =IF(15>=6,ROUND(Assumptions!B46*Assumptions!B44,0),0) | Q69: =IF(16>=6,ROUND(Assumptions!B46*Assumptions!B44,0),0) | R69: =IF(17>=6,ROUND(Assumptions!B46*Assumptions!B44,0),0) | S69: =IF(18>=6,ROUND(Assumptions!B46*Assumptions!B44,0),0) | T69: =IF(19>=6,ROUND(Assumptions!B46*Assumptions!B44,0),0) | U69: =IF(20>=6,ROUND(Assumptions!B46*Assumptions!B44,0),0) | V69: =IF(21>=6,ROUND(Assumptions!B46*Assumptions!B44,0),0) | W69: =IF(22>=6,ROUND(Assumptions!B46*Assumptions!B44,0),0) | X69: =IF(23>=6,ROUND(Assumptions!B46*Assumptions!B44,0),0) | Y69: =IF(24>=6,ROUND(Assumptions!B46*Assumptions!B44,0),0) | Z69: =SUM(B69:Y69)
A70: Growth Marketer (M12+) | B70: =IF(1>=12,ROUND(Assumptions!B47*Assumptions!B44,0),0) | C70: =IF(2>=12,ROUND(Assumptions!B47*Assumptions!B44,0),0) | D70: =IF(3>=12,ROUND(Assumptions!B47*Assumptions!B44,0),0) | E70: =IF(4>=12,ROUND(Assumptions!B47*Assumptions!B44,0),0) | F70: =IF(5>=12,ROUND(Assumptions!B47*Assumptions!B44,0),0) | G70: =IF(6>=12,ROUND(Assumptions!B47*Assumptions!B44,0),0) | H70: =IF(7>=12,ROUND(Assumptions!B47*Assumptions!B44,0),0) | I70: =IF(8>=12,ROUND(Assumptions!B47*Assumptions!B44,0),0) | J70: =IF(9>=12,ROUND(Assumptions!B47*Assumptions!B44,0),0) | K70: =IF(10>=12,ROUND(Assumptions!B47*Assumptions!B44,0),0) | L70: =IF(11>=12,ROUND(Assumptions!B47*Assumptions!B44,0),0) | M70: =IF(12>=12,ROUND(Assumptions!B47*Assumptions!B44,0),0) | N70: =IF(13>=12,ROUND(Assumptions!B47*Assumptions!B44,0),0) | O70: =IF(14>=12,ROUND(Assumptions!B47*Assumptions!B44,0),0) | P70: =IF(15>=12,ROUND(Assumptions!B47*Assumptions!B44,0),0) | Q70: =IF(16>=12,ROUND(Assumptions!B47*Assumptions!B44,0),0) | R70: =IF(17>=12,ROUND(Assumptions!B47*Assumptions!B44,0),0) | S70: =IF(18>=12,ROUND(Assumptions!B47*Assumptions!B44,0),0) | T70: =IF(19>=12,ROUND(Assumptions!B47*Assumptions!B44,0),0) | U70: =IF(20>=12,ROUND(Assumptions!B47*Assumptions!B44,0),0) | V70: =IF(21>=12,ROUND(Assumptions!B47*Assumptions!B44,0),0) | W70: =IF(22>=12,ROUND(Assumptions!B47*Assumptions!B44,0),0) | X70: =IF(23>=12,ROUND(Assumptions!B47*Assumptions!B44,0),0) | Y70: =IF(24>=12,ROUND(Assumptions!B47*Assumptions!B44,0),0) | Z70: =SUM(B70:Y70)
A71: Tech/Ops Lead (M18+) | B71: =IF(1>=18,ROUND(Assumptions!B48*Assumptions!B44,0),0) | C71: =IF(2>=18,ROUND(Assumptions!B48*Assumptions!B44,0),0) | D71: =IF(3>=18,ROUND(Assumptions!B48*Assumptions!B44,0),0) | E71: =IF(4>=18,ROUND(Assumptions!B48*Assumptions!B44,0),0) | F71: =IF(5>=18,ROUND(Assumptions!B48*Assumptions!B44,0),0) | G71: =IF(6>=18,ROUND(Assumptions!B48*Assumptions!B44,0),0) | H71: =IF(7>=18,ROUND(Assumptions!B48*Assumptions!B44,0),0) | I71: =IF(8>=18,ROUND(Assumptions!B48*Assumptions!B44,0),0) | J71: =IF(9>=18,ROUND(Assumptions!B48*Assumptions!B44,0),0) | K71: =IF(10>=18,ROUND(Assumptions!B48*Assumptions!B44,0),0) | L71: =IF(11>=18,ROUND(Assumptions!B48*Assumptions!B44,0),0) | M71: =IF(12>=18,ROUND(Assumptions!B48*Assumptions!B44,0),0) | N71: =IF(13>=18,ROUND(Assumptions!B48*Assumptions!B44,0),0) | O71: =IF(14>=18,ROUND(Assumptions!B48*Assumptions!B44,0),0) | P71: =IF(15>=18,ROUND(Assumptions!B48*Assumptions!B44,0),0) | Q71: =IF(16>=18,ROUND(Assumptions!B48*Assumptions!B44,0),0) | R71: =IF(17>=18,ROUND(Assumptions!B48*Assumptions!B44,0),0) | S71: =IF(18>=18,ROUND(Assumptions!B48*Assumptions!B44,0),0) | T71: =IF(19>=18,ROUND(Assumptions!B48*Assumptions!B44,0),0) | U71: =IF(20>=18,ROUND(Assumptions!B48*Assumptions!B44,0),0) | V71: =IF(21>=18,ROUND(Assumptions!B48*Assumptions!B44,0),0) | W71: =IF(22>=18,ROUND(Assumptions!B48*Assumptions!B44,0),0) | X71: =IF(23>=18,ROUND(Assumptions!B48*Assumptions!B44,0),0) | Y71: =IF(24>=18,ROUND(Assumptions!B48*Assumptions!B44,0),0) | Z71: =SUM(B71:Y71)
A72: BG Insurance (1.5% payroll) | B72: =ROUND((B66+B67+B68+B69+B70+B71)*Assumptions!B49,0) | C72: =ROUND((C66+C67+C68+C69+C70+C71)*Assumptions!B49,0) | D72: =ROUND((D66+D67+D68+D69+D70+D71)*Assumptions!B49,0) | E72: =ROUND((E66+E67+E68+E69+E70+E71)*Assumptions!B49,0) | F72: =ROUND((F66+F67+F68+F69+F70+F71)*Assumptions!B49,0) | G72: =ROUND((G66+G67+G68+G69+G70+G71)*Assumptions!B49,0) | H72: =ROUND((H66+H67+H68+H69+H70+H71)*Assumptions!B49,0) | I72: =ROUND((I66+I67+I68+I69+I70+I71)*Assumptions!B49,0) | J72: =ROUND((J66+J67+J68+J69+J70+J71)*Assumptions!B49,0) | K72: =ROUND((K66+K67+K68+K69+K70+K71)*Assumptions!B49,0) | L72: =ROUND((L66+L67+L68+L69+L70+L71)*Assumptions!B49,0) | M72: =ROUND((M66+M67+M68+M69+M70+M71)*Assumptions!B49,0) | N72: =ROUND((N66+N67+N68+N69+N70+N71)*Assumptions!B49,0) | O72: =ROUND((O66+O67+O68+O69+O70+O71)*Assumptions!B49,0) | P72: =ROUND((P66+P67+P68+P69+P70+P71)*Assumptions!B49,0) | Q72: =ROUND((Q66+Q67+Q68+Q69+Q70+Q71)*Assumptions!B49,0) | R72: =ROUND((R66+R67+R68+R69+R70+R71)*Assumptions!B49,0) | S72: =ROUND((S66+S67+S68+S69+S70+S71)*Assumptions!B49,0) | T72: =ROUND((T66+T67+T68+T69+T70+T71)*Assumptions!B49,0) | U72: =ROUND((U66+U67+U68+U69+U70+U71)*Assumptions!B49,0) | V72: =ROUND((V66+V67+V68+V69+V70+V71)*Assumptions!B49,0) | W72: =ROUND((W66+W67+W68+W69+W70+W71)*Assumptions!B49,0) | X72: =ROUND((X66+X67+X68+X69+X70+X71)*Assumptions!B49,0) | Y72: =ROUND((Y66+Y67+Y68+Y69+Y70+Y71)*Assumptions!B49,0) | Z72: =SUM(B72:Y72)
A73: Payroll Total | B73: =B66+B67+B68+B69+B70+B71+B72 | C73: =C66+C67+C68+C69+C70+C71+C72 | D73: =D66+D67+D68+D69+D70+D71+D72 | E73: =E66+E67+E68+E69+E70+E71+E72 | F73: =F66+F67+F68+F69+F70+F71+F72 | G73: =G66+G67+G68+G69+G70+G71+G72 | H73: =H66+H67+H68+H69+H70+H71+H72 | I73: =I66+I67+I68+I69+I70+I71+I72 | ... Y73: =Y66+Y67+Y68+Y69+Y70+Y71+Y72 | Z73: =SUM(B73:Y73)
A74: R&D
A75: App Maintenance | B75: =Assumptions!B52 | C75: =Assumptions!B52 | D75: =Assumptions!B52 | E75: =Assumptions!B52 | F75: =Assumptions!B52 | G75: =Assumptions!B52 | H75: =Assumptions!B52 | I75: =Assumptions!B52 | J75: =Assumptions!B52 | K75: =Assumptions!B52 | L75: =Assumptions!B52 | M75: =Assumptions!B52 | N75: =Assumptions!B52 | O75: =Assumptions!B52 | P75: =Assumptions!B52 | Q75: =Assumptions!B52 | R75: =Assumptions!B52 | S75: =Assumptions!B52 | T75: =Assumptions!B52 | U75: =Assumptions!B52 | V75: =Assumptions!B52 | W75: =Assumptions!B52 | X75: =Assumptions!B52 | Y75: =Assumptions!B52 | Z75: =SUM(B75:Y75)
A76: UX/UI Design | B76: =Assumptions!B53 | C76: =Assumptions!B53 | D76: =Assumptions!B53 | E76: =Assumptions!B53 | F76: =Assumptions!B53 | G76: =Assumptions!B53 | H76: =Assumptions!B53 | I76: =Assumptions!B53 | J76: =Assumptions!B53 | K76: =Assumptions!B53 | L76: =Assumptions!B53 | M76: =Assumptions!B53 | N76: =Assumptions!B53 | O76: =Assumptions!B53 | P76: =Assumptions!B53 | Q76: =Assumptions!B53 | R76: =Assumptions!B53 | S76: =Assumptions!B53 | T76: =Assumptions!B53 | U76: =Assumptions!B53 | V76: =Assumptions!B53 | W76: =Assumptions!B53 | X76: =Assumptions!B53 | Y76: =Assumptions!B53 | Z76: =SUM(B76:Y76)
A77: R&D Total | B77: =B75+B76 | C77: =C75+C76 | D77: =D75+D76 | E77: =E75+E76 | F77: =F75+F76 | G77: =G75+G76 | H77: =H75+H76 | I77: =I75+I76 | ... Y77: =Y75+Y76 | Z77: =SUM(B77:Y77)
A78: Sales & Marketing
A79: Paid Ads | B79: ='Growth Curves'!B10 | C79: ='Growth Curves'!C10 | D79: ='Growth Curves'!D10 | E79: ='Growth Curves'!E10 | F79: ='Growth Curves'!F10 | G79: ='Growth Curves'!G10 | H79: ='Growth Curves'!H10 | I79: ='Growth Curves'!I10 | ... Y79: ='Growth Curves'!Y10 | Z79: =SUM(B79:Y79)
A80: Content Creation | B80: =Assumptions!B66 | C80: =Assumptions!B66 | D80: =Assumptions!B66 | E80: =Assumptions!B66 | F80: =Assumptions!B66 | G80: =Assumptions!B66 | H80: =Assumptions!B66 | I80: =Assumptions!B66 | J80: =Assumptions!B66 | K80: =Assumptions!B66 | L80: =Assumptions!B66 | M80: =Assumptions!B66 | N80: =Assumptions!B66 | O80: =Assumptions!B66 | P80: =Assumptions!B66 | Q80: =Assumptions!B66 | R80: =Assumptions!B66 | S80: =Assumptions!B66 | T80: =Assumptions!B66 | U80: =Assumptions!B66 | V80: =Assumptions!B66 | W80: =Assumptions!B66 | X80: =Assumptions!B66 | Y80: =Assumptions!B66 | Z80: =SUM(B80:Y80)
A81: Influencer Seeding (M7+) | B81: =IF(1>=7,Assumptions!B67,0) | C81: =IF(2>=7,Assumptions!B67,0) | D81: =IF(3>=7,Assumptions!B67,0) | E81: =IF(4>=7,Assumptions!B67,0) | F81: =IF(5>=7,Assumptions!B67,0) | G81: =IF(6>=7,Assumptions!B67,0) | H81: =IF(7>=7,Assumptions!B67,0) | I81: =IF(8>=7,Assumptions!B67,0) | J81: =IF(9>=7,Assumptions!B67,0) | K81: =IF(10>=7,Assumptions!B67,0) | L81: =IF(11>=7,Assumptions!B67,0) | M81: =IF(12>=7,Assumptions!B67,0) | N81: =IF(13>=7,Assumptions!B67,0) | O81: =IF(14>=7,Assumptions!B67,0) | P81: =IF(15>=7,Assumptions!B67,0) | Q81: =IF(16>=7,Assumptions!B67,0) | R81: =IF(17>=7,Assumptions!B67,0) | S81: =IF(18>=7,Assumptions!B67,0) | T81: =IF(19>=7,Assumptions!B67,0) | U81: =IF(20>=7,Assumptions!B67,0) | V81: =IF(21>=7,Assumptions!B67,0) | W81: =IF(22>=7,Assumptions!B67,0) | X81: =IF(23>=7,Assumptions!B67,0) | Y81: =IF(24>=7,Assumptions!B67,0) | Z81: =SUM(B81:Y81)
A82: S&M Total | B82: =B79+B80+B81 | C82: =C79+C80+C81 | D82: =D79+D80+D81 | E82: =E79+E80+E81 | F82: =F79+F80+F81 | G82: =G79+G80+G81 | H82: =H79+H80+H81 | I82: =I79+I80+I81 | ... Y82: =Y79+Y80+Y81 | Z82: =SUM(B82:Y82)
A83: General & Admin
A84: Rent (co-work M1-3 / space M4+) | B84: =IF(1<=3,Assumptions!B58,Assumptions!B59) | C84: =IF(2<=3,Assumptions!B58,Assumptions!B59) | D84: =IF(3<=3,Assumptions!B58,Assumptions!B59) | E84: =IF(4<=3,Assumptions!B58,Assumptions!B59) | F84: =IF(5<=3,Assumptions!B58,Assumptions!B59) | G84: =IF(6<=3,Assumptions!B58,Assumptions!B59) | H84: =IF(7<=3,Assumptions!B58,Assumptions!B59) | I84: =IF(8<=3,Assumptions!B58,Assumptions!B59) | J84: =IF(9<=3,Assumptions!B58,Assumptions!B59) | K84: =IF(10<=3,Assumptions!B58,Assumptions!B59) | L84: =IF(11<=3,Assumptions!B58,Assumptions!B59) | M84: =IF(12<=3,Assumptions!B58,Assumptions!B59) | N84: =IF(13<=3,Assumptions!B58,Assumptions!B59) | O84: =IF(14<=3,Assumptions!B58,Assumptions!B59) | P84: =IF(15<=3,Assumptions!B58,Assumptions!B59) | Q84: =IF(16<=3,Assumptions!B58,Assumptions!B59) | R84: =IF(17<=3,Assumptions!B58,Assumptions!B59) | S84: =IF(18<=3,Assumptions!B58,Assumptions!B59) | T84: =IF(19<=3,Assumptions!B58,Assumptions!B59) | U84: =IF(20<=3,Assumptions!B58,Assumptions!B59) | V84: =IF(21<=3,Assumptions!B58,Assumptions!B59) | W84: =IF(22<=3,Assumptions!B58,Assumptions!B59) | X84: =IF(23<=3,Assumptions!B58,Assumptions!B59) | Y84: =IF(24<=3,Assumptions!B58,Assumptions!B59) | Z84: =SUM(B84:Y84)
A85: Steuerberater | B85: =Assumptions!B60 | C85: =Assumptions!B60 | D85: =Assumptions!B60 | E85: =Assumptions!B60 | F85: =Assumptions!B60 | G85: =Assumptions!B60 | H85: =Assumptions!B60 | I85: =Assumptions!B60 | J85: =Assumptions!B60 | K85: =Assumptions!B60 | L85: =Assumptions!B60 | M85: =Assumptions!B60 | N85: =Assumptions!B60 | O85: =Assumptions!B60 | P85: =Assumptions!B60 | Q85: =Assumptions!B60 | R85: =Assumptions!B60 | S85: =Assumptions!B60 | T85: =Assumptions!B60 | U85: =Assumptions!B60 | V85: =Assumptions!B60 | W85: =Assumptions!B60 | X85: =Assumptions!B60 | Y85: =Assumptions!B60 | Z85: =SUM(B85:Y85)
A86: Business Insurance | B86: =Assumptions!B61 | C86: =Assumptions!B61 | D86: =Assumptions!B61 | E86: =Assumptions!B61 | F86: =Assumptions!B61 | G86: =Assumptions!B61 | H86: =Assumptions!B61 | I86: =Assumptions!B61 | J86: =Assumptions!B61 | K86: =Assumptions!B61 | L86: =Assumptions!B61 | M86: =Assumptions!B61 | N86: =Assumptions!B61 | O86: =Assumptions!B61 | P86: =Assumptions!B61 | Q86: =Assumptions!B61 | R86: =Assumptions!B61 | S86: =Assumptions!B61 | T86: =Assumptions!B61 | U86: =Assumptions!B61 | V86: =Assumptions!B61 | W86: =Assumptions!B61 | X86: =Assumptions!B61 | Y86: =Assumptions!B61 | Z86: =SUM(B86:Y86)
A87: Utilities (M4+) | B87: =IF(1>=4,Assumptions!B62,0) | C87: =IF(2>=4,Assumptions!B62,0) | D87: =IF(3>=4,Assumptions!B62,0) | E87: =IF(4>=4,Assumptions!B62,0) | F87: =IF(5>=4,Assumptions!B62,0) | G87: =IF(6>=4,Assumptions!B62,0) | H87: =IF(7>=4,Assumptions!B62,0) | I87: =IF(8>=4,Assumptions!B62,0) | J87: =IF(9>=4,Assumptions!B62,0) | K87: =IF(10>=4,Assumptions!B62,0) | L87: =IF(11>=4,Assumptions!B62,0) | M87: =IF(12>=4,Assumptions!B62,0) | N87: =IF(13>=4,Assumptions!B62,0) | O87: =IF(14>=4,Assumptions!B62,0) | P87: =IF(15>=4,Assumptions!B62,0) | Q87: =IF(16>=4,Assumptions!B62,0) | R87: =IF(17>=4,Assumptions!B62,0) | S87: =IF(18>=4,Assumptions!B62,0) | T87: =IF(19>=4,Assumptions!B62,0) | U87: =IF(20>=4,Assumptions!B62,0) | V87: =IF(21>=4,Assumptions!B62,0) | W87: =IF(22>=4,Assumptions!B62,0) | X87: =IF(23>=4,Assumptions!B62,0) | Y87: =IF(24>=4,Assumptions!B62,0) | Z87: =SUM(B87:Y87)
A88: Cleaning/Maintenance (M4+) | B88: =IF(1>=4,Assumptions!B63,0) | C88: =IF(2>=4,Assumptions!B63,0) | D88: =IF(3>=4,Assumptions!B63,0) | E88: =IF(4>=4,Assumptions!B63,0) | F88: =IF(5>=4,Assumptions!B63,0) | G88: =IF(6>=4,Assumptions!B63,0) | H88: =IF(7>=4,Assumptions!B63,0) | I88: =IF(8>=4,Assumptions!B63,0) | J88: =IF(9>=4,Assumptions!B63,0) | K88: =IF(10>=4,Assumptions!B63,0) | L88: =IF(11>=4,Assumptions!B63,0) | M88: =IF(12>=4,Assumptions!B63,0) | N88: =IF(13>=4,Assumptions!B63,0) | O88: =IF(14>=4,Assumptions!B63,0) | P88: =IF(15>=4,Assumptions!B63,0) | Q88: =IF(16>=4,Assumptions!B63,0) | R88: =IF(17>=4,Assumptions!B63,0) | S88: =IF(18>=4,Assumptions!B63,0) | T88: =IF(19>=4,Assumptions!B63,0) | U88: =IF(20>=4,Assumptions!B63,0) | V88: =IF(21>=4,Assumptions!B63,0) | W88: =IF(22>=4,Assumptions!B63,0) | X88: =IF(23>=4,Assumptions!B63,0) | Y88: =IF(24>=4,Assumptions!B63,0) | Z88: =SUM(B88:Y88)
A89: POS System (M4+) | B89: =IF(1>=4,Assumptions!B64,0) | C89: =IF(2>=4,Assumptions!B64,0) | D89: =IF(3>=4,Assumptions!B64,0) | E89: =IF(4>=4,Assumptions!B64,0) | F89: =IF(5>=4,Assumptions!B64,0) | G89: =IF(6>=4,Assumptions!B64,0) | H89: =IF(7>=4,Assumptions!B64,0) | I89: =IF(8>=4,Assumptions!B64,0) | J89: =IF(9>=4,Assumptions!B64,0) | K89: =IF(10>=4,Assumptions!B64,0) | L89: =IF(11>=4,Assumptions!B64,0) | M89: =IF(12>=4,Assumptions!B64,0) | N89: =IF(13>=4,Assumptions!B64,0) | O89: =IF(14>=4,Assumptions!B64,0) | P89: =IF(15>=4,Assumptions!B64,0) | Q89: =IF(16>=4,Assumptions!B64,0) | R89: =IF(17>=4,Assumptions!B64,0) | S89: =IF(18>=4,Assumptions!B64,0) | T89: =IF(19>=4,Assumptions!B64,0) | U89: =IF(20>=4,Assumptions!B64,0) | V89: =IF(21>=4,Assumptions!B64,0) | W89: =IF(22>=4,Assumptions!B64,0) | X89: =IF(23>=4,Assumptions!B64,0) | Y89: =IF(24>=4,Assumptions!B64,0) | Z89: =SUM(B89:Y89)
A90: IHK Berlin | B90: =Assumptions!B65 | C90: =Assumptions!B65 | D90: =Assumptions!B65 | E90: =Assumptions!B65 | F90: =Assumptions!B65 | G90: =Assumptions!B65 | H90: =Assumptions!B65 | I90: =Assumptions!B65 | J90: =Assumptions!B65 | K90: =Assumptions!B65 | L90: =Assumptions!B65 | M90: =Assumptions!B65 | N90: =Assumptions!B65 | O90: =Assumptions!B65 | P90: =Assumptions!B65 | Q90: =Assumptions!B65 | R90: =Assumptions!B65 | S90: =Assumptions!B65 | T90: =Assumptions!B65 | U90: =Assumptions!B65 | V90: =Assumptions!B65 | W90: =Assumptions!B65 | X90: =Assumptions!B65 | Y90: =Assumptions!B65 | Z90: =SUM(B90:Y90)
A91: Permits & Licenses (M3) | B91: =IF(1=3,500,0) | C91: =IF(2=3,500,0) | D91: =IF(3=3,500,0) | E91: =IF(4=3,500,0) | F91: =IF(5=3,500,0) | G91: =IF(6=3,500,0) | H91: =IF(7=3,500,0) | I91: =IF(8=3,500,0) | J91: =IF(9=3,500,0) | K91: =IF(10=3,500,0) | L91: =IF(11=3,500,0) | M91: =IF(12=3,500,0) | N91: =IF(13=3,500,0) | O91: =IF(14=3,500,0) | P91: =IF(15=3,500,0) | Q91: =IF(16=3,500,0) | R91: =IF(17=3,500,0) | S91: =IF(18=3,500,0) | T91: =IF(19=3,500,0) | U91: =IF(20=3,500,0) | V91: =IF(21=3,500,0) | W91: =IF(22=3,500,0) | X91: =IF(23=3,500,0) | Y91: =IF(24=3,500,0) | Z91: =SUM(B91:Y91)
A92: G&A Total | B92: =B84+B85+B86+B87+B88+B89+B90+B91 | C92: =C84+C85+C86+C87+C88+C89+C90+C91 | D92: =D84+D85+D86+D87+D88+D89+D90+D91 | E92: =E84+E85+E86+E87+E88+E89+E90+E91 | F92: =F84+F85+F86+F87+F88+F89+F90+F91 | G92: =G84+G85+G86+G87+G88+G89+G90+G91 | H92: =H84+H85+H86+H87+H88+H89+H90+H91 | I92: =I84+I85+I86+I87+I88+I89+I90+I91 | ... Y92: =Y84+Y85+Y86+Y87+Y88+Y89+Y90+Y91 | Z92: =SUM(B92:Y92)
A93: Management & APIs
A94: SaaS Stack (D9) | B94: =IF(1<=6,Assumptions!B55,IF(1<=12,Assumptions!B56,Assumptions!B57)) | C94: =IF(2<=6,Assumptions!B55,IF(2<=12,Assumptions!B56,Assumptions!B57)) | D94: =IF(3<=6,Assumptions!B55,IF(3<=12,Assumptions!B56,Assumptions!B57)) | E94: =IF(4<=6,Assumptions!B55,IF(4<=12,Assumptions!B56,Assumptions!B57)) | F94: =IF(5<=6,Assumptions!B55,IF(5<=12,Assumptions!B56,Assumptions!B57)) | G94: =IF(6<=6,Assumptions!B55,IF(6<=12,Assumptions!B56,Assumptions!B57)) | H94: =IF(7<=6,Assumptions!B55,IF(7<=12,Assumptions!B56,Assumptions!B57)) | I94: =IF(8<=6,Assumptions!B55,IF(8<=12,Assumptions!B56,Assumptions!B57)) | J94: =IF(9<=6,Assumptions!B55,IF(9<=12,Assumptions!B56,Assumptions!B57)) | K94: =IF(10<=6,Assumptions!B55,IF(10<=12,Assumptions!B56,Assumptions!B57)) | L94: =IF(11<=6,Assumptions!B55,IF(11<=12,Assumptions!B56,Assumptions!B57)) | M94: =IF(12<=6,Assumptions!B55,IF(12<=12,Assumptions!B56,Assumptions!B57)) | N94: =IF(13<=6,Assumptions!B55,IF(13<=12,Assumptions!B56,Assumptions!B57)) | O94: =IF(14<=6,Assumptions!B55,IF(14<=12,Assumptions!B56,Assumptions!B57)) | P94: =IF(15<=6,Assumptions!B55,IF(15<=12,Assumptions!B56,Assumptions!B57)) | Q94: =IF(16<=6,Assumptions!B55,IF(16<=12,Assumptions!B56,Assumptions!B57)) | R94: =IF(17<=6,Assumptions!B55,IF(17<=12,Assumptions!B56,Assumptions!B57)) | S94: =IF(18<=6,Assumptions!B55,IF(18<=12,Assumptions!B56,Assumptions!B57)) | T94: =IF(19<=6,Assumptions!B55,IF(19<=12,Assumptions!B56,Assumptions!B57)) | U94: =IF(20<=6,Assumptions!B55,IF(20<=12,Assumptions!B56,Assumptions!B57)) | V94: =IF(21<=6,Assumptions!B55,IF(21<=12,Assumptions!B56,Assumptions!B57)) | W94: =IF(22<=6,Assumptions!B55,IF(22<=12,Assumptions!B56,Assumptions!B57)) | X94: =IF(23<=6,Assumptions!B55,IF(23<=12,Assumptions!B56,Assumptions!B57)) | Y94: =IF(24<=6,Assumptions!B55,IF(24<=12,Assumptions!B56,Assumptions!B57)) | Z94: =SUM(B94:Y94)
A95: Claude Max (internal) | B95: =Assumptions!B54 | C95: =Assumptions!B54 | D95: =Assumptions!B54 | E95: =Assumptions!B54 | F95: =Assumptions!B54 | G95: =Assumptions!B54 | H95: =Assumptions!B54 | I95: =Assumptions!B54 | J95: =Assumptions!B54 | K95: =Assumptions!B54 | L95: =Assumptions!B54 | M95: =Assumptions!B54 | N95: =Assumptions!B54 | O95: =Assumptions!B54 | P95: =Assumptions!B54 | Q95: =Assumptions!B54 | R95: =Assumptions!B54 | S95: =Assumptions!B54 | T95: =Assumptions!B54 | U95: =Assumptions!B54 | V95: =Assumptions!B54 | W95: =Assumptions!B54 | X95: =Assumptions!B54 | Y95: =Assumptions!B54 | Z95: =SUM(B95:Y95)
A96: Management Total | B96: =B94+B95 | C96: =C94+C95 | D96: =D94+D95 | E96: =E94+E95 | F96: =F94+F95 | G96: =G94+G95 | H96: =H94+H95 | I96: =I94+I95 | ... Y96: =Y94+Y95 | Z96: =SUM(B96:Y96)
A97: Travel
A98: Investor Travel | B98: =Assumptions!B68 | C98: =Assumptions!B68 | D98: =Assumptions!B68 | E98: =Assumptions!B68 | F98: =Assumptions!B68 | G98: =Assumptions!B68 | H98: =Assumptions!B68 | I98: =Assumptions!B68 | J98: =Assumptions!B68 | K98: =Assumptions!B68 | L98: =Assumptions!B68 | M98: =Assumptions!B68 | N98: =Assumptions!B68 | O98: =Assumptions!B68 | P98: =Assumptions!B68 | Q98: =Assumptions!B68 | R98: =Assumptions!B68 | S98: =Assumptions!B68 | T98: =Assumptions!B68 | U98: =Assumptions!B68 | V98: =Assumptions!B68 | W98: =Assumptions!B68 | X98: =Assumptions!B68 | Y98: =Assumptions!B68 | Z98: =SUM(B98:Y98)
A99: Conferences (M7+) | B99: =IF(1>=7,Assumptions!B69,0) | C99: =IF(2>=7,Assumptions!B69,0) | D99: =IF(3>=7,Assumptions!B69,0) | E99: =IF(4>=7,Assumptions!B69,0) | F99: =IF(5>=7,Assumptions!B69,0) | G99: =IF(6>=7,Assumptions!B69,0) | H99: =IF(7>=7,Assumptions!B69,0) | I99: =IF(8>=7,Assumptions!B69,0) | J99: =IF(9>=7,Assumptions!B69,0) | K99: =IF(10>=7,Assumptions!B69,0) | L99: =IF(11>=7,Assumptions!B69,0) | M99: =IF(12>=7,Assumptions!B69,0) | N99: =IF(13>=7,Assumptions!B69,0) | O99: =IF(14>=7,Assumptions!B69,0) | P99: =IF(15>=7,Assumptions!B69,0) | Q99: =IF(16>=7,Assumptions!B69,0) | R99: =IF(17>=7,Assumptions!B69,0) | S99: =IF(18>=7,Assumptions!B69,0) | T99: =IF(19>=7,Assumptions!B69,0) | U99: =IF(20>=7,Assumptions!B69,0) | V99: =IF(21>=7,Assumptions!B69,0) | W99: =IF(22>=7,Assumptions!B69,0) | X99: =IF(23>=7,Assumptions!B69,0) | Y99: =IF(24>=7,Assumptions!B69,0) | Z99: =SUM(B99:Y99)
A100: Local Transport | B100: =Assumptions!B70 | C100: =Assumptions!B70 | D100: =Assumptions!B70 | E100: =Assumptions!B70 | F100: =Assumptions!B70 | G100: =Assumptions!B70 | H100: =Assumptions!B70 | I100: =Assumptions!B70 | J100: =Assumptions!B70 | K100: =Assumptions!B70 | L100: =Assumptions!B70 | M100: =Assumptions!B70 | N100: =Assumptions!B70 | O100: =Assumptions!B70 | P100: =Assumptions!B70 | Q100: =Assumptions!B70 | R100: =Assumptions!B70 | S100: =Assumptions!B70 | T100: =Assumptions!B70 | U100: =Assumptions!B70 | V100: =Assumptions!B70 | W100: =Assumptions!B70 | X100: =Assumptions!B70 | Y100: =Assumptions!B70 | Z100: =SUM(B100:Y100)
A101: Travel Total | B101: =B98+B99+B100 | C101: =C98+C99+C100 | D101: =D98+D99+D100 | E101: =E98+E99+E100 | F101: =F98+F99+F100 | G101: =G98+G99+G100 | H101: =H98+H99+H100 | I101: =I98+I99+I100 | ... Y101: =Y98+Y99+Y100 | Z101: =SUM(B101:Y101)
A102: Recruitment (CTO search M17) | B102: =IF(1=17,Assumptions!B72,0) | C102: =IF(2=17,Assumptions!B72,0) | D102: =IF(3=17,Assumptions!B72,0) | E102: =IF(4=17,Assumptions!B72,0) | F102: =IF(5=17,Assumptions!B72,0) | G102: =IF(6=17,Assumptions!B72,0) | H102: =IF(7=17,Assumptions!B72,0) | I102: =IF(8=17,Assumptions!B72,0) | J102: =IF(9=17,Assumptions!B72,0) | K102: =IF(10=17,Assumptions!B72,0) | L102: =IF(11=17,Assumptions!B72,0) | M102: =IF(12=17,Assumptions!B72,0) | N102: =IF(13=17,Assumptions!B72,0) | O102: =IF(14=17,Assumptions!B72,0) | P102: =IF(15=17,Assumptions!B72,0) | Q102: =IF(16=17,Assumptions!B72,0) | R102: =IF(17=17,Assumptions!B72,0) | S102: =IF(18=17,Assumptions!B72,0) | T102: =IF(19=17,Assumptions!B72,0) | U102: =IF(20=17,Assumptions!B72,0) | V102: =IF(21=17,Assumptions!B72,0) | W102: =IF(22=17,Assumptions!B72,0) | X102: =IF(23=17,Assumptions!B72,0) | Y102: =IF(24=17,Assumptions!B72,0) | Z102: =SUM(B102:Y102)
A104: OpEx (pre-contingency) | B104: =B73+B77+B82+B92+B96+B101+B102 | C104: =C73+C77+C82+C92+C96+C101+C102 | D104: =D73+D77+D82+D92+D96+D101+D102 | E104: =E73+E77+E82+E92+E96+E101+E102 | F104: =F73+F77+F82+F92+F96+F101+F102 | G104: =G73+G77+G82+G92+G96+G101+G102 | H104: =H73+H77+H82+H92+H96+H101+H102 | I104: =I73+I77+I82+I92+I96+I101+I102 | ... Y104: =Y73+Y77+Y82+Y92+Y96+Y101+Y102 | Z104: =SUM(B104:Y104)
A105: Contingency Buffer (10%) | B105: =ROUND(B104*Assumptions!B71,0) | C105: =ROUND(C104*Assumptions!B71,0) | D105: =ROUND(D104*Assumptions!B71,0) | E105: =ROUND(E104*Assumptions!B71,0) | F105: =ROUND(F104*Assumptions!B71,0) | G105: =ROUND(G104*Assumptions!B71,0) | H105: =ROUND(H104*Assumptions!B71,0) | I105: =ROUND(I104*Assumptions!B71,0) | J105: =ROUND(J104*Assumptions!B71,0) | K105: =ROUND(K104*Assumptions!B71,0) | L105: =ROUND(L104*Assumptions!B71,0) | M105: =ROUND(M104*Assumptions!B71,0) | N105: =ROUND(N104*Assumptions!B71,0) | O105: =ROUND(O104*Assumptions!B71,0) | P105: =ROUND(P104*Assumptions!B71,0) | Q105: =ROUND(Q104*Assumptions!B71,0) | R105: =ROUND(R104*Assumptions!B71,0) | S105: =ROUND(S104*Assumptions!B71,0) | T105: =ROUND(T104*Assumptions!B71,0) | U105: =ROUND(U104*Assumptions!B71,0) | V105: =ROUND(V104*Assumptions!B71,0) | W105: =ROUND(W104*Assumptions!B71,0) | X105: =ROUND(X104*Assumptions!B71,0) | Y105: =ROUND(Y104*Assumptions!B71,0) | Z105: =SUM(B105:Y105)
A107: TOTAL OPEX | B107: =B104+B105 | C107: =C104+C105 | D107: =D104+D105 | E107: =E104+E105 | F107: =F104+F105 | G107: =G104+G105 | H107: =H104+H105 | I107: =I104+I105 | ... Y107: =Y104+Y105 | Z107: =SUM(B107:Y107)
A109: EBITDA | B109: =B61-B107 | C109: =C61-C107 | D109: =D61-D107 | E109: =E61-E107 | F109: =F61-F107 | G109: =G61-G107 | H109: =H61-H107 | I109: =I61-I107 | ... Y109: =Y61-Y107 | Z109: =SUM(B109:Y109)
...

Sheet Assumptions
A1: alche — P&L Assumptions
A2: Change any value here → P&L sheet auto-recalculates
A4: SUBSCRIPTION MODEL
A5: Core tier price (EUR/mo) | B5: 19 | C5: Entry tier
A6: Pro tier price (EUR/mo) | B6: 49 | C6: Sweet spot
A7: Premium tier price (EUR/mo) | B7: 99 | C7: Highest ARPU
A8: Monthly churn rate | B8: 0.08 | C8: 8% — locked data
A9: Core tier share | B9: 0.52 | C9: 52%
A10: Pro tier share | B10: 0.38 | C10: 38%
A11: Premium tier share | B11: 0.1 | C11: 10%
A13: SUBSCRIBER GROWTH (new subs/month)
A14: M1-M3 | B14: 3 | C14: Pre-launch beta
A15: M4-M6 | B15: 15 | C15: Product launch
A16: M7-M9 | B16: 22 | C16: Growth acceleration
A17: M10-M12 | B17: 28 | C17: Marketing ramp
A18: M13-M18 | B18: 32 | C18: Scaling
A19: M19-M24 | B19: 38 | C19: Growth marketer effect
A21: PRODUCT PRICING
A22: Potion retail price (EUR) | B22: 49 | C22: R10 validated
A23: Potion COGS (EUR/unit) | B23: 23.5 | C23: R10: wholesale 48% of retail
A24: LED session price (EUR) | B24: 45 | C24: Red light therapy
A25: LED practitioner cost (EUR) | B25: 25 | C25: Per session
A26: Smoothie avg price (EUR) | B26: 9.67 | C26: R2 Cost Analysis PDF
A27: Smoothie COGS rate | B27: 0.35 | C27: 35% ingredients+packaging (R2)
A28: Event ticket price (EUR) | B28: 35 | C28: Community events
A29: Event fixed cost (EUR) | B29: 250 | C29: Venue per event
A30: Ticketing platform fee | B30: 0.07 | C30: 7% Luma/Eventbrite
A31: Doctor SaaS fee (EUR/mo) | B31: 99 | C31: D1: was EUR 150
A32: Doctor verify cost (EUR) | B32: 25 | C32: Per new doctor
A33: Doctor max clinics | B33: 20 | C33: D1: cap for M1-24
A35: COST RATES
A36: Waste — blended rate | B36: 0.055 | C36: D7: capsules 4%, powders 7%
A37: 3PL fulfillment (EUR/unit) | B37: 2.5 | C37: Potions only
A38: Stripe fee rate | B38: 0.029 | C38: 2.9%
A39: AI API per user (EUR/mo) | B39: 0.35 | C39: D6: hybrid Claude+Gemini R9
A40: Refund/returns reserve | B40: 0.015 | C40: 1.5% of product revenue
A42: PAYROLL
A43: Founder gross salary (each) | B43: 4166 | C43: EUR/mo
A44: Employer multiplier | B44: 1.22 | C44: German social contributions
A45: Space staff gross (M4+) | B45: 1230 | C45: Part-time
A46: Partner Mgr gross (M6+) | B46: 2000 | C46: EUR/mo
A47: Growth Marketer gross (M12+) | B47: 4500 | C47: EUR/mo
A48: Tech/Ops Lead gross (M18+) | B48: 6500 | C48: EUR/mo
A49: BG insurance rate | B49: 0.015 | C49: ~1.5% of gross payroll (mandatory)
A51: FIXED OPERATING COSTS
A52: App maintenance retainer | B52: 1500 | C52: External agency
A53: UX/UI design retainer | B53: 800 | C53: R6 flags: EUR 99K/24mo needed
A54: Claude Max (internal AI) | B54: 210 | C54: D6: team budget
A55: SaaS Stack M1-6 | B55: 338 | C55: D9: Google, Figma, Notion, Crisp
A56: SaaS Stack M7-12 | B56: 500 | C56: D9: + tools
A57: SaaS Stack M13+ | B57: 750 | C57: D9: full stack
A58: Rent M1-3 (co-working) | B58: 750 | C58: Before space opens
A59: Rent M4+ (physical space) | B59: 2500 | C59: Wellness space + smoothie bar
A60: Steuerberater | B60: 400 | C60: Tax advisor
A61: Business insurance | B61: 200 | C61: General liability
A62: Utilities M4+ (Strom/Gas/Wasser) | B62: 400 | C62: Physical space
A63: Cleaning/maintenance M4+ | B63: 300 | C63: Physical space
... A72: Recruitment M17 (CTO search) | B72: 5000 | C72: One-off
A74: CAPITAL EXPENDITURES (D5)
A75: GmbH Formation (M1) | B75: 2500 | C75: One-off
A76: Legal Opinion HWG (M1) | B76: 3500 | C76: One-off
A77: R&D Stability Testing (M1) | B77: 5000 | C77: One-off
A78: Space Buildout (M3) | B78: 15000 | C78: One-off
A79: Kitchen Equipment (M3) | B79: 20000 | C79: Smoothie bar
A80: LED Therapy Devices (M3) | B80: 5000 | C80: One-off
A81: CapEx depreciation (months) | B81: 36 | C81: Linear 3-year

Sheet Growth Curves
A1: alche — Monthly Growth Curves (Input Data)
A2: Edit these numbers to change unit forecasts. P&L formulas reference these cells.
A3: Metric | B3: M1 | C3: M2 | D3: M3 | E3: M4 | F3: M5 | G3: M6 | H3: M7 | I3: M8 | J3: M9 | K3: M10 | L3: M11 | M3: M12 | N3: M13 | O3: M14 | P3: M15 | Q3: M16 | R3: M17 | S3: M18 | T3: M19 | U3: M20 | V3: M21 | W3: M22 | X3: M23 | Y3: M24
A4: Potion Units | B4: 0 | C4: 0 | D4: 0 | E4: 50 | F4: 100 | G4: 150 | H4: 250 | I4: 350 | J4: 450 | K4: 600 | L4: 750 | M4: 900 | N4: 1100 | O4: 1300 | P4: 1500 | Q4: 1800 | R4: 2100 | S4: 2400 | T4: 2700 | U4: 3000 | V4: 3400 | W4: 3800 | X4: 4200 | Y4: 4600
A5: LED Sessions | B5: 0 | C5: 0 | D5: 0 | E5: 10 | F5: 20 | G5: 35 | H5: 50 | I5: 65 | J5: 80 | K5: 100 | L5: 120 | M5: 140 | N5: 160 | O5: 180 | P5: 200 | Q5: 220 | R5: 240 | S5: 260 | T5: 280 | U5: 300 | V5: 300 | W5: 300 | X5: 300 | Y5: 300
A6: Smoothie Units | B6: 0 | C6: 0 | D6: 0 | E6: 100 | F6: 150 | G6: 250 | H6: 350 | I6: 450 | J6: 550 | K6: 650 | L6: 750 | M6: 850 | N6: 950 | O6: 1050 | P6: 1150 | Q6: 1250 | R6: 1350 | S6: 1450 | T6: 1550 | U6: 1650 | V6: 1750 | W6: 1850 | X6: 1950 | Y6: 2000
A7: Event Count | B7: 0 | C7: 0 | D7: 0 | E7: 1 | F7: 1 | G7: 2 | H7: 2 | I7: 3 | J7: 3 | K7: 3 | L7: 3 | M7: 3 | N7: 3 | O7: 3 | P7: 4 | Q7: 4 | R7: 4 | S7: 4 | T7: 4 | U7: 5 | V7: 5 | W7: 5 | X7: 5 | Y7: 5
A8: Event Avg Attendees | B8: 0 | C8: 0 | D8: 0 | E8: 12 | F8: 15 | G8: 15 | H8: 18 | I8: 18 | J8: 18 | K8: 20 | L8: 20 | M8: 20 | N8: 22 | O8: 22 | P8: 22 | Q8: 22 | R8: 24 | S8: 24 | T8: 25 | U8: 25 | V8: 25 | W8: 25 | X8: 25 | Y8: 25
A9: Doctor Clinics | B9: 0 | C9: 0 | D9: 0 | E9: 0 | F9: 0 | G9: 2 | H9: 5 | I9: 8 | J9: 10 | K9: 12 | L9: 15 | M9: 17 | N9: 18 | O9: 19 | P9: 20 | Q9: 20 | R9: 20 | S9: 20 | T9: 20 | U9: 20 | V9: 20 | W9: 20 | X9: 20 | Y9: 20
A10: Marketing Spend (EUR) | B10: 50 | C10: 50 | D10: 100 | E10: 200 | F10: 400 | G10: 600 | H10: 800 | I10: 800 | J10: 1000 | K10: 1200 | L10: 1400 | M10: 1400 | N10: 1800 | O10: 1800 | P10: 2000 | Q10: 2000 | R10: 2200 | S10: 2200 | T10: 2500 | U10: 2500 | V10: 2800 | W10: 2800 | X10: 3000 | Y10: 3000
A11: New Doctors (delta) | B11: 0 | C11: =MAX(0,C9-B9) | D11: =MAX(0,D9-C9) | E11: =MAX(0,E9-D9) | F11: =MAX(0,F9-E9) | G11: =MAX(0,G9-F9) | H11: =MAX(0,H9-G9) | I11: =MAX(0,I9-H9) | J11: =MAX(0,J9-I9) | ... Y11: =MAX(0,Y9-X9)
A13: SUBSCRIBER MODEL
A14: New Subs Rate | B14: =IF(1<=3,Assumptions!B14,IF(1<=6,Assumptions!B15,IF(1<=9,Assumptions!B16,IF(1<=12,Assumptions!B17,IF(1<=18,Assumptions!B18,Assumptions!B19))))) | C14: =IF(2<=3,Assumptions!B14,IF(2<=6,Assumptions!B15,IF(2<=9,Assumptions!B16,IF(2<=12,Assumptions!B17,IF(2<=18,Assumptions!B18,Assumptions!B19))))) | D14: =IF(3<=3,Assumptions!B14,IF(3<=6,Assumptions!B15,IF(3<=9,Assumptions!B16,IF(3<=12,Assumptions!B17,IF(3<=18,Assumptions!B18,Assumptions!B19))))) | E14: =IF(4<=3,Assumptions!B14,IF(4<=6,Assumptions!B15,IF(4<=9,Assumptions!B16,IF(4<=12,Assumptions!B17,IF(4<=18,Assumptions!B18,Assumptions!B19))))) | F14: =IF(5<=3,Assumptions!B14,IF(5<=6,Assumptions!B15,IF(5<=9,Assumptions!B16,IF(5<=12,Assumptions!B17,IF(5<=18,Assumptions!B18,Assumptions!B19))))) | G14: =IF(6<=3,Assumptions!B14,IF(6<=6,Assumptions!B15,IF(6<=9,Assumptions!B16,IF(6<=12,Assumptions!B17,IF(6<=18,Assumptions!B18,Assumptions!B19))))) | H14: =IF(7<=3,Assumptions!B14,IF(7<=6,Assumptions!B15,IF(7<=9,Assumptions!B16,IF(7<=12,Assumptions!B17,IF(7<=18,Assumptions!B18,Assumptions!B19))))) | I14: =IF(8<=3,Assumptions!B14,IF(8<=6,Assumptions!B15,IF(8<=9,Assumptions!B16,IF(8<=12,Assumptions!B17,IF(8<=18,Assumptions!B18,Assumptions!B19))))) | J14: =IF(9<=3,Assumptions!B14,IF(9<=6,Assumptions!B15,IF(9<=9,Assumptions!B16,IF(9<=12,Assumptions!B17,IF(9<=18,Assumptions!B18,Assumptions!B19))))) | K14: =IF(10<=3,Assumptions!B14,IF(10<=6,Assumptions!B15,IF(10<=9,Assumptions!B16,IF(10<=12,Assumptions!B17,IF(10<=18,Assumptions!B18,Assumptions!B19))))) | L14: =IF(11<=3,Assumptions!B14,IF(11<=6,Assumptions!B15,IF(11<=9,Assumptions!B16,IF(11<=12,Assumptions!B17,IF(11<=18,Assumptions!B18,Assumptions!B19))))) | M14: =IF(12<=3,Assumptions!B14,IF(12<=6,Assumptions!B15,IF(12<=9,Assumptions!B16,IF(12<=12,Assumptions!B17,IF(12<=18,Assumptions!B18,Assumptions!B19))))) | N14: =IF(13<=3,Assumptions!B14,IF(13<=6,Assumptions!B15,IF(13<=9,Assumptions!B16,IF(13<=12,Assumptions!B17,IF(13<=18,Assumptions!B18,Assumptions!B19))))) | O14: =IF(14<=3,Assumptions!B14,IF(14<=6,Assumptions!B15,IF(14<=9,Assumptions!B16,IF(14<=12,Assumptions!B17,IF(14<=18,Assumptions!B18,Assumptions!B19))))) | P14: =IF(15<=3,Assumptions!B14,IF(15<=6,Assumptions!B15,IF(15<=9,Assumptions!B16,IF(15<=12,Assumptions!B17,IF(15<=18,Assumptions!B18,Assumptions!B19))))) | Q14: =IF(16<=3,Assumptions!B14,IF(16<=6,Assumptions!B15,IF(16<=9,Assumptions!B16,IF(16<=12,Assumptions!B17,IF(16<=18,Assumptions!B18,Assumptions!B19))))) | R14: =IF(17<=3,Assumptions!B14,IF(17<=6,Assumptions!B15,IF(17<=9,Assumptions!B16,IF(17<=12,Assumptions!B17,IF(17<=18,Assumptions!B18,Assumptions!B19))))) | S14: =IF(18<=3,Assumptions!B14,IF(18<=6,Assumptions!B15,IF(18<=9,Assumptions!B16,IF(18<=12,Assumptions!B17,IF(18<=18,Assumptions!B18,Assumptions!B19))))) | T14: =IF(19<=3,Assumptions!B14,IF(19<=6,Assumptions!B15,IF(19<=9,Assumptions!B16,IF(19<=12,Assumptions!B17,IF(19<=18,Assumptions!B18,Assumptions!B19))))) | U14: =IF(20<=3,Assumptions!B14,IF(20<=6,Assumptions!B15,IF(20<=9,Assumptions!B16,IF(20<=12,Assumptions!B17,IF(20<=18,Assumptions!B18,Assumptions!B19))))) | V14: =IF(21<=3,Assumptions!B14,IF(21<=6,Assumptions!B15,IF(21<=9,Assumptions!B16,IF(21<=12,Assumptions!B17,IF(21<=18,Assumptions!B18,Assumptions!B19))))) | W14: =IF(22<=3,Assumptions!B14,IF(22<=6,Assumptions!B15,IF(22<=9,Assumptions!B16,IF(22<=12,Assumptions!B17,IF(22<=18,Assumptions!B18,Assumptions!B19))))) | X14: =IF(23<=3,Assumptions!B14,IF(23<=6,Assumptions!B15,IF(23<=9,Assumptions!B16,IF(23<=12,Assumptions!B17,IF(23<=18,Assumptions!B18,Assumptions!B19))))) | Y14: =IF(24<=3,Assumptions!B14,IF(24<=6,Assumptions!B15,IF(24<=9,Assumptions!B16,IF(24<=12,Assumptions!B17,IF(24<=18,Assumptions!B18,Assumptions!B19)))))
A15: Churned Subs | B15: 0 | C15: =ROUND(B16*Assumptions!B8,0) | D15: =ROUND(C16*Assumptions!B8,0) | E15: =ROUND(D16*Assumptions!B8,0) | F15: =ROUND(E16*Assumptions!B8,0) | G15: =ROUND(F16*Assumptions!B8,0) | H15: =ROUND(G16*Assumptions!B8,0) | I15: =ROUND(H16*Assumptions!B8,0) | J15: =ROUND(I16*Assumptions!B8,0) | K15: =ROUND(J16*Assumptions!B8,0) | L15: =ROUND(K16*Assumptions!B8,0) | M15: =ROUND(L16*Assumptions!B8,0) | N15: =ROUND(M16*Assumptions!B8,0) | O15: =ROUND(N16*Assumptions!B8,0) | P15: =ROUND(O16*Assumptions!B8,0) | Q15: =ROUND(P16*Assumptions!B8,0) | R15: =ROUND(Q16*Assumptions!B8,0) | S15: =ROUND(R16*Assumptions!B8,0) | T15: =ROUND(S16*Assumptions!B8,0) | U15: =ROUND(T16*Assumptions!B8,0) | V15: =ROUND(U16*Assumptions!B8,0) | W15: =ROUND(V16*Assumptions!B8,0) | X15: =ROUND(W16*Assumptions!B8,0) | Y15: =ROUND(X16*Assumptions!B8,0)
A16: Total Subscribers | B16: =MAX(0,B14-B15) | C16: =MAX(0,B16-C15+C14) | D16: =MAX(0,C16-D15+D14) | E16: =MAX(0,D16-E15+E14) | F16: =MAX(0,E16-F15+F14) | G16: =MAX(0,F16-G15+G14) | H16: =MAX(0,G16-H15+H14) | I16: =MAX(0,H16-I15+I14) | J16: =MAX(0,I16-J15+J14) | ... Y16: =MAX(0,X16-Y15+Y14)
A17: Core Subs (52%) | B17: =ROUND(B16*Assumptions!B9,0) | C17: =ROUND(C16*Assumptions!B9,0) | D17: =ROUND(D16*Assumptions!B9,0) | E17: =ROUND(E16*Assumptions!B9,0) | F17: =ROUND(F16*Assumptions!B9,0) | G17: =ROUND(G16*Assumptions!B9,0) | H17: =ROUND(H16*Assumptions!B9,0) | I17: =ROUND(I16*Assumptions!B9,0) | J17: =ROUND(J16*Assumptions!B9,0) | K17: =ROUND(K16*Assumptions!B9,0) | L17: =ROUND(L16*Assumptions!B9,0) | M17: =ROUND(M16*Assumptions!B9,0) | N17: =ROUND(N16*Assumptions!B9,0) | O17: =ROUND(O16*Assumptions!B9,0) | P17: =ROUND(P16*Assumptions!B9,0) | Q17: =ROUND(Q16*Assumptions!B9,0) | R17: =ROUND(R16*Assumptions!B9,0) | S17: =ROUND(S16*Assumptions!B9,0) | T17: =ROUND(T16*Assumptions!B9,0) | U17: =ROUND(U16*Assumptions!B9,0) | V17: =ROUND(V16*Assumptions!B9,0) | W17: =ROUND(W16*Assumptions!B9,0) | X17: =ROUND(X16*Assumptions!B9,0) | Y17: =ROUND(Y16*Assumptions!B9,0)
A18: Pro Subs (38%) | B18: =ROUND(B16*Assumptions!B10,0) | C18: =ROUND(C16*Assumptions!B10,0) | D18: =ROUND(D16*Assumptions!B10,0) | E18: =ROUND(E16*Assumptions!B10,0) | F18: =ROUND(F16*Assumptions!B10,0) | G18: =ROUND(G16*Assumptions!B10,0) | H18: =ROUND(H16*Assumptions!B10,0) | I18: =ROUND(I16*Assumptions!B10,0) | J18: =ROUND(J16*Assumptions!B10,0) | K18: =ROUND(K16*Assumptions!B10,0) | L18: =ROUND(L16*Assumptions!B10,0) | M18: =ROUND(M16*Assumptions!B10,0) | N18: =ROUND(N16*Assumptions!B10,0) | O18: =ROUND(O16*Assumptions!B10,0) | P18: =ROUND(P16*Assumptions!B10,0) | Q18: =ROUND(Q16*Assumptions!B10,0) | R18: =ROUND(R16*Assumptions!B10,0) | S18: =ROUND(S16*Assumptions!B10,0) | T18: =ROUND(T16*Assumptions!B10,0) | U18: =ROUND(U16*Assumptions!B10,0) | V18: =ROUND(V16*Assumptions!B10,0) | W18: =ROUND(W16*Assumptions!B10,0) | X18: =ROUND(X16*Assumptions!B10,0) | Y18: =ROUND(Y16*Assumptions!B10,0)
A19: Premium Subs (10%) | B19: =MAX(0,B16-B17-B18) | C19: =MAX(0,C16-C17-C18) | D19: =MAX(0,D16-D17-D18) | E19: =MAX(0,E16-E17-E18) | F19: =MAX(0,F16-F17-F18) | G19: =MAX(0,G16-G17-G18) | H19: =MAX(0,H16-H17-H18) | I19: =MAX(0,I16-I17-I18) | ... Y19: =MAX(0,Y16-Y17-Y18)

Sheet Decisions
A1: alche — Decision Log (D1-D11)
A2: All decisions from P&L session, 2026-02-23
A4: # | B4: Decision | C4: Choice Made | D4: Old Value | E4: P&L Impact
A5: D1 | B5: Doctor Revenue | C5: C. SaaS EUR 99/mo × 20 clinics | D5: EUR 150/mo × 865 | E5: Revenue -75%; legally safe (StGB §299a)
A6: D2 | B6: Restaurant Revenue | C6: B. Phase 2 (500+ users) | D6: EUR 1.50/cover M6+ | E6: EUR 0 all 24 months
A7: D3 | B7: CGM Hardware | C7: A. Software-Only BYOD | D7: EUR 130 × units | E7: Removed; margin 80-90%
A8: D4 | B8: Physical Space | C8: A. Smoothie bar + space | D8: EUR 0 | E8: New rev + EUR 2,500/mo rent + CapEx
A9: D5 | B9: CapEx Section | C9: Yes, include | D9: All OpEx | E9: EUR 51,000 total
A10: D6 | B10: AI Cost Model | C10: Both internal + user-facing | D10: EUR 210 + EUR 499 Terra | E10: EUR 210 + EUR 0.35/sub (R9)
A11: D7 | B11: Product Waste | C11: Category-weighted | D11: Flat 5% | E11: 5.5% blended
A12: D8 | B12: Terra CGM API | C12: Defer — free HealthKit | D12: EUR 499/mo M6+ | E12: Saves EUR 9,481
A13: D9 | B13: SaaS Stack | C13: Itemized (R8) | D13: EUR 350→1800 | E13: EUR 338→500→750
A14: D10 | B14: Menu Analysis | C14: EUR 0 — founders do it | D14: EUR 500/mo | E14: Saves EUR 12,000
A15: D11 | B15: Retail Products | C15: EUR 49 validated; COGS EUR 23.50 | D15: EUR 11.50 COGS | E15: Margin 76% → 52% (R10)
A18: NEW LINES ADDED (7-Persona Audit)
A19: # | B19: Line Item | C19: Amount | D19: Source Persona | E19: Rationale
A20: P1 | B20: Utilities (Strom/Gas/Wasser) | C20: EUR 400/mo from M4 | D20: Operations Manager | E20: Can't run smoothie bar without electricity
A21: P2 | B21: Cleaning/Maintenance | C21: EUR 300/mo from M4 | D21: Operations Manager | E21: Physical space upkeep
A22: P3 | B22: BG Insurance | C22: ~1.5% of gross payroll | D22: Steuerberater | E22: MANDATORY German employer insurance
A23: P4 | B23: Contingency Buffer | C23: 10% of OpEx | D23: Angel Investor | E23: Every serious investor expects this
A24: P5 | B24: Refund/Returns Reserve | C24: 1.5% of product revenue | D24: CFO/FP&A | E24: Physical product returns
A25: P6 | B25: IHK Berlin | C25: EUR 25/mo (EUR 300/yr) | D25: Steuerberater | E25: Mandatory chamber membership
A26: P7 | B26: Recruitment Cost | C26: EUR 5,000 one-off M17 | D26: HR Manager | E26: CTO job posting / headhunter
A27: P8 | B27: POS System | C27: EUR 50/mo from M4 | D27: Operations Manager | E27: Cash register for space
A28: P9 | B28: Depreciation | C28: CapEx / 36 months linear | D28: CFO/FP&A | E28: Tax-accurate P&L presentation
A29: P10 | B29: Permits & Licenses | C29: EUR 500 one-off M3 | D29: Food Inspector | E29: Lebensmittelüberwachung
A30: P11 | B30: Space Staff | C30: EUR 1,501/mo from M4 | D30: Operations Manager | E30: Part-time for smoothie bar
