Workbook

Sheet P&L
A1: alche — 24-Month P&L v4
A2: Pre-Seed | EUR 300K @ EUR 2.5M Cap | v4: Annual subs + B2B + Gift Cards + Corrected App/Rent costs
A3: All amounts in EUR net of VAT. Click any cell to see the formula.
A4: Budget P&L (EUR) | B4: M1 | C4: M2 | D4: M3 | E4: M4 | F4: M5 | G4: M6 | H4: M7 | I4: M8 | J4: M9 | K4: M10 | L4: M11 | M4: M12 | N4: M13 | O4: M14 | P4: M15 | Q4: M16 | R4: M17 | S4: M18 | T4: M19 | U4: M20 | V4: M21 | W4: M22 | X4: M23 | Y4: M24 | Z4: TOTAL
A5: SUBSCRIBER METRICS
A6: New Subs Added | B6: ='Growth Curves'!B15 | C6: ='Growth Curves'!C15 | D6: ='Growth Curves'!D15 | E6: ='Growth Curves'!E15 | F6: ='Growth Curves'!F15 | G6: ='Growth Curves'!G15 | H6: ='Growth Curves'!H15 | I6: ='Growth Curves'!I15 | ... Y6: ='Growth Curves'!Y15 | Z6: =SUM(B6:Y6)
A7: Churned Subs | B7: ='Growth Curves'!B16 | C7: ='Growth Curves'!C16 | D7: ='Growth Curves'!D16 | E7: ='Growth Curves'!E16 | F7: ='Growth Curves'!F16 | G7: ='Growth Curves'!G16 | H7: ='Growth Curves'!H16 | I7: ='Growth Curves'!I16 | ... Y7: ='Growth Curves'!Y16 | Z7: =SUM(B7:Y7)
A8: Total Subscribers | B8: ='Growth Curves'!B17 | C8: ='Growth Curves'!C17 | D8: ='Growth Curves'!D17 | E8: ='Growth Curves'!E17 | F8: ='Growth Curves'!F17 | G8: ='Growth Curves'!G17 | H8: ='Growth Curves'!H17 | I8: ='Growth Curves'!I17 | ... Y8: ='Growth Curves'!Y17 | Z8: =SUM(B8:Y8)
A9: Core (52%) | B9: ='Growth Curves'!B18 | C9: ='Growth Curves'!C18 | D9: ='Growth Curves'!D18 | E9: ='Growth Curves'!E18 | F9: ='Growth Curves'!F18 | G9: ='Growth Curves'!G18 | H9: ='Growth Curves'!H18 | I9: ='Growth Curves'!I18 | ... Y9: ='Growth Curves'!Y18 | Z9: =SUM(B9:Y9)
A10: Pro (38%) | B10: ='Growth Curves'!B19 | C10: ='Growth Curves'!C19 | D10: ='Growth Curves'!D19 | E10: ='Growth Curves'!E19 | F10: ='Growth Curves'!F19 | G10: ='Growth Curves'!G19 | H10: ='Growth Curves'!H19 | I10: ='Growth Curves'!I19 | ... Y10: ='Growth Curves'!Y19 | Z10: =SUM(B10:Y10)
A11: Premium (10%) | B11: ='Growth Curves'!B20 | C11: ='Growth Curves'!C20 | D11: ='Growth Curves'!D20 | E11: ='Growth Curves'!E20 | F11: ='Growth Curves'!F20 | G11: ='Growth Curves'!G20 | H11: ='Growth Curves'!H20 | I11: ='Growth Curves'!I20 | ... Y11: ='Growth Curves'!Y20 | Z11: =SUM(B11:Y11)
A13: INCOME
A14: Retail Products (D11: EUR 49 validated, COGS EUR 23.50)
A15: Units sold | B15: ='Growth Curves'!B4 | C15: ='Growth Curves'!C4 | D15: ='Growth Curves'!D4 | E15: ='Growth Curves'!E4 | F15: ='Growth Curves'!F4 | G15: ='Growth Curves'!G4 | H15: ='Growth Curves'!H4 | I15: ='Growth Curves'!I4 | ... Y15: ='Growth Curves'!Y4 | Z15: =SUM(B15:Y15)
A16: Price/unit | B16: =Assumptions!B22 | C16: =Assumptions!B22 | D16: =Assumptions!B22 | E16: =Assumptions!B22 | F16: =Assumptions!B22 | G16: =Assumptions!B22 | H16: =Assumptions!B22 | I16: =Assumptions!B22 | J16: =Assumptions!B22 | K16: =Assumptions!B22 | L16: =Assumptions!B22 | M16: =Assumptions!B22 | N16: =Assumptions!B22 | O16: =Assumptions!B22 | P16: =Assumptions!B22 | Q16: =Assumptions!B22 | R16: =Assumptions!B22 | S16: =Assumptions!B22 | T16: =Assumptions!B22 | U16: =Assumptions!B22 | V16: =Assumptions!B22 | W16: =Assumptions!B22 | X16: =Assumptions!B22 | Y16: =Assumptions!B22 | Z16: =SUM(B16:Y16)
A17: Revenue | B17: =B15*Assumptions!B22 | C17: =C15*Assumptions!B22 | D17: =D15*Assumptions!B22 | E17: =E15*Assumptions!B22 | F17: =F15*Assumptions!B22 | G17: =G15*Assumptions!B22 | H17: =H15*Assumptions!B22 | I17: =I15*Assumptions!B22 | J17: =J15*Assumptions!B22 | K17: =K15*Assumptions!B22 | L17: =L15*Assumptions!B22 | M17: =M15*Assumptions!B22 | N17: =N15*Assumptions!B22 | O17: =O15*Assumptions!B22 | P17: =P15*Assumptions!B22 | Q17: =Q15*Assumptions!B22 | R17: =R15*Assumptions!B22 | S17: =S15*Assumptions!B22 | T17: =T15*Assumptions!B22 | U17: =U15*Assumptions!B22 | V17: =V15*Assumptions!B22 | W17: =W15*Assumptions!B22 | X17: =X15*Assumptions!B22 | Y17: =Y15*Assumptions!B22 | Z17: =SUM(B17:Y17)
A18: LED Therapy (Free with Smoothie)
A19: Sessions (self-service) | B19: ='Growth Curves'!B5 | C19: ='Growth Curves'!C5 | D19: ='Growth Curves'!D5 | E19: ='Growth Curves'!E5 | F19: ='Growth Curves'!F5 | G19: ='Growth Curves'!G5 | H19: ='Growth Curves'!H5 | I19: ='Growth Curves'!I5 | ... Y19: ='Growth Curves'!Y5 | Z19: =SUM(B19:Y19)
A20: Price/session | B20: =Assumptions!B24 | C20: =Assumptions!B24 | D20: =Assumptions!B24 | E20: =Assumptions!B24 | F20: =Assumptions!B24 | G20: =Assumptions!B24 | H20: =Assumptions!B24 | I20: =Assumptions!B24 | J20: =Assumptions!B24 | K20: =Assumptions!B24 | L20: =Assumptions!B24 | M20: =Assumptions!B24 | N20: =Assumptions!B24 | O20: =Assumptions!B24 | P20: =Assumptions!B24 | Q20: =Assumptions!B24 | R20: =Assumptions!B24 | S20: =Assumptions!B24 | T20: =Assumptions!B24 | U20: =Assumptions!B24 | V20: =Assumptions!B24 | W20: =Assumptions!B24 | X20: =Assumptions!B24 | Y20: =Assumptions!B24 | Z20: =SUM(B20:Y20)
A21: Revenue (EUR 0 — free amenity) | B21: =B19*Assumptions!B24 | C21: =C19*Assumptions!B24 | D21: =D19*Assumptions!B24 | E21: =E19*Assumptions!B24 | F21: =F19*Assumptions!B24 | G21: =G19*Assumptions!B24 | H21: =H19*Assumptions!B24 | I21: =I19*Assumptions!B24 | J21: =J19*Assumptions!B24 | K21: =K19*Assumptions!B24 | L21: =L19*Assumptions!B24 | M21: =M19*Assumptions!B24 | N21: =N19*Assumptions!B24 | O21: =O19*Assumptions!B24 | P21: =P19*Assumptions!B24 | Q21: =Q19*Assumptions!B24 | R21: =R19*Assumptions!B24 | S21: =S19*Assumptions!B24 | T21: =T19*Assumptions!B24 | U21: =U19*Assumptions!B24 | V21: =V19*Assumptions!B24 | W21: =W19*Assumptions!B24 | X21: =X19*Assumptions!B24 | Y21: =Y19*Assumptions!B24 | Z21: =SUM(B21:Y21)
A22: Smoothie Bar
A23: Units sold | B23: ='Growth Curves'!B6 | C23: ='Growth Curves'!C6 | D23: ='Growth Curves'!D6 | E23: ='Growth Curves'!E6 | F23: ='Growth Curves'!F6 | G23: ='Growth Curves'!G6 | H23: ='Growth Curves'!H6 | I23: ='Growth Curves'!I6 | ... Y23: ='Growth Curves'!Y6 | Z23: =SUM(B23:Y23)
A24: Price/smoothie | B24: =Assumptions!B26 | C24: =Assumptions!B26 | D24: =Assumptions!B26 | E24: =Assumptions!B26 | F24: =Assumptions!B26 | G24: =Assumptions!B26 | H24: =Assumptions!B26 | I24: =Assumptions!B26 | J24: =Assumptions!B26 | K24: =Assumptions!B26 | L24: =Assumptions!B26 | M24: =Assumptions!B26 | N24: =Assumptions!B26 | O24: =Assumptions!B26 | P24: =Assumptions!B26 | Q24: =Assumptions!B26 | R24: =Assumptions!B26 | S24: =Assumptions!B26 | T24: =Assumptions!B26 | U24: =Assumptions!B26 | V24: =Assumptions!B26 | W24: =Assumptions!B26 | X24: =Assumptions!B26 | Y24: =Assumptions!B26 | Z24: =SUM(B24:Y24)
A25: Revenue | B25: =ROUND(B23*Assumptions!B26,0) | C25: =ROUND(C23*Assumptions!B26,0) | D25: =ROUND(D23*Assumptions!B26,0) | E25: =ROUND(E23*Assumptions!B26,0) | F25: =ROUND(F23*Assumptions!B26,0) | G25: =ROUND(G23*Assumptions!B26,0) | H25: =ROUND(H23*Assumptions!B26,0) | I25: =ROUND(I23*Assumptions!B26,0) | J25: =ROUND(J23*Assumptions!B26,0) | K25: =ROUND(K23*Assumptions!B26,0) | L25: =ROUND(L23*Assumptions!B26,0) | M25: =ROUND(M23*Assumptions!B26,0) | N25: =ROUND(N23*Assumptions!B26,0) | O25: =ROUND(O23*Assumptions!B26,0) | P25: =ROUND(P23*Assumptions!B26,0) | Q25: =ROUND(Q23*Assumptions!B26,0) | R25: =ROUND(R23*Assumptions!B26,0) | S25: =ROUND(S23*Assumptions!B26,0) | T25: =ROUND(T23*Assumptions!B26,0) | U25: =ROUND(U23*Assumptions!B26,0) | V25: =ROUND(V23*Assumptions!B26,0) | W25: =ROUND(W23*Assumptions!B26,0) | X25: =ROUND(X23*Assumptions!B26,0) | Y25: =ROUND(Y23*Assumptions!B26,0) | Z25: =SUM(B25:Y25)
A26: Community Events
A27: Event count | B27: ='Growth Curves'!B7 | C27: ='Growth Curves'!C7 | D27: ='Growth Curves'!D7 | E27: ='Growth Curves'!E7 | F27: ='Growth Curves'!F7 | G27: ='Growth Curves'!G7 | H27: ='Growth Curves'!H7 | I27: ='Growth Curves'!I7 | ... Y27: ='Growth Curves'!Y7 | Z27: =SUM(B27:Y27)
A28: Avg attendees/event | B28: ='Growth Curves'!B8 | C28: ='Growth Curves'!C8 | D28: ='Growth Curves'!D8 | E28: ='Growth Curves'!E8 | F28: ='Growth Curves'!F8 | G28: ='Growth Curves'!G8 | H28: ='Growth Curves'!H8 | I28: ='Growth Curves'!I8 | ... Y28: ='Growth Curves'!Y8 | Z28: =SUM(B28:Y28)
A29: Total attendees | B29: =B27*B28 | C29: =C27*C28 | D29: =D27*D28 | E29: =E27*E28 | F29: =F27*F28 | G29: =G27*G28 | H29: =H27*H28 | I29: =I27*I28 | ... Y29: =Y27*Y28 | Z29: =SUM(B29:Y29)
A30: Price/ticket | B30: =Assumptions!B28 | C30: =Assumptions!B28 | D30: =Assumptions!B28 | E30: =Assumptions!B28 | F30: =Assumptions!B28 | G30: =Assumptions!B28 | H30: =Assumptions!B28 | I30: =Assumptions!B28 | J30: =Assumptions!B28 | K30: =Assumptions!B28 | L30: =Assumptions!B28 | M30: =Assumptions!B28 | N30: =Assumptions!B28 | O30: =Assumptions!B28 | P30: =Assumptions!B28 | Q30: =Assumptions!B28 | R30: =Assumptions!B28 | S30: =Assumptions!B28 | T30: =Assumptions!B28 | U30: =Assumptions!B28 | V30: =Assumptions!B28 | W30: =Assumptions!B28 | X30: =Assumptions!B28 | Y30: =Assumptions!B28 | Z30: =SUM(B30:Y30)
A31: Revenue | B31: =B29*Assumptions!B28 | C31: =C29*Assumptions!B28 | D31: =D29*Assumptions!B28 | E31: =E29*Assumptions!B28 | F31: =F29*Assumptions!B28 | G31: =G29*Assumptions!B28 | H31: =H29*Assumptions!B28 | I31: =I29*Assumptions!B28 | J31: =J29*Assumptions!B28 | K31: =K29*Assumptions!B28 | L31: =L29*Assumptions!B28 | M31: =M29*Assumptions!B28 | N31: =N29*Assumptions!B28 | O31: =O29*Assumptions!B28 | P31: =P29*Assumptions!B28 | Q31: =Q29*Assumptions!B28 | R31: =R29*Assumptions!B28 | S31: =S29*Assumptions!B28 | T31: =T29*Assumptions!B28 | U31: =U29*Assumptions!B28 | V31: =V29*Assumptions!B28 | W31: =W29*Assumptions!B28 | X31: =X29*Assumptions!B28 | Y31: =Y29*Assumptions!B28 | Z31: =SUM(B31:Y31)
A32: Doctor SaaS (D1: EUR 99/mo)
A33: Clinics listed | B33: ='Growth Curves'!B9 | C33: ='Growth Curves'!C9 | D33: ='Growth Curves'!D9 | E33: ='Growth Curves'!E9 | F33: ='Growth Curves'!F9 | G33: ='Growth Curves'!G9 | H33: ='Growth Curves'!H9 | I33: ='Growth Curves'!I9 | ... Y33: ='Growth Curves'!Y9 | Z33: =SUM(B33:Y33)
A34: Fee/month | B34: =Assumptions!B31 | C34: =Assumptions!B31 | D34: =Assumptions!B31 | E34: =Assumptions!B31 | F34: =Assumptions!B31 | G34: =Assumptions!B31 | H34: =Assumptions!B31 | I34: =Assumptions!B31 | J34: =Assumptions!B31 | K34: =Assumptions!B31 | L34: =Assumptions!B31 | M34: =Assumptions!B31 | N34: =Assumptions!B31 | O34: =Assumptions!B31 | P34: =Assumptions!B31 | Q34: =Assumptions!B31 | R34: =Assumptions!B31 | S34: =Assumptions!B31 | T34: =Assumptions!B31 | U34: =Assumptions!B31 | V34: =Assumptions!B31 | W34: =Assumptions!B31 | X34: =Assumptions!B31 | Y34: =Assumptions!B31 | Z34: =SUM(B34:Y34)
A35: Revenue | B35: =B33*Assumptions!B31 | C35: =C33*Assumptions!B31 | D35: =D33*Assumptions!B31 | E35: =E33*Assumptions!B31 | F35: =F33*Assumptions!B31 | G35: =G33*Assumptions!B31 | H35: =H33*Assumptions!B31 | I35: =I33*Assumptions!B31 | J35: =J33*Assumptions!B31 | K35: =K33*Assumptions!B31 | L35: =L33*Assumptions!B31 | M35: =M33*Assumptions!B31 | N35: =N33*Assumptions!B31 | O35: =O33*Assumptions!B31 | P35: =P33*Assumptions!B31 | Q35: =Q33*Assumptions!B31 | R35: =R33*Assumptions!B31 | S35: =S33*Assumptions!B31 | T35: =T33*Assumptions!B31 | U35: =U33*Assumptions!B31 | V35: =V33*Assumptions!B31 | W35: =W33*Assumptions!B31 | X35: =X33*Assumptions!B31 | Y35: =Y33*Assumptions!B31 | Z35: =SUM(B35:Y35)
A36: CGM Referral Commission (D3: EUR 15/user/mo — Premium 3-mo gate or add-on) | B36: =ROUND('Growth Curves'!B21*Assumptions!B140,0) | C36: =ROUND('Growth Curves'!C21*Assumptions!B140,0) | D36: =ROUND('Growth Curves'!D21*Assumptions!B140,0) | E36: =ROUND('Growth Curves'!E21*Assumptions!B140,0) | F36: =ROUND('Growth Curves'!F21*Assumptions!B140,0) | G36: =ROUND('Growth Curves'!G21*Assumptions!B140,0) | H36: =ROUND('Growth Curves'!H21*Assumptions!B140,0) | I36: =ROUND('Growth Curves'!I21*Assumptions!B140,0) | J36: =ROUND('Growth Curves'!J21*Assumptions!B140,0) | K36: =ROUND('Growth Curves'!K21*Assumptions!B140,0) | L36: =ROUND('Growth Curves'!L21*Assumptions!B140,0) | M36: =ROUND('Growth Curves'!M21*Assumptions!B140,0) | N36: =ROUND('Growth Curves'!N21*Assumptions!B140,0) | O36: =ROUND('Growth Curves'!O21*Assumptions!B140,0) | P36: =ROUND('Growth Curves'!P21*Assumptions!B140,0) | Q36: =ROUND('Growth Curves'!Q21*Assumptions!B140,0) | R36: =ROUND('Growth Curves'!R21*Assumptions!B140,0) | S36: =ROUND('Growth Curves'!S21*Assumptions!B140,0) | T36: =ROUND('Growth Curves'!T21*Assumptions!B140,0) | U36: =ROUND('Growth Curves'!U21*Assumptions!B140,0) | V36: =ROUND('Growth Curves'!V21*Assumptions!B140,0) | W36: =ROUND('Growth Curves'!W21*Assumptions!B140,0) | X36: =ROUND('Growth Curves'!X21*Assumptions!B140,0) | Y36: =ROUND('Growth Curves'!Y21*Assumptions!B140,0) | Z36: =SUM(B36:Y36)
A37: Restaurant (D2: Phase 2 — EUR 0) | B37: 0 | C37: 0 | D37: 0 | E37: 0 | F37: 0 | G37: 0 | H37: 0 | I37: 0 | J37: 0 | K37: 0 | L37: 0 | M37: 0 | N37: 0 | O37: 0 | P37: 0 | Q37: 0 | R37: 0 | S37: 0 | T37: 0 | U37: 0 | V37: 0 | W37: 0 | X37: 0 | Y37: 0 | Z37: =SUM(B37:Y37)
A38: Subscriptions (EX-01: blended monthly + annual recognition)
A39: Core (blended: monthly EUR 19 / annual EUR 190/yr) | B39: =ROUND('Growth Curves'!B18*((1-IF(1<=6,Assumptions!B131,IF(1<=11,Assumptions!B141,Assumptions!B132)))*Assumptions!B5+IF(1<=6,Assumptions!B131,IF(1<=11,Assumptions!B141,Assumptions!B132))*Assumptions!B128/12),0) | C39: =ROUND('Growth Curves'!C18*((1-IF(2<=6,Assumptions!B131,IF(2<=11,Assumptions!B141,Assumptions!B132)))*Assumptions!B5+IF(2<=6,Assumptions!B131,IF(2<=11,Assumptions!B141,Assumptions!B132))*Assumptions!B128/12),0) | D39: =ROUND('Growth Curves'!D18*((1-IF(3<=6,Assumptions!B131,IF(3<=11,Assumptions!B141,Assumptions!B132)))*Assumptions!B5+IF(3<=6,Assumptions!B131,IF(3<=11,Assumptions!B141,Assumptions!B132))*Assumptions!B128/12),0) | E39: =ROUND('Growth Curves'!E18*((1-IF(4<=6,Assumptions!B131,IF(4<=11,Assumptions!B141,Assumptions!B132)))*Assumptions!B5+IF(4<=6,Assumptions!B131,IF(4<=11,Assumptions!B141,Assumptions!B132))*Assumptions!B128/12),0) | F39: =ROUND('Growth Curves'!F18*((1-IF(5<=6,Assumptions!B131,IF(5<=11,Assumptions!B141,Assumptions!B132)))*Assumptions!B5+IF(5<=6,Assumptions!B131,IF(5<=11,Assumptions!B141,Assumptions!B132))*Assumptions!B128/12),0) | G39: =ROUND('Growth Curves'!G18*((1-IF(6<=6,Assumptions!B131,IF(6<=11,Assumptions!B141,Assumptions!B132)))*Assumptions!B5+IF(6<=6,Assumptions!B131,IF(6<=11,Assumptions!B141,Assumptions!B132))*Assumptions!B128/12),0) | H39: =ROUND('Growth Curves'!H18*((1-IF(7<=6,Assumptions!B131,IF(7<=11,Assumptions!B141,Assumptions!B132)))*Assumptions!B5+IF(7<=6,Assumptions!B131,IF(7<=11,Assumptions!B141,Assumptions!B132))*Assumptions!B128/12),0) | I39: =ROUND('Growth Curves'!I18*((1-IF(8<=6,Assumptions!B131,IF(8<=11,Assumptions!B141,Assumptions!B132)))*Assumptions!B5+IF(8<=6,Assumptions!B131,IF(8<=11,Assumptions!B141,Assumptions!B132))*Assumptions!B128/12),0) | J39: =ROUND('Growth Curves'!J18*((1-IF(9<=6,Assumptions!B131,IF(9<=11,Assumptions!B141,Assumptions!B132)))*Assumptions!B5+IF(9<=6,Assumptions!B131,IF(9<=11,Assumptions!B141,Assumptions!B132))*Assumptions!B128/12),0) | K39: =ROUND('Growth Curves'!K18*((1-IF(10<=6,Assumptions!B131,IF(10<=11,Assumptions!B141,Assumptions!B132)))*Assumptions!B5+IF(10<=6,Assumptions!B131,IF(10<=11,Assumptions!B141,Assumptions!B132))*Assumptions!B128/12),0) | L39: =ROUND('Growth Curves'!L18*((1-IF(11<=6,Assumptions!B131,IF(11<=11,Assumptions!B141,Assumptions!B132)))*Assumptions!B5+IF(11<=6,Assumptions!B131,IF(11<=11,Assumptions!B141,Assumptions!B132))*Assumptions!B128/12),0) | M39: =ROUND('Growth Curves'!M18*((1-IF(12<=6,Assumptions!B131,IF(12<=11,Assumptions!B141,Assumptions!B132)))*Assumptions!B5+IF(12<=6,Assumptions!B131,IF(12<=11,Assumptions!B141,Assumptions!B132))*Assumptions!B128/12),0) | N39: =ROUND('Growth Curves'!N18*((1-IF(13<=6,Assumptions!B131,IF(13<=11,Assumptions!B141,Assumptions!B132)))*Assumptions!B5+IF(13<=6,Assumptions!B131,IF(13<=11,Assumptions!B141,Assumptions!B132))*Assumptions!B128/12),0) | O39: =ROUND('Growth Curves'!O18*((1-IF(14<=6,Assumptions!B131,IF(14<=11,Assumptions!B141,Assumptions!B132)))*Assumptions!B5+IF(14<=6,Assumptions!B131,IF(14<=11,Assumptions!B141,Assumptions!B132))*Assumptions!B128/12),0) | P39: =ROUND('Growth Curves'!P18*((1-IF(15<=6,Assumptions!B131,IF(15<=11,Assumptions!B141,Assumptions!B132)))*Assumptions!B5+IF(15<=6,Assumptions!B131,IF(15<=11,Assumptions!B141,Assumptions!B132))*Assumptions!B128/12),0) | Q39: =ROUND('Growth Curves'!Q18*((1-IF(16<=6,Assumptions!B131,IF(16<=11,Assumptions!B141,Assumptions!B132)))*Assumptions!B5+IF(16<=6,Assumptions!B131,IF(16<=11,Assumptions!B141,Assumptions!B132))*Assumptions!B128/12),0) | R39: =ROUND('Growth Curves'!R18*((1-IF(17<=6,Assumptions!B131,IF(17<=11,Assumptions!B141,Assumptions!B132)))*Assumptions!B5+IF(17<=6,Assumptions!B131,IF(17<=11,Assumptions!B141,Assumptions!B132))*Assumptions!B128/12),0) | S39: =ROUND('Growth Curves'!S18*((1-IF(18<=6,Assumptions!B131,IF(18<=11,Assumptions!B141,Assumptions!B132)))*Assumptions!B5+IF(18<=6,Assumptions!B131,IF(18<=11,Assumptions!B141,Assumptions!B132))*Assumptions!B128/12),0) | T39: =ROUND('Growth Curves'!T18*((1-IF(19<=6,Assumptions!B131,IF(19<=11,Assumptions!B141,Assumptions!B132)))*Assumptions!B5+IF(19<=6,Assumptions!B131,IF(19<=11,Assumptions!B141,Assumptions!B132))*Assumptions!B128/12),0) | U39: =ROUND('Growth Curves'!U18*((1-IF(20<=6,Assumptions!B131,IF(20<=11,Assumptions!B141,Assumptions!B132)))*Assumptions!B5+IF(20<=6,Assumptions!B131,IF(20<=11,Assumptions!B141,Assumptions!B132))*Assumptions!B128/12),0) | V39: =ROUND('Growth Curves'!V18*((1-IF(21<=6,Assumptions!B131,IF(21<=11,Assumptions!B141,Assumptions!B132)))*Assumptions!B5+IF(21<=6,Assumptions!B131,IF(21<=11,Assumptions!B141,Assumptions!B132))*Assumptions!B128/12),0) | W39: =ROUND('Growth Curves'!W18*((1-IF(22<=6,Assumptions!B131,IF(22<=11,Assumptions!B141,Assumptions!B132)))*Assumptions!B5+IF(22<=6,Assumptions!B131,IF(22<=11,Assumptions!B141,Assumptions!B132))*Assumptions!B128/12),0) | X39: =ROUND('Growth Curves'!X18*((1-IF(23<=6,Assumptions!B131,IF(23<=11,Assumptions!B141,Assumptions!B132)))*Assumptions!B5+IF(23<=6,Assumptions!B131,IF(23<=11,Assumptions!B141,Assumptions!B132))*Assumptions!B128/12),0) | Y39: =ROUND('Growth Curves'!Y18*((1-IF(24<=6,Assumptions!B131,IF(24<=11,Assumptions!B141,Assumptions!B132)))*Assumptions!B5+IF(24<=6,Assumptions!B131,IF(24<=11,Assumptions!B141,Assumptions!B132))*Assumptions!B128/12),0) | Z39: =SUM(B39:Y39)
A40: Pro (blended: monthly EUR 49 / annual EUR 490/yr) | B40: =ROUND('Growth Curves'!B19*((1-IF(1<=6,Assumptions!B131,IF(1<=11,Assumptions!B141,Assumptions!B132)))*Assumptions!B6+IF(1<=6,Assumptions!B131,IF(1<=11,Assumptions!B141,Assumptions!B132))*Assumptions!B129/12),0) | C40: =ROUND('Growth Curves'!C19*((1-IF(2<=6,Assumptions!B131,IF(2<=11,Assumptions!B141,Assumptions!B132)))*Assumptions!B6+IF(2<=6,Assumptions!B131,IF(2<=11,Assumptions!B141,Assumptions!B132))*Assumptions!B129/12),0) | D40: =ROUND('Growth Curves'!D19*((1-IF(3<=6,Assumptions!B131,IF(3<=11,Assumptions!B141,Assumptions!B132)))*Assumptions!B6+IF(3<=6,Assumptions!B131,IF(3<=11,Assumptions!B141,Assumptions!B132))*Assumptions!B129/12),0) | E40: =ROUND('Growth Curves'!E19*((1-IF(4<=6,Assumptions!B131,IF(4<=11,Assumptions!B141,Assumptions!B132)))*Assumptions!B6+IF(4<=6,Assumptions!B131,IF(4<=11,Assumptions!B141,Assumptions!B132))*Assumptions!B129/12),0) | F40: =ROUND('Growth Curves'!F19*((1-IF(5<=6,Assumptions!B131,IF(5<=11,Assumptions!B141,Assumptions!B132)))*Assumptions!B6+IF(5<=6,Assumptions!B131,IF(5<=11,Assumptions!B141,Assumptions!B132))*Assumptions!B129/12),0) | G40: =ROUND('Growth Curves'!G19*((1-IF(6<=6,Assumptions!B131,IF(6<=11,Assumptions!B141,Assumptions!B132)))*Assumptions!B6+IF(6<=6,Assumptions!B131,IF(6<=11,Assumptions!B141,Assumptions!B132))*Assumptions!B129/12),0) | H40: =ROUND('Growth Curves'!H19*((1-IF(7<=6,Assumptions!B131,IF(7<=11,Assumptions!B141,Assumptions!B132)))*Assumptions!B6+IF(7<=6,Assumptions!B131,IF(7<=11,Assumptions!B141,Assumptions!B132))*Assumptions!B129/12),0) | I40: =ROUND('Growth Curves'!I19*((1-IF(8<=6,Assumptions!B131,IF(8<=11,Assumptions!B141,Assumptions!B132)))*Assumptions!B6+IF(8<=6,Assumptions!B131,IF(8<=11,Assumptions!B141,Assumptions!B132))*Assumptions!B129/12),0) | J40: =ROUND('Growth Curves'!J19*((1-IF(9<=6,Assumptions!B131,IF(9<=11,Assumptions!B141,Assumptions!B132)))*Assumptions!B6+IF(9<=6,Assumptions!B131,IF(9<=11,Assumptions!B141,Assumptions!B132))*Assumptions!B129/12),0) | K40: =ROUND('Growth Curves'!K19*((1-IF(10<=6,Assumptions!B131,IF(10<=11,Assumptions!B141,Assumptions!B132)))*Assumptions!B6+IF(10<=6,Assumptions!B131,IF(10<=11,Assumptions!B141,Assumptions!B132))*Assumptions!B129/12),0) | L40: =ROUND('Growth Curves'!L19*((1-IF(11<=6,Assumptions!B131,IF(11<=11,Assumptions!B141,Assumptions!B132)))*Assumptions!B6+IF(11<=6,Assumptions!B131,IF(11<=11,Assumptions!B141,Assumptions!B132))*Assumptions!B129/12),0) | M40: =ROUND('Growth Curves'!M19*((1-IF(12<=6,Assumptions!B131,IF(12<=11,Assumptions!B141,Assumptions!B132)))*Assumptions!B6+IF(12<=6,Assumptions!B131,IF(12<=11,Assumptions!B141,Assumptions!B132))*Assumptions!B129/12),0) | N40: =ROUND('Growth Curves'!N19*((1-IF(13<=6,Assumptions!B131,IF(13<=11,Assumptions!B141,Assumptions!B132)))*Assumptions!B6+IF(13<=6,Assumptions!B131,IF(13<=11,Assumptions!B141,Assumptions!B132))*Assumptions!B129/12),0) | O40: =ROUND('Growth Curves'!O19*((1-IF(14<=6,Assumptions!B131,IF(14<=11,Assumptions!B141,Assumptions!B132)))*Assumptions!B6+IF(14<=6,Assumptions!B131,IF(14<=11,Assumptions!B141,Assumptions!B132))*Assumptions!B129/12),0) | P40: =ROUND('Growth Curves'!P19*((1-IF(15<=6,Assumptions!B131,IF(15<=11,Assumptions!B141,Assumptions!B132)))*Assumptions!B6+IF(15<=6,Assumptions!B131,IF(15<=11,Assumptions!B141,Assumptions!B132))*Assumptions!B129/12),0) | Q40: =ROUND('Growth Curves'!Q19*((1-IF(16<=6,Assumptions!B131,IF(16<=11,Assumptions!B141,Assumptions!B132)))*Assumptions!B6+IF(16<=6,Assumptions!B131,IF(16<=11,Assumptions!B141,Assumptions!B132))*Assumptions!B129/12),0) | R40: =ROUND('Growth Curves'!R19*((1-IF(17<=6,Assumptions!B131,IF(17<=11,Assumptions!B141,Assumptions!B132)))*Assumptions!B6+IF(17<=6,Assumptions!B131,IF(17<=11,Assumptions!B141,Assumptions!B132))*Assumptions!B129/12),0) | S40: =ROUND('Growth Curves'!S19*((1-IF(18<=6,Assumptions!B131,IF(18<=11,Assumptions!B141,Assumptions!B132)))*Assumptions!B6+IF(18<=6,Assumptions!B131,IF(18<=11,Assumptions!B141,Assumptions!B132))*Assumptions!B129/12),0) | T40: =ROUND('Growth Curves'!T19*((1-IF(19<=6,Assumptions!B131,IF(19<=11,Assumptions!B141,Assumptions!B132)))*Assumptions!B6+IF(19<=6,Assumptions!B131,IF(19<=11,Assumptions!B141,Assumptions!B132))*Assumptions!B129/12),0) | U40: =ROUND('Growth Curves'!U19*((1-IF(20<=6,Assumptions!B131,IF(20<=11,Assumptions!B141,Assumptions!B132)))*Assumptions!B6+IF(20<=6,Assumptions!B131,IF(20<=11,Assumptions!B141,Assumptions!B132))*Assumptions!B129/12),0) | V40: =ROUND('Growth Curves'!V19*((1-IF(21<=6,Assumptions!B131,IF(21<=11,Assumptions!B141,Assumptions!B132)))*Assumptions!B6+IF(21<=6,Assumptions!B131,IF(21<=11,Assumptions!B141,Assumptions!B132))*Assumptions!B129/12),0) | W40: =ROUND('Growth Curves'!W19*((1-IF(22<=6,Assumptions!B131,IF(22<=11,Assumptions!B141,Assumptions!B132)))*Assumptions!B6+IF(22<=6,Assumptions!B131,IF(22<=11,Assumptions!B141,Assumptions!B132))*Assumptions!B129/12),0) | X40: =ROUND('Growth Curves'!X19*((1-IF(23<=6,Assumptions!B131,IF(23<=11,Assumptions!B141,Assumptions!B132)))*Assumptions!B6+IF(23<=6,Assumptions!B131,IF(23<=11,Assumptions!B141,Assumptions!B132))*Assumptions!B129/12),0) | Y40: =ROUND('Growth Curves'!Y19*((1-IF(24<=6,Assumptions!B131,IF(24<=11,Assumptions!B141,Assumptions!B132)))*Assumptions!B6+IF(24<=6,Assumptions!B131,IF(24<=11,Assumptions!B141,Assumptions!B132))*Assumptions!B129/12),0) | Z40: =SUM(B40:Y40)
A41: Premium (blended: monthly EUR 99 / annual EUR 990/yr) | B41: =ROUND('Growth Curves'!B20*((1-IF(1<=6,Assumptions!B131,IF(1<=11,Assumptions!B141,Assumptions!B132)))*Assumptions!B7+IF(1<=6,Assumptions!B131,IF(1<=11,Assumptions!B141,Assumptions!B132))*Assumptions!B130/12),0) | C41: =ROUND('Growth Curves'!C20*((1-IF(2<=6,Assumptions!B131,IF(2<=11,Assumptions!B141,Assumptions!B132)))*Assumptions!B7+IF(2<=6,Assumptions!B131,IF(2<=11,Assumptions!B141,Assumptions!B132))*Assumptions!B130/12),0) | D41: =ROUND('Growth Curves'!D20*((1-IF(3<=6,Assumptions!B131,IF(3<=11,Assumptions!B141,Assumptions!B132)))*Assumptions!B7+IF(3<=6,Assumptions!B131,IF(3<=11,Assumptions!B141,Assumptions!B132))*Assumptions!B130/12),0) | E41: =ROUND('Growth Curves'!E20*((1-IF(4<=6,Assumptions!B131,IF(4<=11,Assumptions!B141,Assumptions!B132)))*Assumptions!B7+IF(4<=6,Assumptions!B131,IF(4<=11,Assumptions!B141,Assumptions!B132))*Assumptions!B130/12),0) | F41: =ROUND('Growth Curves'!F20*((1-IF(5<=6,Assumptions!B131,IF(5<=11,Assumptions!B141,Assumptions!B132)))*Assumptions!B7+IF(5<=6,Assumptions!B131,IF(5<=11,Assumptions!B141,Assumptions!B132))*Assumptions!B130/12),0) | G41: =ROUND('Growth Curves'!G20*((1-IF(6<=6,Assumptions!B131,IF(6<=11,Assumptions!B141,Assumptions!B132)))*Assumptions!B7+IF(6<=6,Assumptions!B131,IF(6<=11,Assumptions!B141,Assumptions!B132))*Assumptions!B130/12),0) | H41: =ROUND('Growth Curves'!H20*((1-IF(7<=6,Assumptions!B131,IF(7<=11,Assumptions!B141,Assumptions!B132)))*Assumptions!B7+IF(7<=6,Assumptions!B131,IF(7<=11,Assumptions!B141,Assumptions!B132))*Assumptions!B130/12),0) | I41: =ROUND('Growth Curves'!I20*((1-IF(8<=6,Assumptions!B131,IF(8<=11,Assumptions!B141,Assumptions!B132)))*Assumptions!B7+IF(8<=6,Assumptions!B131,IF(8<=11,Assumptions!B141,Assumptions!B132))*Assumptions!B130/12),0) | J41: =ROUND('Growth Curves'!J20*((1-IF(9<=6,Assumptions!B131,IF(9<=11,Assumptions!B141,Assumptions!B132)))*Assumptions!B7+IF(9<=6,Assumptions!B131,IF(9<=11,Assumptions!B141,Assumptions!B132))*Assumptions!B130/12),0) | K41: =ROUND('Growth Curves'!K20*((1-IF(10<=6,Assumptions!B131,IF(10<=11,Assumptions!B141,Assumptions!B132)))*Assumptions!B7+IF(10<=6,Assumptions!B131,IF(10<=11,Assumptions!B141,Assumptions!B132))*Assumptions!B130/12),0) | L41: =ROUND('Growth Curves'!L20*((1-IF(11<=6,Assumptions!B131,IF(11<=11,Assumptions!B141,Assumptions!B132)))*Assumptions!B7+IF(11<=6,Assumptions!B131,IF(11<=11,Assumptions!B141,Assumptions!B132))*Assumptions!B130/12),0) | M41: =ROUND('Growth Curves'!M20*((1-IF(12<=6,Assumptions!B131,IF(12<=11,Assumptions!B141,Assumptions!B132)))*Assumptions!B7+IF(12<=6,Assumptions!B131,IF(12<=11,Assumptions!B141,Assumptions!B132))*Assumptions!B130/12),0) | N41: =ROUND('Growth Curves'!N20*((1-IF(13<=6,Assumptions!B131,IF(13<=11,Assumptions!B141,Assumptions!B132)))*Assumptions!B7+IF(13<=6,Assumptions!B131,IF(13<=11,Assumptions!B141,Assumptions!B132))*Assumptions!B130/12),0) | O41: =ROUND('Growth Curves'!O20*((1-IF(14<=6,Assumptions!B131,IF(14<=11,Assumptions!B141,Assumptions!B132)))*Assumptions!B7+IF(14<=6,Assumptions!B131,IF(14<=11,Assumptions!B141,Assumptions!B132))*Assumptions!B130/12),0) | P41: =ROUND('Growth Curves'!P20*((1-IF(15<=6,Assumptions!B131,IF(15<=11,Assumptions!B141,Assumptions!B132)))*Assumptions!B7+IF(15<=6,Assumptions!B131,IF(15<=11,Assumptions!B141,Assumptions!B132))*Assumptions!B130/12),0) | Q41: =ROUND('Growth Curves'!Q20*((1-IF(16<=6,Assumptions!B131,IF(16<=11,Assumptions!B141,Assumptions!B132)))*Assumptions!B7+IF(16<=6,Assumptions!B131,IF(16<=11,Assumptions!B141,Assumptions!B132))*Assumptions!B130/12),0) | R41: =ROUND('Growth Curves'!R20*((1-IF(17<=6,Assumptions!B131,IF(17<=11,Assumptions!B141,Assumptions!B132)))*Assumptions!B7+IF(17<=6,Assumptions!B131,IF(17<=11,Assumptions!B141,Assumptions!B132))*Assumptions!B130/12),0) | S41: =ROUND('Growth Curves'!S20*((1-IF(18<=6,Assumptions!B131,IF(18<=11,Assumptions!B141,Assumptions!B132)))*Assumptions!B7+IF(18<=6,Assumptions!B131,IF(18<=11,Assumptions!B141,Assumptions!B132))*Assumptions!B130/12),0) | T41: =ROUND('Growth Curves'!T20*((1-IF(19<=6,Assumptions!B131,IF(19<=11,Assumptions!B141,Assumptions!B132)))*Assumptions!B7+IF(19<=6,Assumptions!B131,IF(19<=11,Assumptions!B141,Assumptions!B132))*Assumptions!B130/12),0) | U41: =ROUND('Growth Curves'!U20*((1-IF(20<=6,Assumptions!B131,IF(20<=11,Assumptions!B141,Assumptions!B132)))*Assumptions!B7+IF(20<=6,Assumptions!B131,IF(20<=11,Assumptions!B141,Assumptions!B132))*Assumptions!B130/12),0) | V41: =ROUND('Growth Curves'!V20*((1-IF(21<=6,Assumptions!B131,IF(21<=11,Assumptions!B141,Assumptions!B132)))*Assumptions!B7+IF(21<=6,Assumptions!B131,IF(21<=11,Assumptions!B141,Assumptions!B132))*Assumptions!B130/12),0) | W41: =ROUND('Growth Curves'!W20*((1-IF(22<=6,Assumptions!B131,IF(22<=11,Assumptions!B141,Assumptions!B132)))*Assumptions!B7+IF(22<=6,Assumptions!B131,IF(22<=11,Assumptions!B141,Assumptions!B132))*Assumptions!B130/12),0) | X41: =ROUND('Growth Curves'!X20*((1-IF(23<=6,Assumptions!B131,IF(23<=11,Assumptions!B141,Assumptions!B132)))*Assumptions!B7+IF(23<=6,Assumptions!B131,IF(23<=11,Assumptions!B141,Assumptions!B132))*Assumptions!B130/12),0) | Y41: =ROUND('Growth Curves'!Y20*((1-IF(24<=6,Assumptions!B131,IF(24<=11,Assumptions!B141,Assumptions!B132)))*Assumptions!B7+IF(24<=6,Assumptions!B131,IF(24<=11,Assumptions!B141,Assumptions!B132))*Assumptions!B130/12),0) | Z41: =SUM(B41:Y41)
A42: Subscription MRR (recognized) | B42: =B39+B40+B41 | C42: =C39+C40+C41 | D42: =D39+D40+D41 | E42: =E39+E40+E41 | F42: =F39+F40+F41 | G42: =G39+G40+G41 | H42: =H39+H40+H41 | I42: =I39+I40+I41 | ... Y42: =Y39+Y40+Y41 | Z42: =SUM(B42:Y42)
A43: [INFO] Annual Cash Collected (upfront, not P&L revenue) | B43: =ROUND('Growth Curves'!B15*IF(1<=6,Assumptions!B131,IF(1<=11,Assumptions!B141,Assumptions!B132))*(Assumptions!B9*Assumptions!B128+Assumptions!B10*Assumptions!B129+Assumptions!B11*Assumptions!B130),0) | C43: =ROUND('Growth Curves'!C15*IF(2<=6,Assumptions!B131,IF(2<=11,Assumptions!B141,Assumptions!B132))*(Assumptions!B9*Assumptions!B128+Assumptions!B10*Assumptions!B129+Assumptions!B11*Assumptions!B130),0) | D43: =ROUND('Growth Curves'!D15*IF(3<=6,Assumptions!B131,IF(3<=11,Assumptions!B141,Assumptions!B132))*(Assumptions!B9*Assumptions!B128+Assumptions!B10*Assumptions!B129+Assumptions!B11*Assumptions!B130),0) | E43: =ROUND('Growth Curves'!E15*IF(4<=6,Assumptions!B131,IF(4<=11,Assumptions!B141,Assumptions!B132))*(Assumptions!B9*Assumptions!B128+Assumptions!B10*Assumptions!B129+Assumptions!B11*Assumptions!B130),0) | F43: =ROUND('Growth Curves'!F15*IF(5<=6,Assumptions!B131,IF(5<=11,Assumptions!B141,Assumptions!B132))*(Assumptions!B9*Assumptions!B128+Assumptions!B10*Assumptions!B129+Assumptions!B11*Assumptions!B130),0) | G43: =ROUND('Growth Curves'!G15*IF(6<=6,Assumptions!B131,IF(6<=11,Assumptions!B141,Assumptions!B132))*(Assumptions!B9*Assumptions!B128+Assumptions!B10*Assumptions!B129+Assumptions!B11*Assumptions!B130),0) | H43: =ROUND('Growth Curves'!H15*IF(7<=6,Assumptions!B131,IF(7<=11,Assumptions!B141,Assumptions!B132))*(Assumptions!B9*Assumptions!B128+Assumptions!B10*Assumptions!B129+Assumptions!B11*Assumptions!B130),0) | I43: =ROUND('Growth Curves'!I15*IF(8<=6,Assumptions!B131,IF(8<=11,Assumptions!B141,Assumptions!B132))*(Assumptions!B9*Assumptions!B128+Assumptions!B10*Assumptions!B129+Assumptions!B11*Assumptions!B130),0) | J43: =ROUND('Growth Curves'!J15*IF(9<=6,Assumptions!B131,IF(9<=11,Assumptions!B141,Assumptions!B132))*(Assumptions!B9*Assumptions!B128+Assumptions!B10*Assumptions!B129+Assumptions!B11*Assumptions!B130),0) | K43: =ROUND('Growth Curves'!K15*IF(10<=6,Assumptions!B131,IF(10<=11,Assumptions!B141,Assumptions!B132))*(Assumptions!B9*Assumptions!B128+Assumptions!B10*Assumptions!B129+Assumptions!B11*Assumptions!B130),0) | L43: =ROUND('Growth Curves'!L15*IF(11<=6,Assumptions!B131,IF(11<=11,Assumptions!B141,Assumptions!B132))*(Assumptions!B9*Assumptions!B128+Assumptions!B10*Assumptions!B129+Assumptions!B11*Assumptions!B130),0) | M43: =ROUND('Growth Curves'!M15*IF(12<=6,Assumptions!B131,IF(12<=11,Assumptions!B141,Assumptions!B132))*(Assumptions!B9*Assumptions!B128+Assumptions!B10*Assumptions!B129+Assumptions!B11*Assumptions!B130),0) | N43: =ROUND('Growth Curves'!N15*IF(13<=6,Assumptions!B131,IF(13<=11,Assumptions!B141,Assumptions!B132))*(Assumptions!B9*Assumptions!B128+Assumptions!B10*Assumptions!B129+Assumptions!B11*Assumptions!B130),0) | O43: =ROUND('Growth Curves'!O15*IF(14<=6,Assumptions!B131,IF(14<=11,Assumptions!B141,Assumptions!B132))*(Assumptions!B9*Assumptions!B128+Assumptions!B10*Assumptions!B129+Assumptions!B11*Assumptions!B130),0) | P43: =ROUND('Growth Curves'!P15*IF(15<=6,Assumptions!B131,IF(15<=11,Assumptions!B141,Assumptions!B132))*(Assumptions!B9*Assumptions!B128+Assumptions!B10*Assumptions!B129+Assumptions!B11*Assumptions!B130),0) | Q43: =ROUND('Growth Curves'!Q15*IF(16<=6,Assumptions!B131,IF(16<=11,Assumptions!B141,Assumptions!B132))*(Assumptions!B9*Assumptions!B128+Assumptions!B10*Assumptions!B129+Assumptions!B11*Assumptions!B130),0) | R43: =ROUND('Growth Curves'!R15*IF(17<=6,Assumptions!B131,IF(17<=11,Assumptions!B141,Assumptions!B132))*(Assumptions!B9*Assumptions!B128+Assumptions!B10*Assumptions!B129+Assumptions!B11*Assumptions!B130),0) | S43: =ROUND('Growth Curves'!S15*IF(18<=6,Assumptions!B131,IF(18<=11,Assumptions!B141,Assumptions!B132))*(Assumptions!B9*Assumptions!B128+Assumptions!B10*Assumptions!B129+Assumptions!B11*Assumptions!B130),0) | T43: =ROUND('Growth Curves'!T15*IF(19<=6,Assumptions!B131,IF(19<=11,Assumptions!B141,Assumptions!B132))*(Assumptions!B9*Assumptions!B128+Assumptions!B10*Assumptions!B129+Assumptions!B11*Assumptions!B130),0) | U43: =ROUND('Growth Curves'!U15*IF(20<=6,Assumptions!B131,IF(20<=11,Assumptions!B141,Assumptions!B132))*(Assumptions!B9*Assumptions!B128+Assumptions!B10*Assumptions!B129+Assumptions!B11*Assumptions!B130),0) | V43: =ROUND('Growth Curves'!V15*IF(21<=6,Assumptions!B131,IF(21<=11,Assumptions!B141,Assumptions!B132))*(Assumptions!B9*Assumptions!B128+Assumptions!B10*Assumptions!B129+Assumptions!B11*Assumptions!B130),0) | W43: =ROUND('Growth Curves'!W15*IF(22<=6,Assumptions!B131,IF(22<=11,Assumptions!B141,Assumptions!B132))*(Assumptions!B9*Assumptions!B128+Assumptions!B10*Assumptions!B129+Assumptions!B11*Assumptions!B130),0) | X43: =ROUND('Growth Curves'!X15*IF(23<=6,Assumptions!B131,IF(23<=11,Assumptions!B141,Assumptions!B132))*(Assumptions!B9*Assumptions!B128+Assumptions!B10*Assumptions!B129+Assumptions!B11*Assumptions!B130),0) | Y43: =ROUND('Growth Curves'!Y15*IF(24<=6,Assumptions!B131,IF(24<=11,Assumptions!B141,Assumptions!B132))*(Assumptions!B9*Assumptions!B128+Assumptions!B10*Assumptions!B129+Assumptions!B11*Assumptions!B130),0) | Z43: =SUM(B43:Y43)
A44: B2B Corporate Wellness (EX-02: BGM EUR 39/PEPM) | B44: =ROUND('Growth Curves'!B22*Assumptions!B133*Assumptions!B134,0) | C44: =ROUND('Growth Curves'!C22*Assumptions!B133*Assumptions!B134,0) | D44: =ROUND('Growth Curves'!D22*Assumptions!B133*Assumptions!B134,0) | E44: =ROUND('Growth Curves'!E22*Assumptions!B133*Assumptions!B134,0) | F44: =ROUND('Growth Curves'!F22*Assumptions!B133*Assumptions!B134,0) | G44: =ROUND('Growth Curves'!G22*Assumptions!B133*Assumptions!B134,0) | H44: =ROUND('Growth Curves'!H22*Assumptions!B133*Assumptions!B134,0) | I44: =ROUND('Growth Curves'!I22*Assumptions!B133*Assumptions!B134,0) | J44: =ROUND('Growth Curves'!J22*Assumptions!B133*Assumptions!B134,0) | K44: =ROUND('Growth Curves'!K22*Assumptions!B133*Assumptions!B134,0) | L44: =ROUND('Growth Curves'!L22*Assumptions!B133*Assumptions!B134,0) | M44: =ROUND('Growth Curves'!M22*Assumptions!B133*Assumptions!B134,0) | N44: =ROUND('Growth Curves'!N22*Assumptions!B133*Assumptions!B134,0) | O44: =ROUND('Growth Curves'!O22*Assumptions!B133*Assumptions!B134,0) | P44: =ROUND('Growth Curves'!P22*Assumptions!B133*Assumptions!B134,0) | Q44: =ROUND('Growth Curves'!Q22*Assumptions!B133*Assumptions!B134,0) | R44: =ROUND('Growth Curves'!R22*Assumptions!B133*Assumptions!B134,0) | S44: =ROUND('Growth Curves'!S22*Assumptions!B133*Assumptions!B134,0) | T44: =ROUND('Growth Curves'!T22*Assumptions!B133*Assumptions!B134,0) | U44: =ROUND('Growth Curves'!U22*Assumptions!B133*Assumptions!B134,0) | V44: =ROUND('Growth Curves'!V22*Assumptions!B133*Assumptions!B134,0) | W44: =ROUND('Growth Curves'!W22*Assumptions!B133*Assumptions!B134,0) | X44: =ROUND('Growth Curves'!X22*Assumptions!B133*Assumptions!B134,0) | Y44: =ROUND('Growth Curves'!Y22*Assumptions!B133*Assumptions!B134,0) | Z44: =SUM(B44:Y44)
A45: Gift Cards (EX-03: EUR 441/mo net, 10% breakage applied) | B45: =IF(1>=4,Assumptions!B135,0) | C45: =IF(2>=4,Assumptions!B135,0) | D45: =IF(3>=4,Assumptions!B135,0) | E45: =IF(4>=4,Assumptions!B135,0) | F45: =IF(5>=4,Assumptions!B135,0) | G45: =IF(6>=4,Assumptions!B135,0) | H45: =IF(7>=4,Assumptions!B135,0) | I45: =IF(8>=4,Assumptions!B135,0) | J45: =IF(9>=4,Assumptions!B135,0) | K45: =IF(10>=4,Assumptions!B135,0) | L45: =IF(11>=4,Assumptions!B135,0) | M45: =IF(12>=4,Assumptions!B135,0) | N45: =IF(13>=4,Assumptions!B135,0) | O45: =IF(14>=4,Assumptions!B135,0) | P45: =IF(15>=4,Assumptions!B135,0) | Q45: =IF(16>=4,Assumptions!B135,0) | R45: =IF(17>=4,Assumptions!B135,0) | S45: =IF(18>=4,Assumptions!B135,0) | T45: =IF(19>=4,Assumptions!B135,0) | U45: =IF(20>=4,Assumptions!B135,0) | V45: =IF(21>=4,Assumptions!B135,0) | W45: =IF(22>=4,Assumptions!B135,0) | X45: =IF(23>=4,Assumptions!B135,0) | Y45: =IF(24>=4,Assumptions!B135,0) | Z45: =SUM(B45:Y45)
A47: TOTAL INCOME | B47: =B17+B21+B25+B31+B35+B36+B42+B44+B45 | C47: =C17+C21+C25+C31+C35+C36+C42+C44+C45 | D47: =D17+D21+D25+D31+D35+D36+D42+D44+D45 | E47: =E17+E21+E25+E31+E35+E36+E42+E44+E45 | F47: =F17+F21+F25+F31+F35+F36+F42+F44+F45 | G47: =G17+G21+G25+G31+G35+G36+G42+G44+G45 | H47: =H17+H21+H25+H31+H35+H36+H42+H44+H45 | I47: =I17+I21+I25+I31+I35+I36+I42+I44+I45 | ... Y47: =Y17+Y21+Y25+Y31+Y35+Y36+Y42+Y44+Y45 | Z47: =SUM(B47:Y47)
A49: COST OF GOODS SOLD (COGS)
A50: Retail COGS
A51: Product cost (EUR 23.50/unit) | B51: =ROUND(B15*Assumptions!B23,0) | C51: =ROUND(C15*Assumptions!B23,0) | D51: =ROUND(D15*Assumptions!B23,0) | E51: =ROUND(E15*Assumptions!B23,0) | F51: =ROUND(F15*Assumptions!B23,0) | G51: =ROUND(G15*Assumptions!B23,0) | H51: =ROUND(H15*Assumptions!B23,0) | I51: =ROUND(I15*Assumptions!B23,0) | J51: =ROUND(J15*Assumptions!B23,0) | K51: =ROUND(K15*Assumptions!B23,0) | L51: =ROUND(L15*Assumptions!B23,0) | M51: =ROUND(M15*Assumptions!B23,0) | N51: =ROUND(N15*Assumptions!B23,0) | O51: =ROUND(O15*Assumptions!B23,0) | P51: =ROUND(P15*Assumptions!B23,0) | Q51: =ROUND(Q15*Assumptions!B23,0) | R51: =ROUND(R15*Assumptions!B23,0) | S51: =ROUND(S15*Assumptions!B23,0) | T51: =ROUND(T15*Assumptions!B23,0) | U51: =ROUND(U15*Assumptions!B23,0) | V51: =ROUND(V15*Assumptions!B23,0) | W51: =ROUND(W15*Assumptions!B23,0) | X51: =ROUND(X15*Assumptions!B23,0) | Y51: =ROUND(Y15*Assumptions!B23,0) | Z51: =SUM(B51:Y51)
A52: Waste/spoilage (5.5%) | B52: =ROUND(B17*Assumptions!B36,0) | C52: =ROUND(C17*Assumptions!B36,0) | D52: =ROUND(D17*Assumptions!B36,0) | E52: =ROUND(E17*Assumptions!B36,0) | F52: =ROUND(F17*Assumptions!B36,0) | G52: =ROUND(G17*Assumptions!B36,0) | H52: =ROUND(H17*Assumptions!B36,0) | I52: =ROUND(I17*Assumptions!B36,0) | J52: =ROUND(J17*Assumptions!B36,0) | K52: =ROUND(K17*Assumptions!B36,0) | L52: =ROUND(L17*Assumptions!B36,0) | M52: =ROUND(M17*Assumptions!B36,0) | N52: =ROUND(N17*Assumptions!B36,0) | O52: =ROUND(O17*Assumptions!B36,0) | P52: =ROUND(P17*Assumptions!B36,0) | Q52: =ROUND(Q17*Assumptions!B36,0) | R52: =ROUND(R17*Assumptions!B36,0) | S52: =ROUND(S17*Assumptions!B36,0) | T52: =ROUND(T17*Assumptions!B36,0) | U52: =ROUND(U17*Assumptions!B36,0) | V52: =ROUND(V17*Assumptions!B36,0) | W52: =ROUND(W17*Assumptions!B36,0) | X52: =ROUND(X17*Assumptions!B36,0) | Y52: =ROUND(Y17*Assumptions!B36,0) | Z52: =SUM(B52:Y52)
A53: 3PL fulfillment (EUR 2.50/unit) | B53: =IF(1>=4,ROUND(B15*Assumptions!B37,0),0) | C53: =IF(2>=4,ROUND(C15*Assumptions!B37,0),0) | D53: =IF(3>=4,ROUND(D15*Assumptions!B37,0),0) | E53: =IF(4>=4,ROUND(E15*Assumptions!B37,0),0) | F53: =IF(5>=4,ROUND(F15*Assumptions!B37,0),0) | G53: =IF(6>=4,ROUND(G15*Assumptions!B37,0),0) | H53: =IF(7>=4,ROUND(H15*Assumptions!B37,0),0) | I53: =IF(8>=4,ROUND(I15*Assumptions!B37,0),0) | J53: =IF(9>=4,ROUND(J15*Assumptions!B37,0),0) | K53: =IF(10>=4,ROUND(K15*Assumptions!B37,0),0) | L53: =IF(11>=4,ROUND(L15*Assumptions!B37,0),0) | M53: =IF(12>=4,ROUND(M15*Assumptions!B37,0),0) | N53: =IF(13>=4,ROUND(N15*Assumptions!B37,0),0) | O53: =IF(14>=4,ROUND(O15*Assumptions!B37,0),0) | P53: =IF(15>=4,ROUND(P15*Assumptions!B37,0),0) | Q53: =IF(16>=4,ROUND(Q15*Assumptions!B37,0),0) | R53: =IF(17>=4,ROUND(R15*Assumptions!B37,0),0) | S53: =IF(18>=4,ROUND(S15*Assumptions!B37,0),0) | T53: =IF(19>=4,ROUND(T15*Assumptions!B37,0),0) | U53: =IF(20>=4,ROUND(U15*Assumptions!B37,0),0) | V53: =IF(21>=4,ROUND(V15*Assumptions!B37,0),0) | W53: =IF(22>=4,ROUND(W15*Assumptions!B37,0),0) | X53: =IF(23>=4,ROUND(X15*Assumptions!B37,0),0) | Y53: =IF(24>=4,ROUND(Y15*Assumptions!B37,0),0) | Z53: =SUM(B53:Y53)
A54: LED COGS (free — no practitioner) | B54: =ROUND(B19*Assumptions!B25,0) | C54: =ROUND(C19*Assumptions!B25,0) | D54: =ROUND(D19*Assumptions!B25,0) | E54: =ROUND(E19*Assumptions!B25,0) | F54: =ROUND(F19*Assumptions!B25,0) | G54: =ROUND(G19*Assumptions!B25,0) | H54: =ROUND(H19*Assumptions!B25,0) | I54: =ROUND(I19*Assumptions!B25,0) | J54: =ROUND(J19*Assumptions!B25,0) | K54: =ROUND(K19*Assumptions!B25,0) | L54: =ROUND(L19*Assumptions!B25,0) | M54: =ROUND(M19*Assumptions!B25,0) | N54: =ROUND(N19*Assumptions!B25,0) | O54: =ROUND(O19*Assumptions!B25,0) | P54: =ROUND(P19*Assumptions!B25,0) | Q54: =ROUND(Q19*Assumptions!B25,0) | R54: =ROUND(R19*Assumptions!B25,0) | S54: =ROUND(S19*Assumptions!B25,0) | T54: =ROUND(T19*Assumptions!B25,0) | U54: =ROUND(U19*Assumptions!B25,0) | V54: =ROUND(V19*Assumptions!B25,0) | W54: =ROUND(W19*Assumptions!B25,0) | X54: =ROUND(X19*Assumptions!B25,0) | Y54: =ROUND(Y19*Assumptions!B25,0) | Z54: =SUM(B54:Y54)
A55: Smoothie Bar COGS
A56: Ingredients + packaging (35%) | B56: =ROUND(B25*Assumptions!B27,0) | C56: =ROUND(C25*Assumptions!B27,0) | D56: =ROUND(D25*Assumptions!B27,0) | E56: =ROUND(E25*Assumptions!B27,0) | F56: =ROUND(F25*Assumptions!B27,0) | G56: =ROUND(G25*Assumptions!B27,0) | H56: =ROUND(H25*Assumptions!B27,0) | I56: =ROUND(I25*Assumptions!B27,0) | J56: =ROUND(J25*Assumptions!B27,0) | K56: =ROUND(K25*Assumptions!B27,0) | L56: =ROUND(L25*Assumptions!B27,0) | M56: =ROUND(M25*Assumptions!B27,0) | N56: =ROUND(N25*Assumptions!B27,0) | O56: =ROUND(O25*Assumptions!B27,0) | P56: =ROUND(P25*Assumptions!B27,0) | Q56: =ROUND(Q25*Assumptions!B27,0) | R56: =ROUND(R25*Assumptions!B27,0) | S56: =ROUND(S25*Assumptions!B27,0) | T56: =ROUND(T25*Assumptions!B27,0) | U56: =ROUND(U25*Assumptions!B27,0) | V56: =ROUND(V25*Assumptions!B27,0) | W56: =ROUND(W25*Assumptions!B27,0) | X56: =ROUND(X25*Assumptions!B27,0) | Y56: =ROUND(Y25*Assumptions!B27,0) | Z56: =SUM(B56:Y56)
A57: Events & Ticketing | B57: =ROUND(B27*Assumptions!B29+B31*Assumptions!B30,0) | C57: =ROUND(C27*Assumptions!B29+C31*Assumptions!B30,0) | D57: =ROUND(D27*Assumptions!B29+D31*Assumptions!B30,0) | E57: =ROUND(E27*Assumptions!B29+E31*Assumptions!B30,0) | F57: =ROUND(F27*Assumptions!B29+F31*Assumptions!B30,0) | G57: =ROUND(G27*Assumptions!B29+G31*Assumptions!B30,0) | H57: =ROUND(H27*Assumptions!B29+H31*Assumptions!B30,0) | I57: =ROUND(I27*Assumptions!B29+I31*Assumptions!B30,0) | J57: =ROUND(J27*Assumptions!B29+J31*Assumptions!B30,0) | K57: =ROUND(K27*Assumptions!B29+K31*Assumptions!B30,0) | L57: =ROUND(L27*Assumptions!B29+L31*Assumptions!B30,0) | M57: =ROUND(M27*Assumptions!B29+M31*Assumptions!B30,0) | N57: =ROUND(N27*Assumptions!B29+N31*Assumptions!B30,0) | O57: =ROUND(O27*Assumptions!B29+O31*Assumptions!B30,0) | P57: =ROUND(P27*Assumptions!B29+P31*Assumptions!B30,0) | Q57: =ROUND(Q27*Assumptions!B29+Q31*Assumptions!B30,0) | R57: =ROUND(R27*Assumptions!B29+R31*Assumptions!B30,0) | S57: =ROUND(S27*Assumptions!B29+S31*Assumptions!B30,0) | T57: =ROUND(T27*Assumptions!B29+T31*Assumptions!B30,0) | U57: =ROUND(U27*Assumptions!B29+U31*Assumptions!B30,0) | V57: =ROUND(V27*Assumptions!B29+V31*Assumptions!B30,0) | W57: =ROUND(W27*Assumptions!B29+W31*Assumptions!B30,0) | X57: =ROUND(X27*Assumptions!B29+X31*Assumptions!B30,0) | Y57: =ROUND(Y27*Assumptions!B29+Y31*Assumptions!B30,0) | Z57: =SUM(B57:Y57)
A58: Doctor Verification (EUR 25/new) | B58: =ROUND('Growth Curves'!B12*Assumptions!B32,0) | C58: =ROUND('Growth Curves'!C12*Assumptions!B32,0) | D58: =ROUND('Growth Curves'!D12*Assumptions!B32,0) | E58: =ROUND('Growth Curves'!E12*Assumptions!B32,0) | F58: =ROUND('Growth Curves'!F12*Assumptions!B32,0) | G58: =ROUND('Growth Curves'!G12*Assumptions!B32,0) | H58: =ROUND('Growth Curves'!H12*Assumptions!B32,0) | I58: =ROUND('Growth Curves'!I12*Assumptions!B32,0) | J58: =ROUND('Growth Curves'!J12*Assumptions!B32,0) | K58: =ROUND('Growth Curves'!K12*Assumptions!B32,0) | L58: =ROUND('Growth Curves'!L12*Assumptions!B32,0) | M58: =ROUND('Growth Curves'!M12*Assumptions!B32,0) | N58: =ROUND('Growth Curves'!N12*Assumptions!B32,0) | O58: =ROUND('Growth Curves'!O12*Assumptions!B32,0) | P58: =ROUND('Growth Curves'!P12*Assumptions!B32,0) | Q58: =ROUND('Growth Curves'!Q12*Assumptions!B32,0) | R58: =ROUND('Growth Curves'!R12*Assumptions!B32,0) | S58: =ROUND('Growth Curves'!S12*Assumptions!B32,0) | T58: =ROUND('Growth Curves'!T12*Assumptions!B32,0) | U58: =ROUND('Growth Curves'!U12*Assumptions!B32,0) | V58: =ROUND('Growth Curves'!V12*Assumptions!B32,0) | W58: =ROUND('Growth Curves'!W12*Assumptions!B32,0) | X58: =ROUND('Growth Curves'!X12*Assumptions!B32,0) | Y58: =ROUND('Growth Curves'!Y12*Assumptions!B32,0) | Z58: =SUM(B58:Y58)
A59: AI API — User-Facing (EUR 0.35/sub) | B59: =ROUND('Growth Curves'!B17*Assumptions!B39,0) | C59: =ROUND('Growth Curves'!C17*Assumptions!B39,0) | D59: =ROUND('Growth Curves'!D17*Assumptions!B39,0) | E59: =ROUND('Growth Curves'!E17*Assumptions!B39,0) | F59: =ROUND('Growth Curves'!F17*Assumptions!B39,0) | G59: =ROUND('Growth Curves'!G17*Assumptions!B39,0) | H59: =ROUND('Growth Curves'!H17*Assumptions!B39,0) | I59: =ROUND('Growth Curves'!I17*Assumptions!B39,0) | J59: =ROUND('Growth Curves'!J17*Assumptions!B39,0) | K59: =ROUND('Growth Curves'!K17*Assumptions!B39,0) | L59: =ROUND('Growth Curves'!L17*Assumptions!B39,0) | M59: =ROUND('Growth Curves'!M17*Assumptions!B39,0) | N59: =ROUND('Growth Curves'!N17*Assumptions!B39,0) | O59: =ROUND('Growth Curves'!O17*Assumptions!B39,0) | P59: =ROUND('Growth Curves'!P17*Assumptions!B39,0) | Q59: =ROUND('Growth Curves'!Q17*Assumptions!B39,0) | R59: =ROUND('Growth Curves'!R17*Assumptions!B39,0) | S59: =ROUND('Growth Curves'!S17*Assumptions!B39,0) | T59: =ROUND('Growth Curves'!T17*Assumptions!B39,0) | U59: =ROUND('Growth Curves'!U17*Assumptions!B39,0) | V59: =ROUND('Growth Curves'!V17*Assumptions!B39,0) | W59: =ROUND('Growth Curves'!W17*Assumptions!B39,0) | X59: =ROUND('Growth Curves'!X17*Assumptions!B39,0) | Y59: =ROUND('Growth Curves'!Y17*Assumptions!B39,0) | Z59: =SUM(B59:Y59)
A60: Refund/Returns Reserve (1.5%) | B60: =ROUND((B17+B25+B31)*Assumptions!B40,0) | C60: =ROUND((C17+C25+C31)*Assumptions!B40,0) | D60: =ROUND((D17+D25+D31)*Assumptions!B40,0) | E60: =ROUND((E17+E25+E31)*Assumptions!B40,0) | F60: =ROUND((F17+F25+F31)*Assumptions!B40,0) | G60: =ROUND((G17+G25+G31)*Assumptions!B40,0) | H60: =ROUND((H17+H25+H31)*Assumptions!B40,0) | I60: =ROUND((I17+I25+I31)*Assumptions!B40,0) | J60: =ROUND((J17+J25+J31)*Assumptions!B40,0) | K60: =ROUND((K17+K25+K31)*Assumptions!B40,0) | L60: =ROUND((L17+L25+L31)*Assumptions!B40,0) | M60: =ROUND((M17+M25+M31)*Assumptions!B40,0) | N60: =ROUND((N17+N25+N31)*Assumptions!B40,0) | O60: =ROUND((O17+O25+O31)*Assumptions!B40,0) | P60: =ROUND((P17+P25+P31)*Assumptions!B40,0) | Q60: =ROUND((Q17+Q25+Q31)*Assumptions!B40,0) | R60: =ROUND((R17+R25+R31)*Assumptions!B40,0) | S60: =ROUND((S17+S25+S31)*Assumptions!B40,0) | T60: =ROUND((T17+T25+T31)*Assumptions!B40,0) | U60: =ROUND((U17+U25+U31)*Assumptions!B40,0) | V60: =ROUND((V17+V25+V31)*Assumptions!B40,0) | W60: =ROUND((W17+W25+W31)*Assumptions!B40,0) | X60: =ROUND((X17+X25+X31)*Assumptions!B40,0) | Y60: =ROUND((Y17+Y25+Y31)*Assumptions!B40,0) | Z60: =SUM(B60:Y60)
A61: Bad Debt Provision (0.5%) | B61: =ROUND(B47*Assumptions!B41,0) | C61: =ROUND(C47*Assumptions!B41,0) | D61: =ROUND(D47*Assumptions!B41,0) | E61: =ROUND(E47*Assumptions!B41,0) | F61: =ROUND(F47*Assumptions!B41,0) | G61: =ROUND(G47*Assumptions!B41,0) | H61: =ROUND(H47*Assumptions!B41,0) | I61: =ROUND(I47*Assumptions!B41,0) | J61: =ROUND(J47*Assumptions!B41,0) | K61: =ROUND(K47*Assumptions!B41,0) | L61: =ROUND(L47*Assumptions!B41,0) | M61: =ROUND(M47*Assumptions!B41,0) | N61: =ROUND(N47*Assumptions!B41,0) | O61: =ROUND(O47*Assumptions!B41,0) | P61: =ROUND(P47*Assumptions!B41,0) | Q61: =ROUND(Q47*Assumptions!B41,0) | R61: =ROUND(R47*Assumptions!B41,0) | S61: =ROUND(S47*Assumptions!B41,0) | T61: =ROUND(T47*Assumptions!B41,0) | U61: =ROUND(U47*Assumptions!B41,0) | V61: =ROUND(V47*Assumptions!B41,0) | W61: =ROUND(W47*Assumptions!B41,0) | X61: =ROUND(X47*Assumptions!B41,0) | Y61: =ROUND(Y47*Assumptions!B41,0) | Z61: =SUM(B61:Y61)
A62: Stripe Processing (2.9%) | B62: =ROUND(B47*Assumptions!B38,0) | C62: =ROUND(C47*Assumptions!B38,0) | D62: =ROUND(D47*Assumptions!B38,0) | E62: =ROUND(E47*Assumptions!B38,0) | F62: =ROUND(F47*Assumptions!B38,0) | G62: =ROUND(G47*Assumptions!B38,0) | H62: =ROUND(H47*Assumptions!B38,0) | I62: =ROUND(I47*Assumptions!B38,0) | J62: =ROUND(J47*Assumptions!B38,0) | K62: =ROUND(K47*Assumptions!B38,0) | L62: =ROUND(L47*Assumptions!B38,0) | M62: =ROUND(M47*Assumptions!B38,0) | N62: =ROUND(N47*Assumptions!B38,0) | O62: =ROUND(O47*Assumptions!B38,0) | P62: =ROUND(P47*Assumptions!B38,0) | Q62: =ROUND(Q47*Assumptions!B38,0) | R62: =ROUND(R47*Assumptions!B38,0) | S62: =ROUND(S47*Assumptions!B38,0) | T62: =ROUND(T47*Assumptions!B38,0) | U62: =ROUND(U47*Assumptions!B38,0) | V62: =ROUND(V47*Assumptions!B38,0) | W62: =ROUND(W47*Assumptions!B38,0) | X62: =ROUND(X47*Assumptions!B38,0) | Y62: =ROUND(Y47*Assumptions!B38,0) | Z62: =SUM(B62:Y62)
A64: TOTAL COGS | B64: =B51+B52+B53+B54+B56+B57+B58+B59+B60+B61+B62 | C64: =C51+C52+C53+C54+C56+C57+C58+C59+C60+C61+C62 | D64: =D51+D52+D53+D54+D56+D57+D58+D59+D60+D61+D62 | E64: =E51+E52+E53+E54+E56+E57+E58+E59+E60+E61+E62 | F64: =F51+F52+F53+F54+F56+F57+F58+F59+F60+F61+F62 | G64: =G51+G52+G53+G54+G56+G57+G58+G59+G60+G61+G62 | H64: =H51+H52+H53+H54+H56+H57+H58+H59+H60+H61+H62 | I64: =I51+I52+I53+I54+I56+I57+I58+I59+I60+I61+I62 | ... Y64: =Y51+Y52+Y53+Y54+Y56+Y57+Y58+Y59+Y60+Y61+Y62 | Z64: =SUM(B64:Y64)
A66: GROSS PROFIT | B66: =B47-B64 | C66: =C47-C64 | D66: =D47-D64 | E66: =E47-E64 | F66: =F47-F64 | G66: =G47-G64 | H66: =H47-H64 | I66: =I47-I64 | ... Y66: =Y47-Y64 | Z66: =SUM(B66:Y66)
A67: Gross Margin % | B67: =IF(B47>0,B66/B47,0) | C67: =IF(C47>0,C66/C47,0) | D67: =IF(D47>0,D66/D47,0) | E67: =IF(E47>0,E66/E47,0) | F67: =IF(F47>0,F66/F47,0) | G67: =IF(G47>0,G66/G47,0) | H67: =IF(H47>0,H66/H47,0) | I67: =IF(I47>0,I66/I47,0) | ... Z67: =IF(Z47>0,Z66/Z47,0)
A69: OPERATING EXPENSES
A70: Payroll
A71: Timu (CEO) | B71: =ROUND(Assumptions!B44*Assumptions!B45,0) | C71: =ROUND(Assumptions!B44*Assumptions!B45,0) | D71: =ROUND(Assumptions!B44*Assumptions!B45,0) | E71: =ROUND(Assumptions!B44*Assumptions!B45,0) | F71: =ROUND(Assumptions!B44*Assumptions!B45,0) | G71: =ROUND(Assumptions!B44*Assumptions!B45,0) | H71: =ROUND(Assumptions!B44*Assumptions!B45,0) | I71: =ROUND(Assumptions!B44*Assumptions!B45,0) | J71: =ROUND(Assumptions!B44*Assumptions!B45,0) | K71: =ROUND(Assumptions!B44*Assumptions!B45,0) | L71: =ROUND(Assumptions!B44*Assumptions!B45,0) | M71: =ROUND(Assumptions!B44*Assumptions!B45,0) | N71: =ROUND(Assumptions!B44*Assumptions!B45,0) | O71: =ROUND(Assumptions!B44*Assumptions!B45,0) | P71: =ROUND(Assumptions!B44*Assumptions!B45,0) | Q71: =ROUND(Assumptions!B44*Assumptions!B45,0) | R71: =ROUND(Assumptions!B44*Assumptions!B45,0) | S71: =ROUND(Assumptions!B44*Assumptions!B45,0) | T71: =ROUND(Assumptions!B44*Assumptions!B45,0) | U71: =ROUND(Assumptions!B44*Assumptions!B45,0) | V71: =ROUND(Assumptions!B44*Assumptions!B45,0) | W71: =ROUND(Assumptions!B44*Assumptions!B45,0) | X71: =ROUND(Assumptions!B44*Assumptions!B45,0) | Y71: =ROUND(Assumptions!B44*Assumptions!B45,0) | Z71: =SUM(B71:Y71)
A72: Daria (COO) | B72: =ROUND(Assumptions!B44*Assumptions!B45,0) | C72: =ROUND(Assumptions!B44*Assumptions!B45,0) | D72: =ROUND(Assumptions!B44*Assumptions!B45,0) | E72: =ROUND(Assumptions!B44*Assumptions!B45,0) | F72: =ROUND(Assumptions!B44*Assumptions!B45,0) | G72: =ROUND(Assumptions!B44*Assumptions!B45,0) | H72: =ROUND(Assumptions!B44*Assumptions!B45,0) | I72: =ROUND(Assumptions!B44*Assumptions!B45,0) | J72: =ROUND(Assumptions!B44*Assumptions!B45,0) | K72: =ROUND(Assumptions!B44*Assumptions!B45,0) | L72: =ROUND(Assumptions!B44*Assumptions!B45,0) | M72: =ROUND(Assumptions!B44*Assumptions!B45,0) | N72: =ROUND(Assumptions!B44*Assumptions!B45,0) | O72: =ROUND(Assumptions!B44*Assumptions!B45,0) | P72: =ROUND(Assumptions!B44*Assumptions!B45,0) | Q72: =ROUND(Assumptions!B44*Assumptions!B45,0) | R72: =ROUND(Assumptions!B44*Assumptions!B45,0) | S72: =ROUND(Assumptions!B44*Assumptions!B45,0) | T72: =ROUND(Assumptions!B44*Assumptions!B45,0) | U72: =ROUND(Assumptions!B44*Assumptions!B45,0) | V72: =ROUND(Assumptions!B44*Assumptions!B45,0) | W72: =ROUND(Assumptions!B44*Assumptions!B45,0) | X72: =ROUND(Assumptions!B44*Assumptions!B45,0) | Y72: =ROUND(Assumptions!B44*Assumptions!B45,0) | Z72: =SUM(B72:Y72)
A73: Space Staff (M4+) | B73: =IF(1>=4,ROUND(Assumptions!B46*Assumptions!B45,0),0) | C73: =IF(2>=4,ROUND(Assumptions!B46*Assumptions!B45,0),0) | D73: =IF(3>=4,ROUND(Assumptions!B46*Assumptions!B45,0),0) | E73: =IF(4>=4,ROUND(Assumptions!B46*Assumptions!B45,0),0) | F73: =IF(5>=4,ROUND(Assumptions!B46*Assumptions!B45,0),0) | G73: =IF(6>=4,ROUND(Assumptions!B46*Assumptions!B45,0),0) | H73: =IF(7>=4,ROUND(Assumptions!B46*Assumptions!B45,0),0) | I73: =IF(8>=4,ROUND(Assumptions!B46*Assumptions!B45,0),0) | J73: =IF(9>=4,ROUND(Assumptions!B46*Assumptions!B45,0),0) | K73: =IF(10>=4,ROUND(Assumptions!B46*Assumptions!B45,0),0) | L73: =IF(11>=4,ROUND(Assumptions!B46*Assumptions!B45,0),0) | M73: =IF(12>=4,ROUND(Assumptions!B46*Assumptions!B45,0),0) | N73: =IF(13>=4,ROUND(Assumptions!B46*Assumptions!B45,0),0) | O73: =IF(14>=4,ROUND(Assumptions!B46*Assumptions!B45,0),0) | P73: =IF(15>=4,ROUND(Assumptions!B46*Assumptions!B45,0),0) | Q73: =IF(16>=4,ROUND(Assumptions!B46*Assumptions!B45,0),0) | R73: =IF(17>=4,ROUND(Assumptions!B46*Assumptions!B45,0),0) | S73: =IF(18>=4,ROUND(Assumptions!B46*Assumptions!B45,0),0) | T73: =IF(19>=4,ROUND(Assumptions!B46*Assumptions!B45,0),0) | U73: =IF(20>=4,ROUND(Assumptions!B46*Assumptions!B45,0),0) | V73: =IF(21>=4,ROUND(Assumptions!B46*Assumptions!B45,0),0) | W73: =IF(22>=4,ROUND(Assumptions!B46*Assumptions!B45,0),0) | X73: =IF(23>=4,ROUND(Assumptions!B46*Assumptions!B45,0),0) | Y73: =IF(24>=4,ROUND(Assumptions!B46*Assumptions!B45,0),0) | Z73: =SUM(B73:Y73)
A74: Partner Mgr (M6+) | B74: =IF(1>=6,ROUND(Assumptions!B47*Assumptions!B45,0),0) | C74: =IF(2>=6,ROUND(Assumptions!B47*Assumptions!B45,0),0) | D74: =IF(3>=6,ROUND(Assumptions!B47*Assumptions!B45,0),0) | E74: =IF(4>=6,ROUND(Assumptions!B47*Assumptions!B45,0),0) | F74: =IF(5>=6,ROUND(Assumptions!B47*Assumptions!B45,0),0) | G74: =IF(6>=6,ROUND(Assumptions!B47*Assumptions!B45,0),0) | H74: =IF(7>=6,ROUND(Assumptions!B47*Assumptions!B45,0),0) | I74: =IF(8>=6,ROUND(Assumptions!B47*Assumptions!B45,0),0) | J74: =IF(9>=6,ROUND(Assumptions!B47*Assumptions!B45,0),0) | K74: =IF(10>=6,ROUND(Assumptions!B47*Assumptions!B45,0),0) | L74: =IF(11>=6,ROUND(Assumptions!B47*Assumptions!B45,0),0) | M74: =IF(12>=6,ROUND(Assumptions!B47*Assumptions!B45,0),0) | N74: =IF(13>=6,ROUND(Assumptions!B47*Assumptions!B45,0),0) | O74: =IF(14>=6,ROUND(Assumptions!B47*Assumptions!B45,0),0) | P74: =IF(15>=6,ROUND(Assumptions!B47*Assumptions!B45,0),0) | Q74: =IF(16>=6,ROUND(Assumptions!B47*Assumptions!B45,0),0) | R74: =IF(17>=6,ROUND(Assumptions!B47*Assumptions!B45,0),0) | S74: =IF(18>=6,ROUND(Assumptions!B47*Assumptions!B45,0),0) | T74: =IF(19>=6,ROUND(Assumptions!B47*Assumptions!B45,0),0) | U74: =IF(20>=6,ROUND(Assumptions!B47*Assumptions!B45,0),0) | V74: =IF(21>=6,ROUND(Assumptions!B47*Assumptions!B45,0),0) | W74: =IF(22>=6,ROUND(Assumptions!B47*Assumptions!B45,0),0) | X74: =IF(23>=6,ROUND(Assumptions!B47*Assumptions!B45,0),0) | Y74: =IF(24>=6,ROUND(Assumptions!B47*Assumptions!B45,0),0) | Z74: =SUM(B74:Y74)
A75: CTO (M18+) | B75: =IF(1>=18,ROUND(Assumptions!B48*Assumptions!B45,0),0) | C75: =IF(2>=18,ROUND(Assumptions!B48*Assumptions!B45,0),0) | D75: =IF(3>=18,ROUND(Assumptions!B48*Assumptions!B45,0),0) | E75: =IF(4>=18,ROUND(Assumptions!B48*Assumptions!B45,0),0) | F75: =IF(5>=18,ROUND(Assumptions!B48*Assumptions!B45,0),0) | G75: =IF(6>=18,ROUND(Assumptions!B48*Assumptions!B45,0),0) | H75: =IF(7>=18,ROUND(Assumptions!B48*Assumptions!B45,0),0) | I75: =IF(8>=18,ROUND(Assumptions!B48*Assumptions!B45,0),0) | J75: =IF(9>=18,ROUND(Assumptions!B48*Assumptions!B45,0),0) | K75: =IF(10>=18,ROUND(Assumptions!B48*Assumptions!B45,0),0) | L75: =IF(11>=18,ROUND(Assumptions!B48*Assumptions!B45,0),0) | M75: =IF(12>=18,ROUND(Assumptions!B48*Assumptions!B45,0),0) | N75: =IF(13>=18,ROUND(Assumptions!B48*Assumptions!B45,0),0) | O75: =IF(14>=18,ROUND(Assumptions!B48*Assumptions!B45,0),0) | P75: =IF(15>=18,ROUND(Assumptions!B48*Assumptions!B45,0),0) | Q75: =IF(16>=18,ROUND(Assumptions!B48*Assumptions!B45,0),0) | R75: =IF(17>=18,ROUND(Assumptions!B48*Assumptions!B45,0),0) | S75: =IF(18>=18,ROUND(Assumptions!B48*Assumptions!B45,0),0) | T75: =IF(19>=18,ROUND(Assumptions!B48*Assumptions!B45,0),0) | U75: =IF(20>=18,ROUND(Assumptions!B48*Assumptions!B45,0),0) | V75: =IF(21>=18,ROUND(Assumptions!B48*Assumptions!B45,0),0) | W75: =IF(22>=18,ROUND(Assumptions!B48*Assumptions!B45,0),0) | X75: =IF(23>=18,ROUND(Assumptions!B48*Assumptions!B45,0),0) | Y75: =IF(24>=18,ROUND(Assumptions!B48*Assumptions!B45,0),0) | Z75: =SUM(B75:Y75)
A76: BG Insurance (0.5% payroll) | B76: =ROUND((B71+B72+B73+B74+B75)*Assumptions!B49,0) | C76: =ROUND((C71+C72+C73+C74+C75)*Assumptions!B49,0) | D76: =ROUND((D71+D72+D73+D74+D75)*Assumptions!B49,0) | E76: =ROUND((E71+E72+E73+E74+E75)*Assumptions!B49,0) | F76: =ROUND((F71+F72+F73+F74+F75)*Assumptions!B49,0) | G76: =ROUND((G71+G72+G73+G74+G75)*Assumptions!B49,0) | H76: =ROUND((H71+H72+H73+H74+H75)*Assumptions!B49,0) | I76: =ROUND((I71+I72+I73+I74+I75)*Assumptions!B49,0) | J76: =ROUND((J71+J72+J73+J74+J75)*Assumptions!B49,0) | K76: =ROUND((K71+K72+K73+K74+K75)*Assumptions!B49,0) | L76: =ROUND((L71+L72+L73+L74+L75)*Assumptions!B49,0) | M76: =ROUND((M71+M72+M73+M74+M75)*Assumptions!B49,0) | N76: =ROUND((N71+N72+N73+N74+N75)*Assumptions!B49,0) | O76: =ROUND((O71+O72+O73+O74+O75)*Assumptions!B49,0) | P76: =ROUND((P71+P72+P73+P74+P75)*Assumptions!B49,0) | Q76: =ROUND((Q71+Q72+Q73+Q74+Q75)*Assumptions!B49,0) | R76: =ROUND((R71+R72+R73+R74+R75)*Assumptions!B49,0) | S76: =ROUND((S71+S72+S73+S74+S75)*Assumptions!B49,0) | T76: =ROUND((T71+T72+T73+T74+T75)*Assumptions!B49,0) | U76: =ROUND((U71+U72+U73+U74+U75)*Assumptions!B49,0) | V76: =ROUND((V71+V72+V73+V74+V75)*Assumptions!B49,0) | W76: =ROUND((W71+W72+W73+W74+W75)*Assumptions!B49,0) | X76: =ROUND((X71+X72+X73+X74+X75)*Assumptions!B49,0) | Y76: =ROUND((Y71+Y72+Y73+Y74+Y75)*Assumptions!B49,0) | Z76: =SUM(B76:Y76)
A77: KSK Levy (4.9% on freelancers) | B77: =ROUND('Growth Curves'!B11*Assumptions!B50,0) | C77: =ROUND('Growth Curves'!C11*Assumptions!B50,0) | D77: =ROUND('Growth Curves'!D11*Assumptions!B50,0) | E77: =ROUND('Growth Curves'!E11*Assumptions!B50,0) | F77: =ROUND('Growth Curves'!F11*Assumptions!B50,0) | G77: =ROUND('Growth Curves'!G11*Assumptions!B50,0) | H77: =ROUND('Growth Curves'!H11*Assumptions!B50,0) | I77: =ROUND('Growth Curves'!I11*Assumptions!B50,0) | J77: =ROUND('Growth Curves'!J11*Assumptions!B50,0) | K77: =ROUND('Growth Curves'!K11*Assumptions!B50,0) | L77: =ROUND('Growth Curves'!L11*Assumptions!B50,0) | M77: =ROUND('Growth Curves'!M11*Assumptions!B50,0) | N77: =ROUND('Growth Curves'!N11*Assumptions!B50,0) | O77: =ROUND('Growth Curves'!O11*Assumptions!B50,0) | P77: =ROUND('Growth Curves'!P11*Assumptions!B50,0) | Q77: =ROUND('Growth Curves'!Q11*Assumptions!B50,0) | R77: =ROUND('Growth Curves'!R11*Assumptions!B50,0) | S77: =ROUND('Growth Curves'!S11*Assumptions!B50,0) | T77: =ROUND('Growth Curves'!T11*Assumptions!B50,0) | U77: =ROUND('Growth Curves'!U11*Assumptions!B50,0) | V77: =ROUND('Growth Curves'!V11*Assumptions!B50,0) | W77: =ROUND('Growth Curves'!W11*Assumptions!B50,0) | X77: =ROUND('Growth Curves'!X11*Assumptions!B50,0) | Y77: =ROUND('Growth Curves'!Y11*Assumptions!B50,0) | Z77: =SUM(B77:Y77)
A78: Payroll Total | B78: =B71+B72+B73+B74+B75+B76+B77 | C78: =C71+C72+C73+C74+C75+C76+C77 | D78: =D71+D72+D73+D74+D75+D76+D77 | E78: =E71+E72+E73+E74+E75+E76+E77 | F78: =F71+F72+F73+F74+F75+F76+F77 | G78: =G71+G72+G73+G74+G75+G76+G77 | H78: =H71+H72+H73+H74+H75+H76+H77 | I78: =I71+I72+I73+I74+I75+I76+I77 | ... Y78: =Y71+Y72+Y73+Y74+Y75+Y76+Y77 | Z78: =SUM(B78:Y78)
A79: Sales & Marketing
A80: Paid Ads | B80: ='Growth Curves'!B10 | C80: ='Growth Curves'!C10 | D80: ='Growth Curves'!D10 | E80: ='Growth Curves'!E10 | F80: ='Growth Curves'!F10 | G80: ='Growth Curves'!G10 | H80: ='Growth Curves'!H10 | I80: ='Growth Curves'!I10 | ... Y80: ='Growth Curves'!Y10 | Z80: =SUM(B80:Y80)
A81: Content Creation | B81: =Assumptions!B86 | C81: =Assumptions!B86 | D81: =Assumptions!B86 | E81: =Assumptions!B86 | F81: =Assumptions!B86 | G81: =Assumptions!B86 | H81: =Assumptions!B86 | I81: =Assumptions!B86 | J81: =Assumptions!B86 | K81: =Assumptions!B86 | L81: =Assumptions!B86 | M81: =Assumptions!B86 | N81: =Assumptions!B86 | O81: =Assumptions!B86 | P81: =Assumptions!B86 | Q81: =Assumptions!B86 | R81: =Assumptions!B86 | S81: =Assumptions!B86 | T81: =Assumptions!B86 | U81: =Assumptions!B86 | V81: =Assumptions!B86 | W81: =Assumptions!B86 | X81: =Assumptions!B86 | Y81: =Assumptions!B86 | Z81: =SUM(B81:Y81)
A82: Influencer Seeding (M7+) | B82: =IF(1>=7,Assumptions!B87,0) | C82: =IF(2>=7,Assumptions!B87,0) | D82: =IF(3>=7,Assumptions!B87,0) | E82: =IF(4>=7,Assumptions!B87,0) | F82: =IF(5>=7,Assumptions!B87,0) | G82: =IF(6>=7,Assumptions!B87,0) | H82: =IF(7>=7,Assumptions!B87,0) | I82: =IF(8>=7,Assumptions!B87,0) | J82: =IF(9>=7,Assumptions!B87,0) | K82: =IF(10>=7,Assumptions!B87,0) | L82: =IF(11>=7,Assumptions!B87,0) | M82: =IF(12>=7,Assumptions!B87,0) | N82: =IF(13>=7,Assumptions!B87,0) | O82: =IF(14>=7,Assumptions!B87,0) | P82: =IF(15>=7,Assumptions!B87,0) | Q82: =IF(16>=7,Assumptions!B87,0) | R82: =IF(17>=7,Assumptions!B87,0) | S82: =IF(18>=7,Assumptions!B87,0) | T82: =IF(19>=7,Assumptions!B87,0) | U82: =IF(20>=7,Assumptions!B87,0) | V82: =IF(21>=7,Assumptions!B87,0) | W82: =IF(22>=7,Assumptions!B87,0) | X82: =IF(23>=7,Assumptions!B87,0) | Y82: =IF(24>=7,Assumptions!B87,0) | Z82: =SUM(B82:Y82)
A83: S&M Total | B83: =B80+B81+B82 | C83: =C80+C81+C82 | D83: =D80+D81+D82 | E83: =E80+E81+E82 | F83: =F80+F81+F82 | G83: =G80+G81+G82 | H83: =H80+H81+H82 | I83: =I80+I81+I82 | ... Y83: =Y80+Y81+Y82 | Z83: =SUM(B83:Y83)
A84: General & Admin
A85: Rent (co-work M1-3 / space M4+) | B85: =IF(1<=3,Assumptions!B61,Assumptions!B62) | C85: =IF(2<=3,Assumptions!B61,Assumptions!B62) | D85: =IF(3<=3,Assumptions!B61,Assumptions!B62) | E85: =IF(4<=3,Assumptions!B61,Assumptions!B62) | F85: =IF(5<=3,Assumptions!B61,Assumptions!B62) | G85: =IF(6<=3,Assumptions!B61,Assumptions!B62) | H85: =IF(7<=3,Assumptions!B61,Assumptions!B62) | I85: =IF(8<=3,Assumptions!B61,Assumptions!B62) | J85: =IF(9<=3,Assumptions!B61,Assumptions!B62) | K85: =IF(10<=3,Assumptions!B61,Assumptions!B62) | L85: =IF(11<=3,Assumptions!B61,Assumptions!B62) | M85: =IF(12<=3,Assumptions!B61,Assumptions!B62) | N85: =IF(13<=3,Assumptions!B61,Assumptions!B62) | O85: =IF(14<=3,Assumptions!B61,Assumptions!B62) | P85: =IF(15<=3,Assumptions!B61,Assumptions!B62) | Q85: =IF(16<=3,Assumptions!B61,Assumptions!B62) | R85: =IF(17<=3,Assumptions!B61,Assumptions!B62) | S85: =IF(18<=3,Assumptions!B61,Assumptions!B62) | T85: =IF(19<=3,Assumptions!B61,Assumptions!B62) | U85: =IF(20<=3,Assumptions!B61,Assumptions!B62) | V85: =IF(21<=3,Assumptions!B61,Assumptions!B62) | W85: =IF(22<=3,Assumptions!B61,Assumptions!B62) | X85: =IF(23<=3,Assumptions!B61,Assumptions!B62) | Y85: =IF(24<=3,Assumptions!B61,Assumptions!B62) | Z85: =SUM(B85:Y85)
A86: Nebenkosten M4+ (P3) | B86: =IF(1>=4,Assumptions!B63,0) | C86: =IF(2>=4,Assumptions!B63,0) | D86: =IF(3>=4,Assumptions!B63,0) | E86: =IF(4>=4,Assumptions!B63,0) | F86: =IF(5>=4,Assumptions!B63,0) | G86: =IF(6>=4,Assumptions!B63,0) | H86: =IF(7>=4,Assumptions!B63,0) | I86: =IF(8>=4,Assumptions!B63,0) | J86: =IF(9>=4,Assumptions!B63,0) | K86: =IF(10>=4,Assumptions!B63,0) | L86: =IF(11>=4,Assumptions!B63,0) | M86: =IF(12>=4,Assumptions!B63,0) | N86: =IF(13>=4,Assumptions!B63,0) | O86: =IF(14>=4,Assumptions!B63,0) | P86: =IF(15>=4,Assumptions!B63,0) | Q86: =IF(16>=4,Assumptions!B63,0) | R86: =IF(17>=4,Assumptions!B63,0) | S86: =IF(18>=4,Assumptions!B63,0) | T86: =IF(19>=4,Assumptions!B63,0) | U86: =IF(20>=4,Assumptions!B63,0) | V86: =IF(21>=4,Assumptions!B63,0) | W86: =IF(22>=4,Assumptions!B63,0) | X86: =IF(23>=4,Assumptions!B63,0) | Y86: =IF(24>=4,Assumptions!B63,0) | Z86: =SUM(B86:Y86)
A87: Steuerberater | B87: =Assumptions!B64 | C87: =Assumptions!B64 | D87: =Assumptions!B64 | E87: =Assumptions!B64 | F87: =Assumptions!B64 | G87: =Assumptions!B64 | H87: =Assumptions!B64 | I87: =Assumptions!B64 | J87: =Assumptions!B64 | K87: =Assumptions!B64 | L87: =Assumptions!B64 | M87: =Assumptions!B64 | N87: =Assumptions!B64 | O87: =Assumptions!B64 | P87: =Assumptions!B64 | Q87: =Assumptions!B64 | R87: =Assumptions!B64 | S87: =Assumptions!B64 | T87: =Assumptions!B64 | U87: =Assumptions!B64 | V87: =Assumptions!B64 | W87: =Assumptions!B64 | X87: =Assumptions!B64 | Y87: =Assumptions!B64 | Z87: =SUM(B87:Y87)
A88: General Liability Insurance | B88: =Assumptions!B65 | C88: =Assumptions!B65 | D88: =Assumptions!B65 | E88: =Assumptions!B65 | F88: =Assumptions!B65 | G88: =Assumptions!B65 | H88: =Assumptions!B65 | I88: =Assumptions!B65 | J88: =Assumptions!B65 | K88: =Assumptions!B65 | L88: =Assumptions!B65 | M88: =Assumptions!B65 | N88: =Assumptions!B65 | O88: =Assumptions!B65 | P88: =Assumptions!B65 | Q88: =Assumptions!B65 | R88: =Assumptions!B65 | S88: =Assumptions!B65 | T88: =Assumptions!B65 | U88: =Assumptions!B65 | V88: =Assumptions!B65 | W88: =Assumptions!B65 | X88: =Assumptions!B65 | Y88: =Assumptions!B65 | Z88: =SUM(B88:Y88)
A89: D&O Insurance (P6) | B89: =Assumptions!B66 | C89: =Assumptions!B66 | D89: =Assumptions!B66 | E89: =Assumptions!B66 | F89: =Assumptions!B66 | G89: =Assumptions!B66 | H89: =Assumptions!B66 | I89: =Assumptions!B66 | J89: =Assumptions!B66 | K89: =Assumptions!B66 | L89: =Assumptions!B66 | M89: =Assumptions!B66 | N89: =Assumptions!B66 | O89: =Assumptions!B66 | P89: =Assumptions!B66 | Q89: =Assumptions!B66 | R89: =Assumptions!B66 | S89: =Assumptions!B66 | T89: =Assumptions!B66 | U89: =Assumptions!B66 | V89: =Assumptions!B66 | W89: =Assumptions!B66 | X89: =Assumptions!B66 | Y89: =Assumptions!B66 | Z89: =SUM(B89:Y89)
A90: Cyber Insurance (P6) | B90: =Assumptions!B67 | C90: =Assumptions!B67 | D90: =Assumptions!B67 | E90: =Assumptions!B67 | F90: =Assumptions!B67 | G90: =Assumptions!B67 | H90: =Assumptions!B67 | I90: =Assumptions!B67 | J90: =Assumptions!B67 | K90: =Assumptions!B67 | L90: =Assumptions!B67 | M90: =Assumptions!B67 | N90: =Assumptions!B67 | O90: =Assumptions!B67 | P90: =Assumptions!B67 | Q90: =Assumptions!B67 | R90: =Assumptions!B67 | S90: =Assumptions!B67 | T90: =Assumptions!B67 | U90: =Assumptions!B67 | V90: =Assumptions!B67 | W90: =Assumptions!B67 | X90: =Assumptions!B67 | Y90: =Assumptions!B67 | Z90: =SUM(B90:Y90)
A91: Product Liability Insurance (P6) | B91: =Assumptions!B68 | C91: =Assumptions!B68 | D91: =Assumptions!B68 | E91: =Assumptions!B68 | F91: =Assumptions!B68 | G91: =Assumptions!B68 | H91: =Assumptions!B68 | I91: =Assumptions!B68 | J91: =Assumptions!B68 | K91: =Assumptions!B68 | L91: =Assumptions!B68 | M91: =Assumptions!B68 | N91: =Assumptions!B68 | O91: =Assumptions!B68 | P91: =Assumptions!B68 | Q91: =Assumptions!B68 | R91: =Assumptions!B68 | S91: =Assumptions!B68 | T91: =Assumptions!B68 | U91: =Assumptions!B68 | V91: =Assumptions!B68 | W91: =Assumptions!B68 | X91: =Assumptions!B68 | Y91: =Assumptions!B68 | Z91: =SUM(B91:Y91)
A92: Product Recall Insurance M4+ (P4) | B92: =IF(1>=4,Assumptions!B69,0) | C92: =IF(2>=4,Assumptions!B69,0) | D92: =IF(3>=4,Assumptions!B69,0) | E92: =IF(4>=4,Assumptions!B69,0) | F92: =IF(5>=4,Assumptions!B69,0) | G92: =IF(6>=4,Assumptions!B69,0) | H92: =IF(7>=4,Assumptions!B69,0) | I92: =IF(8>=4,Assumptions!B69,0) | J92: =IF(9>=4,Assumptions!B69,0) | K92: =IF(10>=4,Assumptions!B69,0) | L92: =IF(11>=4,Assumptions!B69,0) | M92: =IF(12>=4,Assumptions!B69,0) | N92: =IF(13>=4,Assumptions!B69,0) | O92: =IF(14>=4,Assumptions!B69,0) | P92: =IF(15>=4,Assumptions!B69,0) | Q92: =IF(16>=4,Assumptions!B69,0) | R92: =IF(17>=4,Assumptions!B69,0) | S92: =IF(18>=4,Assumptions!B69,0) | T92: =IF(19>=4,Assumptions!B69,0) | U92: =IF(20>=4,Assumptions!B69,0) | V92: =IF(21>=4,Assumptions!B69,0) | W92: =IF(22>=4,Assumptions!B69,0) | X92: =IF(23>=4,Assumptions!B69,0) | Y92: =IF(24>=4,Assumptions!B69,0) | Z92: =SUM(B92:Y92)
A93: Utilities (M4+) | B93: =IF(1>=4,Assumptions!B70,0) | C93: =IF(2>=4,Assumptions!B70,0) | D93: =IF(3>=4,Assumptions!B70,0) | E93: =IF(4>=4,Assumptions!B70,0) | F93: =IF(5>=4,Assumptions!B70,0) | G93: =IF(6>=4,Assumptions!B70,0) | H93: =IF(7>=4,Assumptions!B70,0) | I93: =IF(8>=4,Assumptions!B70,0) | J93: =IF(9>=4,Assumptions!B70,0) | K93: =IF(10>=4,Assumptions!B70,0) | L93: =IF(11>=4,Assumptions!B70,0) | M93: =IF(12>=4,Assumptions!B70,0) | N93: =IF(13>=4,Assumptions!B70,0) | O93: =IF(14>=4,Assumptions!B70,0) | P93: =IF(15>=4,Assumptions!B70,0) | Q93: =IF(16>=4,Assumptions!B70,0) | R93: =IF(17>=4,Assumptions!B70,0) | S93: =IF(18>=4,Assumptions!B70,0) | T93: =IF(19>=4,Assumptions!B70,0) | U93: =IF(20>=4,Assumptions!B70,0) | V93: =IF(21>=4,Assumptions!B70,0) | W93: =IF(22>=4,Assumptions!B70,0) | X93: =IF(23>=4,Assumptions!B70,0) | Y93: =IF(24>=4,Assumptions!B70,0) | Z93: =SUM(B93:Y93)
A94: Cleaning/Maintenance (M4+) | B94: =IF(1>=4,Assumptions!B71,0) | C94: =IF(2>=4,Assumptions!B71,0) | D94: =IF(3>=4,Assumptions!B71,0) | E94: =IF(4>=4,Assumptions!B71,0) | F94: =IF(5>=4,Assumptions!B71,0) | G94: =IF(6>=4,Assumptions!B71,0) | H94: =IF(7>=4,Assumptions!B71,0) | I94: =IF(8>=4,Assumptions!B71,0) | J94: =IF(9>=4,Assumptions!B71,0) | K94: =IF(10>=4,Assumptions!B71,0) | L94: =IF(11>=4,Assumptions!B71,0) | M94: =IF(12>=4,Assumptions!B71,0) | N94: =IF(13>=4,Assumptions!B71,0) | O94: =IF(14>=4,Assumptions!B71,0) | P94: =IF(15>=4,Assumptions!B71,0) | Q94: =IF(16>=4,Assumptions!B71,0) | R94: =IF(17>=4,Assumptions!B71,0) | S94: =IF(18>=4,Assumptions!B71,0) | T94: =IF(19>=4,Assumptions!B71,0) | U94: =IF(20>=4,Assumptions!B71,0) | V94: =IF(21>=4,Assumptions!B71,0) | W94: =IF(22>=4,Assumptions!B71,0) | X94: =IF(23>=4,Assumptions!B71,0) | Y94: =IF(24>=4,Assumptions!B71,0) | Z94: =SUM(B94:Y94)
A95: Maintenance Reserve M4+ (P3) | B95: =IF(1>=4,Assumptions!B72,0) | C95: =IF(2>=4,Assumptions!B72,0) | D95: =IF(3>=4,Assumptions!B72,0) | E95: =IF(4>=4,Assumptions!B72,0) | F95: =IF(5>=4,Assumptions!B72,0) | G95: =IF(6>=4,Assumptions!B72,0) | H95: =IF(7>=4,Assumptions!B72,0) | I95: =IF(8>=4,Assumptions!B72,0) | J95: =IF(9>=4,Assumptions!B72,0) | K95: =IF(10>=4,Assumptions!B72,0) | L95: =IF(11>=4,Assumptions!B72,0) | M95: =IF(12>=4,Assumptions!B72,0) | N95: =IF(13>=4,Assumptions!B72,0) | O95: =IF(14>=4,Assumptions!B72,0) | P95: =IF(15>=4,Assumptions!B72,0) | Q95: =IF(16>=4,Assumptions!B72,0) | R95: =IF(17>=4,Assumptions!B72,0) | S95: =IF(18>=4,Assumptions!B72,0) | T95: =IF(19>=4,Assumptions!B72,0) | U95: =IF(20>=4,Assumptions!B72,0) | V95: =IF(21>=4,Assumptions!B72,0) | W95: =IF(22>=4,Assumptions!B72,0) | X95: =IF(23>=4,Assumptions!B72,0) | Y95: =IF(24>=4,Assumptions!B72,0) | Z95: =SUM(B95:Y95)
A96: Waste Disposal M4+ (P3) | B96: =IF(1>=4,Assumptions!B73,0) | C96: =IF(2>=4,Assumptions!B73,0) | D96: =IF(3>=4,Assumptions!B73,0) | E96: =IF(4>=4,Assumptions!B73,0) | F96: =IF(5>=4,Assumptions!B73,0) | G96: =IF(6>=4,Assumptions!B73,0) | H96: =IF(7>=4,Assumptions!B73,0) | I96: =IF(8>=4,Assumptions!B73,0) | J96: =IF(9>=4,Assumptions!B73,0) | K96: =IF(10>=4,Assumptions!B73,0) | L96: =IF(11>=4,Assumptions!B73,0) | M96: =IF(12>=4,Assumptions!B73,0) | N96: =IF(13>=4,Assumptions!B73,0) | O96: =IF(14>=4,Assumptions!B73,0) | P96: =IF(15>=4,Assumptions!B73,0) | Q96: =IF(16>=4,Assumptions!B73,0) | R96: =IF(17>=4,Assumptions!B73,0) | S96: =IF(18>=4,Assumptions!B73,0) | T96: =IF(19>=4,Assumptions!B73,0) | U96: =IF(20>=4,Assumptions!B73,0) | V96: =IF(21>=4,Assumptions!B73,0) | W96: =IF(22>=4,Assumptions!B73,0) | X96: =IF(23>=4,Assumptions!B73,0) | Y96: =IF(24>=4,Assumptions!B73,0) | Z96: =SUM(B96:Y96)
A97: WiFi/Internet M4+ (P3) | B97: =IF(1>=4,Assumptions!B74,0) | C97: =IF(2>=4,Assumptions!B74,0) | D97: =IF(3>=4,Assumptions!B74,0) | E97: =IF(4>=4,Assumptions!B74,0) | F97: =IF(5>=4,Assumptions!B74,0) | G97: =IF(6>=4,Assumptions!B74,0) | H97: =IF(7>=4,Assumptions!B74,0) | I97: =IF(8>=4,Assumptions!B74,0) | J97: =IF(9>=4,Assumptions!B74,0) | K97: =IF(10>=4,Assumptions!B74,0) | L97: =IF(11>=4,Assumptions!B74,0) | M97: =IF(12>=4,Assumptions!B74,0) | N97: =IF(13>=4,Assumptions!B74,0) | O97: =IF(14>=4,Assumptions!B74,0) | P97: =IF(15>=4,Assumptions!B74,0) | Q97: =IF(16>=4,Assumptions!B74,0) | R97: =IF(17>=4,Assumptions!B74,0) | S97: =IF(18>=4,Assumptions!B74,0) | T97: =IF(19>=4,Assumptions!B74,0) | U97: =IF(20>=4,Assumptions!B74,0) | V97: =IF(21>=4,Assumptions!B74,0) | W97: =IF(22>=4,Assumptions!B74,0) | X97: =IF(23>=4,Assumptions!B74,0) | Y97: =IF(24>=4,Assumptions!B74,0) | Z97: =SUM(B97:Y97)
A98: POS System (M4+) | B98: =IF(1>=4,Assumptions!B75,0) | C98: =IF(2>=4,Assumptions!B75,0) | D98: =IF(3>=4,Assumptions!B75,0) | E98: =IF(4>=4,Assumptions!B75,0) | F98: =IF(5>=4,Assumptions!B75,0) | G98: =IF(6>=4,Assumptions!B75,0) | H98: =IF(7>=4,Assumptions!B75,0) | I98: =IF(8>=4,Assumptions!B75,0) | J98: =IF(9>=4,Assumptions!B75,0) | K98: =IF(10>=4,Assumptions!B75,0) | L98: =IF(11>=4,Assumptions!B75,0) | M98: =IF(12>=4,Assumptions!B75,0) | N98: =IF(13>=4,Assumptions!B75,0) | O98: =IF(14>=4,Assumptions!B75,0) | P98: =IF(15>=4,Assumptions!B75,0) | Q98: =IF(16>=4,Assumptions!B75,0) | R98: =IF(17>=4,Assumptions!B75,0) | S98: =IF(18>=4,Assumptions!B75,0) | T98: =IF(19>=4,Assumptions!B75,0) | U98: =IF(20>=4,Assumptions!B75,0) | V98: =IF(21>=4,Assumptions!B75,0) | W98: =IF(22>=4,Assumptions!B75,0) | X98: =IF(23>=4,Assumptions!B75,0) | Y98: =IF(24>=4,Assumptions!B75,0) | Z98: =SUM(B98:Y98)
A99: DSB / ext. DPO (P6: mandatory) | B99: =Assumptions!B76 | C99: =Assumptions!B76 | D99: =Assumptions!B76 | E99: =Assumptions!B76 | F99: =Assumptions!B76 | G99: =Assumptions!B76 | H99: =Assumptions!B76 | I99: =Assumptions!B76 | J99: =Assumptions!B76 | K99: =Assumptions!B76 | L99: =Assumptions!B76 | M99: =Assumptions!B76 | N99: =Assumptions!B76 | O99: =Assumptions!B76 | P99: =Assumptions!B76 | Q99: =Assumptions!B76 | R99: =Assumptions!B76 | S99: =Assumptions!B76 | T99: =Assumptions!B76 | U99: =Assumptions!B76 | V99: =Assumptions!B76 | W99: =Assumptions!B76 | X99: =Assumptions!B76 | Y99: =Assumptions!B76 | Z99: =SUM(B99:Y99)
A100: CMP Cookie Tool (P6) | B100: =Assumptions!B77 | C100: =Assumptions!B77 | D100: =Assumptions!B77 | E100: =Assumptions!B77 | F100: =Assumptions!B77 | G100: =Assumptions!B77 | H100: =Assumptions!B77 | I100: =Assumptions!B77 | J100: =Assumptions!B77 | K100: =Assumptions!B77 | L100: =Assumptions!B77 | M100: =Assumptions!B77 | N100: =Assumptions!B77 | O100: =Assumptions!B77 | P100: =Assumptions!B77 | Q100: =Assumptions!B77 | R100: =Assumptions!B77 | S100: =Assumptions!B77 | T100: =Assumptions!B77 | U100: =Assumptions!B77 | V100: =Assumptions!B77 | W100: =Assumptions!B77 | X100: =Assumptions!B77 | Y100: =Assumptions!B77 | Z100: =SUM(B100:Y100)
A101: Food Safety Compliance M4+ (P4) | B101: =IF(1>=4,Assumptions!B78,0) | C101: =IF(2>=4,Assumptions!B78,0) | D101: =IF(3>=4,Assumptions!B78,0) | E101: =IF(4>=4,Assumptions!B78,0) | F101: =IF(5>=4,Assumptions!B78,0) | G101: =IF(6>=4,Assumptions!B78,0) | H101: =IF(7>=4,Assumptions!B78,0) | I101: =IF(8>=4,Assumptions!B78,0) | J101: =IF(9>=4,Assumptions!B78,0) | K101: =IF(10>=4,Assumptions!B78,0) | L101: =IF(11>=4,Assumptions!B78,0) | M101: =IF(12>=4,Assumptions!B78,0) | N101: =IF(13>=4,Assumptions!B78,0) | O101: =IF(14>=4,Assumptions!B78,0) | P101: =IF(15>=4,Assumptions!B78,0) | Q101: =IF(16>=4,Assumptions!B78,0) | R101: =IF(17>=4,Assumptions!B78,0) | S101: =IF(18>=4,Assumptions!B78,0) | T101: =IF(19>=4,Assumptions!B78,0) | U101: =IF(20>=4,Assumptions!B78,0) | V101: =IF(21>=4,Assumptions!B78,0) | W101: =IF(22>=4,Assumptions!B78,0) | X101: =IF(23>=4,Assumptions!B78,0) | Y101: =IF(24>=4,Assumptions!B78,0) | Z101: =SUM(B101:Y101)
A102: IHK Berlin (P2: EUR 120/yr) | B102: =Assumptions!B79 | C102: =Assumptions!B79 | D102: =Assumptions!B79 | E102: =Assumptions!B79 | F102: =Assumptions!B79 | G102: =Assumptions!B79 | H102: =Assumptions!B79 | I102: =Assumptions!B79 | J102: =Assumptions!B79 | K102: =Assumptions!B79 | L102: =Assumptions!B79 | M102: =Assumptions!B79 | N102: =Assumptions!B79 | O102: =Assumptions!B79 | P102: =Assumptions!B79 | Q102: =Assumptions!B79 | R102: =Assumptions!B79 | S102: =Assumptions!B79 | T102: =Assumptions!B79 | U102: =Assumptions!B79 | V102: =Assumptions!B79 | W102: =Assumptions!B79 | X102: =Assumptions!B79 | Y102: =Assumptions!B79 | Z102: =SUM(B102:Y102)
A103: GEMA M4+ (P2) | B103: =IF(1>=4,Assumptions!B80,0) | C103: =IF(2>=4,Assumptions!B80,0) | D103: =IF(3>=4,Assumptions!B80,0) | E103: =IF(4>=4,Assumptions!B80,0) | F103: =IF(5>=4,Assumptions!B80,0) | G103: =IF(6>=4,Assumptions!B80,0) | H103: =IF(7>=4,Assumptions!B80,0) | I103: =IF(8>=4,Assumptions!B80,0) | J103: =IF(9>=4,Assumptions!B80,0) | K103: =IF(10>=4,Assumptions!B80,0) | L103: =IF(11>=4,Assumptions!B80,0) | M103: =IF(12>=4,Assumptions!B80,0) | N103: =IF(13>=4,Assumptions!B80,0) | O103: =IF(14>=4,Assumptions!B80,0) | P103: =IF(15>=4,Assumptions!B80,0) | Q103: =IF(16>=4,Assumptions!B80,0) | R103: =IF(17>=4,Assumptions!B80,0) | S103: =IF(18>=4,Assumptions!B80,0) | T103: =IF(19>=4,Assumptions!B80,0) | U103: =IF(20>=4,Assumptions!B80,0) | V103: =IF(21>=4,Assumptions!B80,0) | W103: =IF(22>=4,Assumptions!B80,0) | X103: =IF(23>=4,Assumptions!B80,0) | Y103: =IF(24>=4,Assumptions!B80,0) | Z103: =SUM(B103:Y103)
A104: Rundfunkbeitrag M4+ (P2 — fix: starts when space opens) | B104: =IF(1>=4,Assumptions!B81,0) | C104: =IF(2>=4,Assumptions!B81,0) | D104: =IF(3>=4,Assumptions!B81,0) | E104: =IF(4>=4,Assumptions!B81,0) | F104: =IF(5>=4,Assumptions!B81,0) | G104: =IF(6>=4,Assumptions!B81,0) | H104: =IF(7>=4,Assumptions!B81,0) | I104: =IF(8>=4,Assumptions!B81,0) | J104: =IF(9>=4,Assumptions!B81,0) | K104: =IF(10>=4,Assumptions!B81,0) | L104: =IF(11>=4,Assumptions!B81,0) | M104: =IF(12>=4,Assumptions!B81,0) | N104: =IF(13>=4,Assumptions!B81,0) | O104: =IF(14>=4,Assumptions!B81,0) | P104: =IF(15>=4,Assumptions!B81,0) | Q104: =IF(16>=4,Assumptions!B81,0) | R104: =IF(17>=4,Assumptions!B81,0) | S104: =IF(18>=4,Assumptions!B81,0) | T104: =IF(19>=4,Assumptions!B81,0) | U104: =IF(20>=4,Assumptions!B81,0) | V104: =IF(21>=4,Assumptions!B81,0) | W104: =IF(22>=4,Assumptions!B81,0) | X104: =IF(23>=4,Assumptions!B81,0) | Y104: =IF(24>=4,Assumptions!B81,0) | Z104: =SUM(B104:Y104)
A105: Verpackungsgesetz (P2) | B105: =Assumptions!B82 | C105: =Assumptions!B82 | D105: =Assumptions!B82 | E105: =Assumptions!B82 | F105: =Assumptions!B82 | G105: =Assumptions!B82 | H105: =Assumptions!B82 | I105: =Assumptions!B82 | J105: =Assumptions!B82 | K105: =Assumptions!B82 | L105: =Assumptions!B82 | M105: =Assumptions!B82 | N105: =Assumptions!B82 | O105: =Assumptions!B82 | P105: =Assumptions!B82 | Q105: =Assumptions!B82 | R105: =Assumptions!B82 | S105: =Assumptions!B82 | T105: =Assumptions!B82 | U105: =Assumptions!B82 | V105: =Assumptions!B82 | W105: =Assumptions!B82 | X105: =Assumptions!B82 | Y105: =Assumptions!B82 | Z105: =SUM(B105:Y105)
A106: Bank Fees (P5) | B106: =Assumptions!B94 | C106: =Assumptions!B94 | D106: =Assumptions!B94 | E106: =Assumptions!B94 | F106: =Assumptions!B94 | G106: =Assumptions!B94 | H106: =Assumptions!B94 | I106: =Assumptions!B94 | J106: =Assumptions!B94 | K106: =Assumptions!B94 | L106: =Assumptions!B94 | M106: =Assumptions!B94 | N106: =Assumptions!B94 | O106: =Assumptions!B94 | P106: =Assumptions!B94 | Q106: =Assumptions!B94 | R106: =Assumptions!B94 | S106: =Assumptions!B94 | T106: =Assumptions!B94 | U106: =Assumptions!B94 | V106: =Assumptions!B94 | W106: =Assumptions!B94 | X106: =Assumptions!B94 | Y106: =Assumptions!B94 | Z106: =SUM(B106:Y106)
...

Sheet Assumptions
A1: alche — P&L Assumptions v4
A2: Change any value here → P&L auto-recalculates. All persona findings incorporated.
A4: SUBSCRIPTION MODEL
A5: Core tier price (EUR/mo) | B5: 19 | C5: Entry tier
A6: Pro tier price (EUR/mo) | B6: 49 | C6: Sweet spot
A7: Premium tier price (EUR/mo) | B7: 99 | C7: Highest ARPU
A8: Monthly churn rate | B8: 0.08 | C8: 8% — locked data
A9: Core tier share | B9: 0.52 | C9: 52%
A10: Pro tier share | B10: 0.38 | C10: 38%
A11: Premium tier share | B11: 0.1 | C11: 10%
A13: SUBSCRIBER GROWTH (new subs/month)
A14: M1-M3 | B14: 0 | C14: Pre-launch — no app yet
A15: M4-M6 | B15: 15 | C15: Product launch
A16: M7-M9 | B16: 22 | C16: Growth acceleration
A17: M10-M12 | B17: 28 | C17: Marketing ramp
A18: M13-M18 | B18: 32 | C18: Scaling
A19: M19-M24 | B19: 38 | C19: Scaling phase
A21: PRODUCT PRICING
A22: Retail product price (EUR) | B22: 49 | C22: R10 validated
A23: Retail product COGS (EUR/unit) | B23: 23.5 | C23: R10: wholesale ~48% of retail
A24: LED session price (EUR) | B24: 0 | C24: Free with smoothie purchase
A25: LED practitioner cost (EUR) | B25: 0 | C25: Self-service — no practitioner
A26: Smoothie avg price (EUR) | B26: 9.67 | C26: R2 Cost Analysis
A27: Smoothie COGS rate | B27: 0.35 | C27: 35% ingredients+packaging (R2)
A28: Event ticket price (EUR) | B28: 35 | C28: Community events
A29: Event fixed cost (EUR) | B29: 250 | C29: Venue per event
A30: Ticketing platform fee | B30: 0.07 | C30: 7% Luma/Eventbrite
A31: Doctor SaaS fee (EUR/mo) | B31: 99 | C31: D1: StGB 299a safe
A32: Doctor verify cost (EUR) | B32: 25 | C32: Per new doctor
A33: Doctor max clinics | B33: 20 | C33: Cap M1-24
A35: COST RATES
A36: Waste — blended rate | B36: 0.055 | C36: D7: capsules 4%, powders 7%
A37: 3PL fulfillment (EUR/unit) | B37: 2.5 | C37: Retail products only
A38: Stripe fee rate | B38: 0.029 | C38: 2.9%
A39: AI API per user (EUR/mo) | B39: 0.35 | C39: D6: hybrid Claude+Gemini
A40: Refund/returns reserve | B40: 0.015 | C40: 1.5% of product revenue
A41: Bad debt provision | B41: 0.005 | C41: P5: 0.5% of total revenue
A43: PAYROLL
A44: Founder gross salary (each) | B44: 2000 | C44: EUR 24K/yr gross each (Timu + Daria)
A45: Employer multiplier | B45: 1.25 | C45: P2/P7: incl. U1/U2/U3 (was 1.22)
A46: Space staff gross (M4+) | B46: 1230 | C46: Midijob ~25 hrs/wk
A47: Partner Mgr gross (M6+) | B47: 2000 | C47: EUR/mo
A48: CTO gross (M18+) | B48: 6500 | C48: EUR 78K — P7: below 25th pctile
A49: BG insurance rate | B49: 0.005 | C49: P7: ~0.5% for office (was 1.5%)
A50: KSK levy rate | B50: 0.049 | C50: P2: 4.9% on creative freelancer fees
A51: Recruitment CTO (M14, contingency) | B51: 19000 | C51: EX-10: EUR 19K if network hire fails; moved to M14
A52: CTO onboarding (M18) | B52: 3500 | C52: P7: equipment + setup
A55: FIXED OPERATING COSTS
A56: App maintenance retainer (legacy) | B56: 1500 | C56: EX-06: Superseded by MVP CapEx approach
A57: Claude Max (internal AI) | B57: 210 | C57: D6: team budget
A58: SaaS Stack M1-6 | B58: 338 | C58: D9: Google, Figma, Notion, Crisp
A59: SaaS Stack M7-12 | B59: 500 | C59: D9: + tools
A60: SaaS Stack M13+ | B60: 750 | C60: D9: full stack
A61: Rent M1-3 (co-working) | B61: 750 | C61: Before space opens
A62: Rent M4+ (all-in, incl. Nebenkosten) | B62: 1500 | C62: EX-07: EUR 1,500/mo all-in (50sqm B-location)
A63: Nebenkosten M4+ (bundled in rent) | B63: 0 | C63: EX-07: EUR 0 — included in EUR 1,500 all-in rent
A64: Steuerberater | B64: 400 | C64: Tax advisor monthly
A65: General liability insurance | B65: 200 | C65: Betriebshaftpflicht
A66: D&O insurance | B66: 100 | C66: P6: mandatory with investors
A67: Cyber insurance | B67: 150 | C67: P6: health data — Art. 9 GDPR
... A82: Verpackungsgesetz (annual ÷ 12) | B82: 6 | C82: P2: LUCID + dual system
A85: SALES & MARKETING
A86: Content creation tools | B86: 150 | C86: Canva, stock, etc.
A87: Influencer seeding M7+ | B87: 200 | C87: Product seeding
A88: Investor travel | B88: 150 | C88: Monthly
A89: Conferences M7+ | B89: 100 | C89: Industry events
A90: Local transport | B90: 50 | C90: BVG
A92: BUFFERS
A93: Contingency buffer rate | B93: 0.1 | C93: 10% of OpEx (pre-contingency)
A94: Bank fees | B94: 35 | C94: P5: Geschaeftskonto monthly
A96: TAX (P2: Berlin GmbH)
A97: Gewerbesteuer rate (Berlin) | B97: 0.1435 | C97: P2: 3.5% × 410% Hebesatz
A98: KSt + Soli rate | B98: 0.15825 | C98: P2: 15% + 5.5% Soli
A99: Combined tax rate (simplified) | B99: 0.3 | C99: P2: ~30.18% rounded down
A101: CAPITAL EXPENDITURES
A102: GmbH Formation (M1) | B102: 2500 | C102: Notary + registration
A103: Legal Opinion HWG (M1) | B103: 3500 | C103: D3/R3
A104: R&D Stability Testing (M1) | B104: 5000 | C104: Supplement formulation
A105: DPIA (M1) | B105: 7500 | C105: P6: MANDATORY Art. 35 GDPR
A106: MDR Classification Opinion (M1) | B106: 7500 | C106: P6: MANDATORY pre-launch
A107: Privacy Policy + ToS (M1) | B107: 5000 | C107: P6: Art. 13/14 GDPR
A108: App Design & Development (M1) | B108: 15000 | C108: CapEx: UX/UI capitalized
A109: Space Buildout (M3) | B109: 25000 | C109: P3: was EUR 15K
A110: Kitchen Equipment (M3) | B110: 20000 | C110: Smoothie bar
A111: LED Therapy Devices (M3) | B111: 5000 | C111: MITO LIGHT panels
A112: Fire Safety Equipment (M3) | B112: 300 | C112: P3: extinguishers + signage
A113: Signage & Branding (M3) | B113: 500 | C113: P3: window + exterior
... A119: Depreciation period (months) | B119: 36 | C119: Linear 3-year
A120: SCENARIO MULTIPLIERS
A121: Bull — revenue multiplier | B121: 1.3 | C121: Optimistic growth
A122: Bull — churn multiplier | B122: 0.75 | C122: Lower churn
A123: Bear — revenue multiplier | B123: 0.6 | C123: Slower growth
A124: Bear — churn multiplier | B124: 1.5 | C124: Higher churn
A125: Bear — CAC multiplier | B125: 2 | C125: Higher acquisition cost
A127: v4 CHANGES — NEW ASSUMPTIONS (Feb 2026)
A128: Annual Essential price (EUR/yr) | B128: 190 | C128: EX-01: 10 months — 2 months free
A129: Annual Protocol price (EUR/yr) | B129: 490 | C129: EX-01: 10 months — 2 months free
A130: Annual Concierge price (EUR/yr) | B130: 990 | C130: EX-01: 10 months — 2 months free
A131: Annual mix M1-6 | B131: 0.2 | C131: EX-01: 20% of new subs choose annual in M1-6
A132: Annual mix M12+ | B132: 0.3 | C132: EX-01: 30% on annual by M12; M7-11 = 25%
...

Sheet Growth Curves
A1: alche — Monthly Growth Curves (Input Data)
A2: Edit numbers to change unit forecasts. P&L formulas reference these cells.
A3: Metric | B3: M1 | C3: M2 | D3: M3 | E3: M4 | F3: M5 | G3: M6 | H3: M7 | I3: M8 | J3: M9 | K3: M10 | L3: M11 | M3: M12 | N3: M13 | O3: M14 | P3: M15 | Q3: M16 | R3: M17 | S3: M18 | T3: M19 | U3: M20 | V3: M21 | W3: M22 | X3: M23 | Y3: M24
A4: Retail Units | B4: 0 | C4: 0 | D4: 0 | E4: 50 | F4: 100 | G4: 150 | H4: 250 | I4: 350 | J4: 450 | K4: 600 | L4: 750 | M4: 900 | N4: 1100 | O4: 1300 | P4: 1500 | Q4: 1800 | R4: 2100 | S4: 2400 | T4: 2700 | U4: 3000 | V4: 3400 | W4: 3800 | X4: 4200 | Y4: 4600
A5: LED Sessions | B5: 0 | C5: 0 | D5: 0 | E5: 10 | F5: 20 | G5: 35 | H5: 50 | I5: 65 | J5: 80 | K5: 100 | L5: 120 | M5: 140 | N5: 160 | O5: 180 | P5: 200 | Q5: 220 | R5: 240 | S5: 260 | T5: 280 | U5: 300 | V5: 300 | W5: 300 | X5: 300 | Y5: 300
A6: Smoothie Units | B6: 0 | C6: 0 | D6: 0 | E6: 100 | F6: 150 | G6: 250 | H6: 350 | I6: 450 | J6: 550 | K6: 650 | L6: 750 | M6: 850 | N6: 950 | O6: 1050 | P6: 1150 | Q6: 1250 | R6: 1350 | S6: 1450 | T6: 1550 | U6: 1650 | V6: 1750 | W6: 1850 | X6: 1950 | Y6: 2000
A7: Event Count | B7: 0 | C7: 0 | D7: 0 | E7: 1 | F7: 1 | G7: 2 | H7: 2 | I7: 3 | J7: 3 | K7: 3 | L7: 3 | M7: 3 | N7: 3 | O7: 3 | P7: 4 | Q7: 4 | R7: 4 | S7: 4 | T7: 4 | U7: 5 | V7: 5 | W7: 5 | X7: 5 | Y7: 5
A8: Event Avg Attendees | B8: 0 | C8: 0 | D8: 0 | E8: 12 | F8: 15 | G8: 15 | H8: 18 | I8: 18 | J8: 18 | K8: 20 | L8: 20 | M8: 20 | N8: 22 | O8: 22 | P8: 22 | Q8: 22 | R8: 24 | S8: 24 | T8: 25 | U8: 25 | V8: 25 | W8: 25 | X8: 25 | Y8: 25
A9: Doctor Clinics | B9: 0 | C9: 0 | D9: 0 | E9: 0 | F9: 0 | G9: 2 | H9: 5 | I9: 8 | J9: 10 | K9: 12 | L9: 15 | M9: 17 | N9: 18 | O9: 19 | P9: 20 | Q9: 20 | R9: 20 | S9: 20 | T9: 20 | U9: 20 | V9: 20 | W9: 20 | X9: 20 | Y9: 20
A10: Marketing Spend (EUR) | B10: 50 | C10: 50 | D10: 100 | E10: 200 | F10: 400 | G10: 600 | H10: 800 | I10: 800 | J10: 1000 | K10: 1200 | L10: 1400 | M10: 1400 | N10: 1800 | O10: 1800 | P10: 2000 | Q10: 2000 | R10: 2200 | S10: 2200 | T10: 2500 | U10: 2500 | V10: 2800 | W10: 2800 | X10: 3000 | Y10: 3000
A11: KSK-Eligible Freelancer Spend | B11: 500 | C11: 500 | D11: 500 | E11: 500 | F11: 800 | G11: 800 | H11: 800 | I11: 800 | J11: 800 | K11: 800 | L11: 800 | M11: 800 | N11: 800 | O11: 800 | P11: 800 | Q11: 800 | R11: 800 | S11: 800 | T11: 800 | U11: 800 | V11: 800 | W11: 800 | X11: 800 | Y11: 800
A12: New Doctors (delta) | B12: 0 | C12: =MAX(0,C9-B9) | D12: =MAX(0,D9-C9) | E12: =MAX(0,E9-D9) | F12: =MAX(0,F9-E9) | G12: =MAX(0,G9-F9) | H12: =MAX(0,H9-G9) | I12: =MAX(0,I9-H9) | J12: =MAX(0,J9-I9) | ... Y12: =MAX(0,Y9-X9)
A14: SUBSCRIBER MODEL
A15: New Subs Rate | B15: =IF(1<=3,Assumptions!B14,IF(1<=6,Assumptions!B15,IF(1<=9,Assumptions!B16,IF(1<=12,Assumptions!B17,IF(1<=18,Assumptions!B18,Assumptions!B19))))) | C15: =IF(2<=3,Assumptions!B14,IF(2<=6,Assumptions!B15,IF(2<=9,Assumptions!B16,IF(2<=12,Assumptions!B17,IF(2<=18,Assumptions!B18,Assumptions!B19))))) | D15: =IF(3<=3,Assumptions!B14,IF(3<=6,Assumptions!B15,IF(3<=9,Assumptions!B16,IF(3<=12,Assumptions!B17,IF(3<=18,Assumptions!B18,Assumptions!B19))))) | E15: =IF(4<=3,Assumptions!B14,IF(4<=6,Assumptions!B15,IF(4<=9,Assumptions!B16,IF(4<=12,Assumptions!B17,IF(4<=18,Assumptions!B18,Assumptions!B19))))) | F15: =IF(5<=3,Assumptions!B14,IF(5<=6,Assumptions!B15,IF(5<=9,Assumptions!B16,IF(5<=12,Assumptions!B17,IF(5<=18,Assumptions!B18,Assumptions!B19))))) | G15: =IF(6<=3,Assumptions!B14,IF(6<=6,Assumptions!B15,IF(6<=9,Assumptions!B16,IF(6<=12,Assumptions!B17,IF(6<=18,Assumptions!B18,Assumptions!B19))))) | H15: =IF(7<=3,Assumptions!B14,IF(7<=6,Assumptions!B15,IF(7<=9,Assumptions!B16,IF(7<=12,Assumptions!B17,IF(7<=18,Assumptions!B18,Assumptions!B19))))) | I15: =IF(8<=3,Assumptions!B14,IF(8<=6,Assumptions!B15,IF(8<=9,Assumptions!B16,IF(8<=12,Assumptions!B17,IF(8<=18,Assumptions!B18,Assumptions!B19))))) | J15: =IF(9<=3,Assumptions!B14,IF(9<=6,Assumptions!B15,IF(9<=9,Assumptions!B16,IF(9<=12,Assumptions!B17,IF(9<=18,Assumptions!B18,Assumptions!B19))))) | K15: =IF(10<=3,Assumptions!B14,IF(10<=6,Assumptions!B15,IF(10<=9,Assumptions!B16,IF(10<=12,Assumptions!B17,IF(10<=18,Assumptions!B18,Assumptions!B19))))) | L15: =IF(11<=3,Assumptions!B14,IF(11<=6,Assumptions!B15,IF(11<=9,Assumptions!B16,IF(11<=12,Assumptions!B17,IF(11<=18,Assumptions!B18,Assumptions!B19))))) | M15: =IF(12<=3,Assumptions!B14,IF(12<=6,Assumptions!B15,IF(12<=9,Assumptions!B16,IF(12<=12,Assumptions!B17,IF(12<=18,Assumptions!B18,Assumptions!B19))))) | N15: =IF(13<=3,Assumptions!B14,IF(13<=6,Assumptions!B15,IF(13<=9,Assumptions!B16,IF(13<=12,Assumptions!B17,IF(13<=18,Assumptions!B18,Assumptions!B19))))) | O15: =IF(14<=3,Assumptions!B14,IF(14<=6,Assumptions!B15,IF(14<=9,Assumptions!B16,IF(14<=12,Assumptions!B17,IF(14<=18,Assumptions!B18,Assumptions!B19))))) | P15: =IF(15<=3,Assumptions!B14,IF(15<=6,Assumptions!B15,IF(15<=9,Assumptions!B16,IF(15<=12,Assumptions!B17,IF(15<=18,Assumptions!B18,Assumptions!B19))))) | Q15: =IF(16<=3,Assumptions!B14,IF(16<=6,Assumptions!B15,IF(16<=9,Assumptions!B16,IF(16<=12,Assumptions!B17,IF(16<=18,Assumptions!B18,Assumptions!B19))))) | R15: =IF(17<=3,Assumptions!B14,IF(17<=6,Assumptions!B15,IF(17<=9,Assumptions!B16,IF(17<=12,Assumptions!B17,IF(17<=18,Assumptions!B18,Assumptions!B19))))) | S15: =IF(18<=3,Assumptions!B14,IF(18<=6,Assumptions!B15,IF(18<=9,Assumptions!B16,IF(18<=12,Assumptions!B17,IF(18<=18,Assumptions!B18,Assumptions!B19))))) | T15: =IF(19<=3,Assumptions!B14,IF(19<=6,Assumptions!B15,IF(19<=9,Assumptions!B16,IF(19<=12,Assumptions!B17,IF(19<=18,Assumptions!B18,Assumptions!B19))))) | U15: =IF(20<=3,Assumptions!B14,IF(20<=6,Assumptions!B15,IF(20<=9,Assumptions!B16,IF(20<=12,Assumptions!B17,IF(20<=18,Assumptions!B18,Assumptions!B19))))) | V15: =IF(21<=3,Assumptions!B14,IF(21<=6,Assumptions!B15,IF(21<=9,Assumptions!B16,IF(21<=12,Assumptions!B17,IF(21<=18,Assumptions!B18,Assumptions!B19))))) | W15: =IF(22<=3,Assumptions!B14,IF(22<=6,Assumptions!B15,IF(22<=9,Assumptions!B16,IF(22<=12,Assumptions!B17,IF(22<=18,Assumptions!B18,Assumptions!B19))))) | X15: =IF(23<=3,Assumptions!B14,IF(23<=6,Assumptions!B15,IF(23<=9,Assumptions!B16,IF(23<=12,Assumptions!B17,IF(23<=18,Assumptions!B18,Assumptions!B19))))) | Y15: =IF(24<=3,Assumptions!B14,IF(24<=6,Assumptions!B15,IF(24<=9,Assumptions!B16,IF(24<=12,Assumptions!B17,IF(24<=18,Assumptions!B18,Assumptions!B19)))))
A16: Churned Subs | B16: 0 | C16: =ROUND(B17*Assumptions!B8,0) | D16: =ROUND(C17*Assumptions!B8,0) | E16: =ROUND(D17*Assumptions!B8,0) | F16: =ROUND(E17*Assumptions!B8,0) | G16: =ROUND(F17*Assumptions!B8,0) | H16: =ROUND(G17*Assumptions!B8,0) | I16: =ROUND(H17*Assumptions!B8,0) | J16: =ROUND(I17*Assumptions!B8,0) | K16: =ROUND(J17*Assumptions!B8,0) | L16: =ROUND(K17*Assumptions!B8,0) | M16: =ROUND(L17*Assumptions!B8,0) | N16: =ROUND(M17*Assumptions!B8,0) | O16: =ROUND(N17*Assumptions!B8,0) | P16: =ROUND(O17*Assumptions!B8,0) | Q16: =ROUND(P17*Assumptions!B8,0) | R16: =ROUND(Q17*Assumptions!B8,0) | S16: =ROUND(R17*Assumptions!B8,0) | T16: =ROUND(S17*Assumptions!B8,0) | U16: =ROUND(T17*Assumptions!B8,0) | V16: =ROUND(U17*Assumptions!B8,0) | W16: =ROUND(V17*Assumptions!B8,0) | X16: =ROUND(W17*Assumptions!B8,0) | Y16: =ROUND(X17*Assumptions!B8,0)
A17: Total Subscribers | B17: =MAX(0,B15-B16) | C17: =MAX(0,B17-C16+C15) | D17: =MAX(0,C17-D16+D15) | E17: =MAX(0,D17-E16+E15) | F17: =MAX(0,E17-F16+F15) | G17: =MAX(0,F17-G16+G15) | H17: =MAX(0,G17-H16+H15) | I17: =MAX(0,H17-I16+I15) | J17: =MAX(0,I17-J16+J15) | ... Y17: =MAX(0,X17-Y16+Y15)
A18: Core Subs (52%) | B18: =ROUND(B17*Assumptions!B9,0) | C18: =ROUND(C17*Assumptions!B9,0) | D18: =ROUND(D17*Assumptions!B9,0) | E18: =ROUND(E17*Assumptions!B9,0) | F18: =ROUND(F17*Assumptions!B9,0) | G18: =ROUND(G17*Assumptions!B9,0) | H18: =ROUND(H17*Assumptions!B9,0) | I18: =ROUND(I17*Assumptions!B9,0) | J18: =ROUND(J17*Assumptions!B9,0) | K18: =ROUND(K17*Assumptions!B9,0) | L18: =ROUND(L17*Assumptions!B9,0) | M18: =ROUND(M17*Assumptions!B9,0) | N18: =ROUND(N17*Assumptions!B9,0) | O18: =ROUND(O17*Assumptions!B9,0) | P18: =ROUND(P17*Assumptions!B9,0) | Q18: =ROUND(Q17*Assumptions!B9,0) | R18: =ROUND(R17*Assumptions!B9,0) | S18: =ROUND(S17*Assumptions!B9,0) | T18: =ROUND(T17*Assumptions!B9,0) | U18: =ROUND(U17*Assumptions!B9,0) | V18: =ROUND(V17*Assumptions!B9,0) | W18: =ROUND(W17*Assumptions!B9,0) | X18: =ROUND(X17*Assumptions!B9,0) | Y18: =ROUND(Y17*Assumptions!B9,0)
A19: Pro Subs (38%) | B19: =ROUND(B17*Assumptions!B10,0) | C19: =ROUND(C17*Assumptions!B10,0) | D19: =ROUND(D17*Assumptions!B10,0) | E19: =ROUND(E17*Assumptions!B10,0) | F19: =ROUND(F17*Assumptions!B10,0) | G19: =ROUND(G17*Assumptions!B10,0) | H19: =ROUND(H17*Assumptions!B10,0) | I19: =ROUND(I17*Assumptions!B10,0) | J19: =ROUND(J17*Assumptions!B10,0) | K19: =ROUND(K17*Assumptions!B10,0) | L19: =ROUND(L17*Assumptions!B10,0) | M19: =ROUND(M17*Assumptions!B10,0) | N19: =ROUND(N17*Assumptions!B10,0) | O19: =ROUND(O17*Assumptions!B10,0) | P19: =ROUND(P17*Assumptions!B10,0) | Q19: =ROUND(Q17*Assumptions!B10,0) | R19: =ROUND(R17*Assumptions!B10,0) | S19: =ROUND(S17*Assumptions!B10,0) | T19: =ROUND(T17*Assumptions!B10,0) | U19: =ROUND(U17*Assumptions!B10,0) | V19: =ROUND(V17*Assumptions!B10,0) | W19: =ROUND(W17*Assumptions!B10,0) | X19: =ROUND(X17*Assumptions!B10,0) | Y19: =ROUND(Y17*Assumptions!B10,0)
A20: Premium Subs (10%) | B20: =MAX(0,B17-B18-B19) | C20: =MAX(0,C17-C18-C19) | D20: =MAX(0,D17-D18-D19) | E20: =MAX(0,E17-E18-E19) | F20: =MAX(0,F17-F18-F19) | G20: =MAX(0,G17-G18-G19) | H20: =MAX(0,H17-H18-H19) | I20: =MAX(0,I17-I18-I19) | ... Y20: =MAX(0,Y17-Y18-Y19)
A21: CGM Active Users | B21: 0 | C21: 0 | D21: 0 | E21: 0 | F21: 0 | G21: 0 | H21: 3 | I21: 6 | J21: 9 | K21: 12 | L21: 15 | M21: 18 | N21: 21 | O21: 24 | P21: 27 | Q21: 30 | R21: 32 | S21: 34 | T21: 36 | U21: 38 | V21: 39 | W21: 40 | X21: 41 | Y21: 42
A22: B2B Clients | B22: 0 | C22: 0 | D22: 0 | E22: 0 | F22: 0 | G22: 0 | H22: 0 | I22: 0 | J22: 1 | K22: 1 | L22: 1 | M22: 2 | N22: 2 | O22: 2 | P22: 2 | Q22: 2 | R22: 2 | S22: 3 | T22: 3 | U22: 3 | V22: 3 | W22: 3 | X22: 3 | Y22: 3

Sheet Cash Flow
A1: alche — Cash Flow Statement v3
A2: P5: EUR ~218K gap between P&L profit and actual cash. This sheet closes that gap.
A3: Cash Flow (EUR) | B3: M1 | C3: M2 | D3: M3 | E3: M4 | F3: M5 | G3: M6 | H3: M7 | I3: M8 | J3: M9 | K3: M10 | L3: M11 | M3: M12 | N3: M13 | O3: M14 | P3: M15 | Q3: M16 | R3: M17 | S3: M18 | T3: M19 | U3: M20 | V3: M21 | W3: M22 | X3: M23 | Y3: M24 | Z3: TOTAL
A4: OPERATING ACTIVITIES
A5: EBITDA | B5: ='P&L'!B133 | C5: ='P&L'!C133 | D5: ='P&L'!D133 | E5: ='P&L'!E133 | F5: ='P&L'!F133 | G5: ='P&L'!G133 | H5: ='P&L'!H133 | I5: ='P&L'!I133 | ... Y5: ='P&L'!Y133 | Z5: =SUM(B5:Y5)
A6: - Tax Provision | B6: =-'P&L'!B166 | C6: =-'P&L'!C166 | D6: =-'P&L'!D166 | E6: =-'P&L'!E166 | F6: =-'P&L'!F166 | G6: =-'P&L'!G166 | H6: =-'P&L'!H166 | I6: =-'P&L'!I166 | ... Y6: =-'P&L'!Y166 | Z6: =SUM(B6:Y6)
A7: - Working Capital Build (inventory) | B7: =-ROUND('Growth Curves'!B4*Assumptions!B23*2,0) | C7: =-ROUND(MAX(0,('Growth Curves'!C4-'Growth Curves'!B4)*Assumptions!B23*2),0) | D7: =-ROUND(MAX(0,('Growth Curves'!D4-'Growth Curves'!C4)*Assumptions!B23*2),0) | E7: =-ROUND(MAX(0,('Growth Curves'!E4-'Growth Curves'!D4)*Assumptions!B23*2),0) | F7: =-ROUND(MAX(0,('Growth Curves'!F4-'Growth Curves'!E4)*Assumptions!B23*2),0) | G7: =-ROUND(MAX(0,('Growth Curves'!G4-'Growth Curves'!F4)*Assumptions!B23*2),0) | H7: =-ROUND(MAX(0,('Growth Curves'!H4-'Growth Curves'!G4)*Assumptions!B23*2),0) | I7: =-ROUND(MAX(0,('Growth Curves'!I4-'Growth Curves'!H4)*Assumptions!B23*2),0) | J7: =-ROUND(MAX(0,('Growth Curves'!J4-'Growth Curves'!I4)*Assumptions!B23*2),0) | K7: =-ROUND(MAX(0,('Growth Curves'!K4-'Growth Curves'!J4)*Assumptions!B23*2),0) | L7: =-ROUND(MAX(0,('Growth Curves'!L4-'Growth Curves'!K4)*Assumptions!B23*2),0) | M7: =-ROUND(MAX(0,('Growth Curves'!M4-'Growth Curves'!L4)*Assumptions!B23*2),0) | N7: =-ROUND(MAX(0,('Growth Curves'!N4-'Growth Curves'!M4)*Assumptions!B23*2),0) | O7: =-ROUND(MAX(0,('Growth Curves'!O4-'Growth Curves'!N4)*Assumptions!B23*2),0) | P7: =-ROUND(MAX(0,('Growth Curves'!P4-'Growth Curves'!O4)*Assumptions!B23*2),0) | Q7: =-ROUND(MAX(0,('Growth Curves'!Q4-'Growth Curves'!P4)*Assumptions!B23*2),0) | R7: =-ROUND(MAX(0,('Growth Curves'!R4-'Growth Curves'!Q4)*Assumptions!B23*2),0) | S7: =-ROUND(MAX(0,('Growth Curves'!S4-'Growth Curves'!R4)*Assumptions!B23*2),0) | T7: =-ROUND(MAX(0,('Growth Curves'!T4-'Growth Curves'!S4)*Assumptions!B23*2),0) | U7: =-ROUND(MAX(0,('Growth Curves'!U4-'Growth Curves'!T4)*Assumptions!B23*2),0) | V7: =-ROUND(MAX(0,('Growth Curves'!V4-'Growth Curves'!U4)*Assumptions!B23*2),0) | W7: =-ROUND(MAX(0,('Growth Curves'!W4-'Growth Curves'!V4)*Assumptions!B23*2),0) | X7: =-ROUND(MAX(0,('Growth Curves'!X4-'Growth Curves'!W4)*Assumptions!B23*2),0) | Y7: =-ROUND(MAX(0,('Growth Curves'!Y4-'Growth Curves'!X4)*Assumptions!B23*2),0) | Z7: =SUM(B7:Y7)
A8: Operating Cash Flow | B8: =B5+B6+B7 | C8: =C5+C6+C7 | D8: =D5+D6+D7 | E8: =E5+E6+E7 | F8: =F5+F6+F7 | G8: =G5+G6+G7 | H8: =H5+H6+H7 | I8: =I5+I6+I7 | ... Y8: =Y5+Y6+Y7 | Z8: =SUM(B8:Y8)
A10: INVESTING ACTIVITIES
A11: CapEx | B11: =-'P&L'!B160 | C11: =-'P&L'!C160 | D11: =-'P&L'!D160 | E11: =-'P&L'!E160 | F11: =-'P&L'!F160 | G11: =-'P&L'!G160 | H11: =-'P&L'!H160 | I11: =-'P&L'!I160 | ... Y11: =-'P&L'!Y160 | Z11: =SUM(B11:Y11)
A12: Kaution — Security Deposit (M3) | B12: =IF(1=3,-Assumptions!B118,0) | C12: =IF(2=3,-Assumptions!B118,0) | D12: =IF(3=3,-Assumptions!B118,0) | E12: =IF(4=3,-Assumptions!B118,0) | F12: =IF(5=3,-Assumptions!B118,0) | G12: =IF(6=3,-Assumptions!B118,0) | H12: =IF(7=3,-Assumptions!B118,0) | I12: =IF(8=3,-Assumptions!B118,0) | J12: =IF(9=3,-Assumptions!B118,0) | K12: =IF(10=3,-Assumptions!B118,0) | L12: =IF(11=3,-Assumptions!B118,0) | M12: =IF(12=3,-Assumptions!B118,0) | N12: =IF(13=3,-Assumptions!B118,0) | O12: =IF(14=3,-Assumptions!B118,0) | P12: =IF(15=3,-Assumptions!B118,0) | Q12: =IF(16=3,-Assumptions!B118,0) | R12: =IF(17=3,-Assumptions!B118,0) | S12: =IF(18=3,-Assumptions!B118,0) | T12: =IF(19=3,-Assumptions!B118,0) | U12: =IF(20=3,-Assumptions!B118,0) | V12: =IF(21=3,-Assumptions!B118,0) | W12: =IF(22=3,-Assumptions!B118,0) | X12: =IF(23=3,-Assumptions!B118,0) | Y12: =IF(24=3,-Assumptions!B118,0) | Z12: =SUM(B12:Y12)
A13: Space Security Deposit M3 (EX-07: balance sheet, refundable) | B13: =IF(1=3,-Assumptions!B139,0) | C13: =IF(2=3,-Assumptions!B139,0) | D13: =IF(3=3,-Assumptions!B139,0) | E13: =IF(4=3,-Assumptions!B139,0) | F13: =IF(5=3,-Assumptions!B139,0) | G13: =IF(6=3,-Assumptions!B139,0) | H13: =IF(7=3,-Assumptions!B139,0) | I13: =IF(8=3,-Assumptions!B139,0) | J13: =IF(9=3,-Assumptions!B139,0) | K13: =IF(10=3,-Assumptions!B139,0) | L13: =IF(11=3,-Assumptions!B139,0) | M13: =IF(12=3,-Assumptions!B139,0) | N13: =IF(13=3,-Assumptions!B139,0) | O13: =IF(14=3,-Assumptions!B139,0) | P13: =IF(15=3,-Assumptions!B139,0) | Q13: =IF(16=3,-Assumptions!B139,0) | R13: =IF(17=3,-Assumptions!B139,0) | S13: =IF(18=3,-Assumptions!B139,0) | T13: =IF(19=3,-Assumptions!B139,0) | U13: =IF(20=3,-Assumptions!B139,0) | V13: =IF(21=3,-Assumptions!B139,0) | W13: =IF(22=3,-Assumptions!B139,0) | X13: =IF(23=3,-Assumptions!B139,0) | Y13: =IF(24=3,-Assumptions!B139,0) | Z13: =SUM(B13:Y13)
A14: Investing Cash Flow | B14: =B11+B12+B13 | C14: =C11+C12+C13 | D14: =D11+D12+D13 | E14: =E11+E12+E13 | F14: =F11+F12+F13 | G14: =G11+G12+G13 | H14: =H11+H12+H13 | I14: =I11+I12+I13 | ... Y14: =Y11+Y12+Y13 | Z14: =SUM(B14:Y14)
A16: FINANCING ACTIVITIES
A17: Pre-Seed Funding (M1) | B17: =IF(1=1,Assumptions!B142,0) | C17: =IF(2=1,Assumptions!B142,0) | D17: =IF(3=1,Assumptions!B142,0) | E17: =IF(4=1,Assumptions!B142,0) | F17: =IF(5=1,Assumptions!B142,0) | G17: =IF(6=1,Assumptions!B142,0) | H17: =IF(7=1,Assumptions!B142,0) | I17: =IF(8=1,Assumptions!B142,0) | J17: =IF(9=1,Assumptions!B142,0) | K17: =IF(10=1,Assumptions!B142,0) | L17: =IF(11=1,Assumptions!B142,0) | M17: =IF(12=1,Assumptions!B142,0) | N17: =IF(13=1,Assumptions!B142,0) | O17: =IF(14=1,Assumptions!B142,0) | P17: =IF(15=1,Assumptions!B142,0) | Q17: =IF(16=1,Assumptions!B142,0) | R17: =IF(17=1,Assumptions!B142,0) | S17: =IF(18=1,Assumptions!B142,0) | T17: =IF(19=1,Assumptions!B142,0) | U17: =IF(20=1,Assumptions!B142,0) | V17: =IF(21=1,Assumptions!B142,0) | W17: =IF(22=1,Assumptions!B142,0) | X17: =IF(23=1,Assumptions!B142,0) | Y17: =IF(24=1,Assumptions!B142,0) | Z17: =SUM(B17:Y17)
A18: Financing Cash Flow | B18: =B17 | C18: =C17 | D18: =D17 | E18: =E17 | F18: =F17 | G18: =G17 | H18: =H17 | I18: =I17 | ... Y18: =Y17 | Z18: =SUM(B18:Y18)
A20: NET CASH FLOW | B20: =B8+B14+B18 | C20: =C8+C14+C18 | D20: =D8+D14+D18 | E20: =E8+E14+E18 | F20: =F8+F14+F18 | G20: =G8+G14+G18 | H20: =H8+H14+H18 | I20: =I8+I14+I18 | ... Y20: =Y8+Y14+Y18 | Z20: =SUM(B20:Y20)
A21: CUMULATIVE CASH BALANCE | B21: =B20 | C21: =B21+C20 | D21: =C21+D20 | E21: =D21+E20 | F21: =E21+F20 | G21: =F21+G20 | H21: =G21+H20 | I21: =H21+I20 | J21: =I21+J20 | ... Y21: =X21+Y20 | Z21: =Y21
A23: P&L vs CASH GAP ANALYSIS
A24: P&L Cumulative Cash | B24: ='P&L'!B169 | C24: ='P&L'!C169 | D24: ='P&L'!D169 | E24: ='P&L'!E169 | F24: ='P&L'!F169 | G24: ='P&L'!G169 | H24: ='P&L'!H169 | I24: ='P&L'!I169 | ... Y24: ='P&L'!Y169 | Z24: =SUM(B24:Y24)
A25: Actual Cash (this sheet) | B25: =B21 | C25: =C21 | D25: =D21 | E25: =E21 | F25: =F21 | G25: =G21 | H25: =H21 | I25: =I21 | ... Y25: =Y21 | Z25: =SUM(B25:Y25)
A26: GAP (Working Capital Drag) | B26: =B25-B24 | C26: =C25-C24 | D26: =D25-D24 | E26: =E25-E24 | F26: =F25-F24 | G26: =G25-G24 | H26: =H25-H24 | I26: =I25-I24 | ... Y26: =Y25-Y24 | Z26: =SUM(B26:Y26)

Sheet Unit Economics
A1: alche — Unit Economics Dashboard
A2: P1/P5: LTV:CAC, payback period, contribution margin per stream
A3: Metric | B3: M1 | C3: M2 | D3: M3 | E3: M4 | F3: M5 | G3: M6 | H3: M7 | I3: M8 | J3: M9 | K3: M10 | L3: M11 | M3: M12 | N3: M13 | O3: M14 | P3: M15 | Q3: M16 | R3: M17 | S3: M18 | T3: M19 | U3: M20 | V3: M21 | W3: M22 | X3: M23 | Y3: M24 | Z3: TOTAL
A4: SUBSCRIPTION METRICS
A5: Subscription ARPU (EUR/sub/mo) | B5: =IF('Growth Curves'!B17>0,ROUND('P&L'!B42/'Growth Curves'!B17,2),0) | C5: =IF('Growth Curves'!C17>0,ROUND('P&L'!C42/'Growth Curves'!C17,2),0) | D5: =IF('Growth Curves'!D17>0,ROUND('P&L'!D42/'Growth Curves'!D17,2),0) | E5: =IF('Growth Curves'!E17>0,ROUND('P&L'!E42/'Growth Curves'!E17,2),0) | F5: =IF('Growth Curves'!F17>0,ROUND('P&L'!F42/'Growth Curves'!F17,2),0) | G5: =IF('Growth Curves'!G17>0,ROUND('P&L'!G42/'Growth Curves'!G17,2),0) | H5: =IF('Growth Curves'!H17>0,ROUND('P&L'!H42/'Growth Curves'!H17,2),0) | I5: =IF('Growth Curves'!I17>0,ROUND('P&L'!I42/'Growth Curves'!I17,2),0) | ... Y5: =IF('Growth Curves'!Y17>0,ROUND('P&L'!Y42/'Growth Curves'!Y17,2),0) | Z5: =Y5
A6: Subscription LTV (ARPU / churn) | B6: =IF('Growth Curves'!B17>0,ROUND(('P&L'!B42/'Growth Curves'!B17)/Assumptions!B8,0),0) | C6: =IF('Growth Curves'!C17>0,ROUND(('P&L'!C42/'Growth Curves'!C17)/Assumptions!B8,0),0) | D6: =IF('Growth Curves'!D17>0,ROUND(('P&L'!D42/'Growth Curves'!D17)/Assumptions!B8,0),0) | E6: =IF('Growth Curves'!E17>0,ROUND(('P&L'!E42/'Growth Curves'!E17)/Assumptions!B8,0),0) | F6: =IF('Growth Curves'!F17>0,ROUND(('P&L'!F42/'Growth Curves'!F17)/Assumptions!B8,0),0) | G6: =IF('Growth Curves'!G17>0,ROUND(('P&L'!G42/'Growth Curves'!G17)/Assumptions!B8,0),0) | H6: =IF('Growth Curves'!H17>0,ROUND(('P&L'!H42/'Growth Curves'!H17)/Assumptions!B8,0),0) | I6: =IF('Growth Curves'!I17>0,ROUND(('P&L'!I42/'Growth Curves'!I17)/Assumptions!B8,0),0) | J6: =IF('Growth Curves'!J17>0,ROUND(('P&L'!J42/'Growth Curves'!J17)/Assumptions!B8,0),0) | K6: =IF('Growth Curves'!K17>0,ROUND(('P&L'!K42/'Growth Curves'!K17)/Assumptions!B8,0),0) | L6: =IF('Growth Curves'!L17>0,ROUND(('P&L'!L42/'Growth Curves'!L17)/Assumptions!B8,0),0) | M6: =IF('Growth Curves'!M17>0,ROUND(('P&L'!M42/'Growth Curves'!M17)/Assumptions!B8,0),0) | N6: =IF('Growth Curves'!N17>0,ROUND(('P&L'!N42/'Growth Curves'!N17)/Assumptions!B8,0),0) | O6: =IF('Growth Curves'!O17>0,ROUND(('P&L'!O42/'Growth Curves'!O17)/Assumptions!B8,0),0) | P6: =IF('Growth Curves'!P17>0,ROUND(('P&L'!P42/'Growth Curves'!P17)/Assumptions!B8,0),0) | Q6: =IF('Growth Curves'!Q17>0,ROUND(('P&L'!Q42/'Growth Curves'!Q17)/Assumptions!B8,0),0) | R6: =IF('Growth Curves'!R17>0,ROUND(('P&L'!R42/'Growth Curves'!R17)/Assumptions!B8,0),0) | S6: =IF('Growth Curves'!S17>0,ROUND(('P&L'!S42/'Growth Curves'!S17)/Assumptions!B8,0),0) | T6: =IF('Growth Curves'!T17>0,ROUND(('P&L'!T42/'Growth Curves'!T17)/Assumptions!B8,0),0) | U6: =IF('Growth Curves'!U17>0,ROUND(('P&L'!U42/'Growth Curves'!U17)/Assumptions!B8,0),0) | V6: =IF('Growth Curves'!V17>0,ROUND(('P&L'!V42/'Growth Curves'!V17)/Assumptions!B8,0),0) | W6: =IF('Growth Curves'!W17>0,ROUND(('P&L'!W42/'Growth Curves'!W17)/Assumptions!B8,0),0) | X6: =IF('Growth Curves'!X17>0,ROUND(('P&L'!X42/'Growth Curves'!X17)/Assumptions!B8,0),0) | Y6: =IF('Growth Curves'!Y17>0,ROUND(('P&L'!Y42/'Growth Curves'!Y17)/Assumptions!B8,0),0) | Z6: =Y6
A7: CAC (paid ads / new subs) | B7: =IF('Growth Curves'!B15>0,ROUND('Growth Curves'!B10/'Growth Curves'!B15,0),0) | C7: =IF('Growth Curves'!C15>0,ROUND('Growth Curves'!C10/'Growth Curves'!C15,0),0) | D7: =IF('Growth Curves'!D15>0,ROUND('Growth Curves'!D10/'Growth Curves'!D15,0),0) | E7: =IF('Growth Curves'!E15>0,ROUND('Growth Curves'!E10/'Growth Curves'!E15,0),0) | F7: =IF('Growth Curves'!F15>0,ROUND('Growth Curves'!F10/'Growth Curves'!F15,0),0) | G7: =IF('Growth Curves'!G15>0,ROUND('Growth Curves'!G10/'Growth Curves'!G15,0),0) | H7: =IF('Growth Curves'!H15>0,ROUND('Growth Curves'!H10/'Growth Curves'!H15,0),0) | I7: =IF('Growth Curves'!I15>0,ROUND('Growth Curves'!I10/'Growth Curves'!I15,0),0) | ... Y7: =IF('Growth Curves'!Y15>0,ROUND('Growth Curves'!Y10/'Growth Curves'!Y15,0),0) | Z7: =Y7
A8: LTV:CAC Ratio | B8: =IF(B7>0,ROUND(B6/B7,1),0) | C8: =IF(C7>0,ROUND(C6/C7,1),0) | D8: =IF(D7>0,ROUND(D6/D7,1),0) | E8: =IF(E7>0,ROUND(E6/E7,1),0) | F8: =IF(F7>0,ROUND(F6/F7,1),0) | G8: =IF(G7>0,ROUND(G6/G7,1),0) | H8: =IF(H7>0,ROUND(H6/H7,1),0) | I8: =IF(I7>0,ROUND(I6/I7,1),0) | ... Y8: =IF(Y7>0,ROUND(Y6/Y7,1),0) | Z8: =Y8
A9: CAC Payback (months) | B9: =IF(AND(B6>0,B5>0),ROUND(B7/B5,1),0) | C9: =IF(AND(C6>0,C5>0),ROUND(C7/C5,1),0) | D9: =IF(AND(D6>0,D5>0),ROUND(D7/D5,1),0) | E9: =IF(AND(E6>0,E5>0),ROUND(E7/E5,1),0) | F9: =IF(AND(F6>0,F5>0),ROUND(F7/F5,1),0) | G9: =IF(AND(G6>0,G5>0),ROUND(G7/G5,1),0) | H9: =IF(AND(H6>0,H5>0),ROUND(H7/H5,1),0) | I9: =IF(AND(I6>0,I5>0),ROUND(I7/I5,1),0) | ... Y9: =IF(AND(Y6>0,Y5>0),ROUND(Y7/Y5,1),0) | Z9: =Y9
A11: CONTRIBUTION MARGIN BY STREAM
A12: Retail Contribution Margin % | B12: =IF('P&L'!B17>0,('P&L'!B17-'P&L'!B51-'P&L'!B52-'P&L'!B53)/'P&L'!B17,0) | C12: =IF('P&L'!C17>0,('P&L'!C17-'P&L'!C51-'P&L'!C52-'P&L'!C53)/'P&L'!C17,0) | D12: =IF('P&L'!D17>0,('P&L'!D17-'P&L'!D51-'P&L'!D52-'P&L'!D53)/'P&L'!D17,0) | E12: =IF('P&L'!E17>0,('P&L'!E17-'P&L'!E51-'P&L'!E52-'P&L'!E53)/'P&L'!E17,0) | F12: =IF('P&L'!F17>0,('P&L'!F17-'P&L'!F51-'P&L'!F52-'P&L'!F53)/'P&L'!F17,0) | G12: =IF('P&L'!G17>0,('P&L'!G17-'P&L'!G51-'P&L'!G52-'P&L'!G53)/'P&L'!G17,0) | H12: =IF('P&L'!H17>0,('P&L'!H17-'P&L'!H51-'P&L'!H52-'P&L'!H53)/'P&L'!H17,0) | I12: =IF('P&L'!I17>0,('P&L'!I17-'P&L'!I51-'P&L'!I52-'P&L'!I53)/'P&L'!I17,0) | ... Y12: =IF('P&L'!Y17>0,('P&L'!Y17-'P&L'!Y51-'P&L'!Y52-'P&L'!Y53)/'P&L'!Y17,0) | Z12: =Y12
A13: LED Therapy Contribution Margin % | B13: =IF('P&L'!B21>0,('P&L'!B21-'P&L'!B54)/'P&L'!B21,0) | C13: =IF('P&L'!C21>0,('P&L'!C21-'P&L'!C54)/'P&L'!C21,0) | D13: =IF('P&L'!D21>0,('P&L'!D21-'P&L'!D54)/'P&L'!D21,0) | E13: =IF('P&L'!E21>0,('P&L'!E21-'P&L'!E54)/'P&L'!E21,0) | F13: =IF('P&L'!F21>0,('P&L'!F21-'P&L'!F54)/'P&L'!F21,0) | G13: =IF('P&L'!G21>0,('P&L'!G21-'P&L'!G54)/'P&L'!G21,0) | H13: =IF('P&L'!H21>0,('P&L'!H21-'P&L'!H54)/'P&L'!H21,0) | I13: =IF('P&L'!I21>0,('P&L'!I21-'P&L'!I54)/'P&L'!I21,0) | ... Y13: =IF('P&L'!Y21>0,('P&L'!Y21-'P&L'!Y54)/'P&L'!Y21,0) | Z13: =Y13
A14: Smoothie Bar Contribution Margin % | B14: =IF('P&L'!B25>0,('P&L'!B25-'P&L'!B56)/'P&L'!B25,0) | C14: =IF('P&L'!C25>0,('P&L'!C25-'P&L'!C56)/'P&L'!C25,0) | D14: =IF('P&L'!D25>0,('P&L'!D25-'P&L'!D56)/'P&L'!D25,0) | E14: =IF('P&L'!E25>0,('P&L'!E25-'P&L'!E56)/'P&L'!E25,0) | F14: =IF('P&L'!F25>0,('P&L'!F25-'P&L'!F56)/'P&L'!F25,0) | G14: =IF('P&L'!G25>0,('P&L'!G25-'P&L'!G56)/'P&L'!G25,0) | H14: =IF('P&L'!H25>0,('P&L'!H25-'P&L'!H56)/'P&L'!H25,0) | I14: =IF('P&L'!I25>0,('P&L'!I25-'P&L'!I56)/'P&L'!I25,0) | ... Y14: =IF('P&L'!Y25>0,('P&L'!Y25-'P&L'!Y56)/'P&L'!Y25,0) | Z14: =Y14
A15: Subscription Contribution Margin % | B15: =IF('P&L'!B42>0,('P&L'!B42-'P&L'!B59)/'P&L'!B42,0) | C15: =IF('P&L'!C42>0,('P&L'!C42-'P&L'!C59)/'P&L'!C42,0) | D15: =IF('P&L'!D42>0,('P&L'!D42-'P&L'!D59)/'P&L'!D42,0) | E15: =IF('P&L'!E42>0,('P&L'!E42-'P&L'!E59)/'P&L'!E42,0) | F15: =IF('P&L'!F42>0,('P&L'!F42-'P&L'!F59)/'P&L'!F42,0) | G15: =IF('P&L'!G42>0,('P&L'!G42-'P&L'!G59)/'P&L'!G42,0) | H15: =IF('P&L'!H42>0,('P&L'!H42-'P&L'!H59)/'P&L'!H42,0) | I15: =IF('P&L'!I42>0,('P&L'!I42-'P&L'!I59)/'P&L'!I42,0) | ... Y15: =IF('P&L'!Y42>0,('P&L'!Y42-'P&L'!Y59)/'P&L'!Y42,0) | Z15: =Y15
A17: REVENUE MIX (P5: only 4.7% subs at M24)
A18: Retail % | B18: =IF('P&L'!B47>0,'P&L'!B17/'P&L'!B47,0) | C18: =IF('P&L'!C47>0,'P&L'!C17/'P&L'!C47,0) | D18: =IF('P&L'!D47>0,'P&L'!D17/'P&L'!D47,0) | E18: =IF('P&L'!E47>0,'P&L'!E17/'P&L'!E47,0) | F18: =IF('P&L'!F47>0,'P&L'!F17/'P&L'!F47,0) | G18: =IF('P&L'!G47>0,'P&L'!G17/'P&L'!G47,0) | H18: =IF('P&L'!H47>0,'P&L'!H17/'P&L'!H47,0) | I18: =IF('P&L'!I47>0,'P&L'!I17/'P&L'!I47,0) | ... Y18: =IF('P&L'!Y47>0,'P&L'!Y17/'P&L'!Y47,0) | Z18: =Y18
A19: LED % | B19: =IF('P&L'!B47>0,'P&L'!B21/'P&L'!B47,0) | C19: =IF('P&L'!C47>0,'P&L'!C21/'P&L'!C47,0) | D19: =IF('P&L'!D47>0,'P&L'!D21/'P&L'!D47,0) | E19: =IF('P&L'!E47>0,'P&L'!E21/'P&L'!E47,0) | F19: =IF('P&L'!F47>0,'P&L'!F21/'P&L'!F47,0) | G19: =IF('P&L'!G47>0,'P&L'!G21/'P&L'!G47,0) | H19: =IF('P&L'!H47>0,'P&L'!H21/'P&L'!H47,0) | I19: =IF('P&L'!I47>0,'P&L'!I21/'P&L'!I47,0) | ... Y19: =IF('P&L'!Y47>0,'P&L'!Y21/'P&L'!Y47,0) | Z19: =Y19
A20: Smoothie % | B20: =IF('P&L'!B47>0,'P&L'!B25/'P&L'!B47,0) | C20: =IF('P&L'!C47>0,'P&L'!C25/'P&L'!C47,0) | D20: =IF('P&L'!D47>0,'P&L'!D25/'P&L'!D47,0) | E20: =IF('P&L'!E47>0,'P&L'!E25/'P&L'!E47,0) | F20: =IF('P&L'!F47>0,'P&L'!F25/'P&L'!F47,0) | G20: =IF('P&L'!G47>0,'P&L'!G25/'P&L'!G47,0) | H20: =IF('P&L'!H47>0,'P&L'!H25/'P&L'!H47,0) | I20: =IF('P&L'!I47>0,'P&L'!I25/'P&L'!I47,0) | ... Y20: =IF('P&L'!Y47>0,'P&L'!Y25/'P&L'!Y47,0) | Z20: =Y20
A21: Events % | B21: =IF('P&L'!B47>0,'P&L'!B31/'P&L'!B47,0) | C21: =IF('P&L'!C47>0,'P&L'!C31/'P&L'!C47,0) | D21: =IF('P&L'!D47>0,'P&L'!D31/'P&L'!D47,0) | E21: =IF('P&L'!E47>0,'P&L'!E31/'P&L'!E47,0) | F21: =IF('P&L'!F47>0,'P&L'!F31/'P&L'!F47,0) | G21: =IF('P&L'!G47>0,'P&L'!G31/'P&L'!G47,0) | H21: =IF('P&L'!H47>0,'P&L'!H31/'P&L'!H47,0) | I21: =IF('P&L'!I47>0,'P&L'!I31/'P&L'!I47,0) | ... Y21: =IF('P&L'!Y47>0,'P&L'!Y31/'P&L'!Y47,0) | Z21: =Y21
A22: Doctor SaaS % | B22: =IF('P&L'!B47>0,'P&L'!B35/'P&L'!B47,0) | C22: =IF('P&L'!C47>0,'P&L'!C35/'P&L'!C47,0) | D22: =IF('P&L'!D47>0,'P&L'!D35/'P&L'!D47,0) | E22: =IF('P&L'!E47>0,'P&L'!E35/'P&L'!E47,0) | F22: =IF('P&L'!F47>0,'P&L'!F35/'P&L'!F47,0) | G22: =IF('P&L'!G47>0,'P&L'!G35/'P&L'!G47,0) | H22: =IF('P&L'!H47>0,'P&L'!H35/'P&L'!H47,0) | I22: =IF('P&L'!I47>0,'P&L'!I35/'P&L'!I47,0) | ... Y22: =IF('P&L'!Y47>0,'P&L'!Y35/'P&L'!Y47,0) | Z22: =Y22
A23: CGM % | B23: =IF('P&L'!B47>0,'P&L'!B36/'P&L'!B47,0) | C23: =IF('P&L'!C47>0,'P&L'!C36/'P&L'!C47,0) | D23: =IF('P&L'!D47>0,'P&L'!D36/'P&L'!D47,0) | E23: =IF('P&L'!E47>0,'P&L'!E36/'P&L'!E47,0) | F23: =IF('P&L'!F47>0,'P&L'!F36/'P&L'!F47,0) | G23: =IF('P&L'!G47>0,'P&L'!G36/'P&L'!G47,0) | H23: =IF('P&L'!H47>0,'P&L'!H36/'P&L'!H47,0) | I23: =IF('P&L'!I47>0,'P&L'!I36/'P&L'!I47,0) | ... Y23: =IF('P&L'!Y47>0,'P&L'!Y36/'P&L'!Y47,0) | Z23: =Y23
A24: B2B Corporate % | B24: =IF('P&L'!B47>0,'P&L'!B44/'P&L'!B47,0) | C24: =IF('P&L'!C47>0,'P&L'!C44/'P&L'!C47,0) | D24: =IF('P&L'!D47>0,'P&L'!D44/'P&L'!D47,0) | E24: =IF('P&L'!E47>0,'P&L'!E44/'P&L'!E47,0) | F24: =IF('P&L'!F47>0,'P&L'!F44/'P&L'!F47,0) | G24: =IF('P&L'!G47>0,'P&L'!G44/'P&L'!G47,0) | H24: =IF('P&L'!H47>0,'P&L'!H44/'P&L'!H47,0) | I24: =IF('P&L'!I47>0,'P&L'!I44/'P&L'!I47,0) | ... Y24: =IF('P&L'!Y47>0,'P&L'!Y44/'P&L'!Y47,0) | Z24: =Y24
A25: Gift Cards % | B25: =IF('P&L'!B47>0,'P&L'!B45/'P&L'!B47,0) | C25: =IF('P&L'!C47>0,'P&L'!C45/'P&L'!C47,0) | D25: =IF('P&L'!D47>0,'P&L'!D45/'P&L'!D47,0) | E25: =IF('P&L'!E47>0,'P&L'!E45/'P&L'!E47,0) | F25: =IF('P&L'!F47>0,'P&L'!F45/'P&L'!F47,0) | G25: =IF('P&L'!G47>0,'P&L'!G45/'P&L'!G47,0) | H25: =IF('P&L'!H47>0,'P&L'!H45/'P&L'!H47,0) | I25: =IF('P&L'!I47>0,'P&L'!I45/'P&L'!I47,0) | ... Y25: =IF('P&L'!Y47>0,'P&L'!Y45/'P&L'!Y47,0) | Z25: =Y25
A26: Subscriptions % | B26: =IF('P&L'!B47>0,'P&L'!B42/'P&L'!B47,0) | C26: =IF('P&L'!C47>0,'P&L'!C42/'P&L'!C47,0) | D26: =IF('P&L'!D47>0,'P&L'!D42/'P&L'!D47,0) | E26: =IF('P&L'!E47>0,'P&L'!E42/'P&L'!E47,0) | F26: =IF('P&L'!F47>0,'P&L'!F42/'P&L'!F47,0) | G26: =IF('P&L'!G47>0,'P&L'!G42/'P&L'!G47,0) | H26: =IF('P&L'!H47>0,'P&L'!H42/'P&L'!H47,0) | I26: =IF('P&L'!I47>0,'P&L'!I42/'P&L'!I47,0) | ... Y26: =IF('P&L'!Y47>0,'P&L'!Y42/'P&L'!Y47,0) | Z26: =Y26

Sheet Scenarios
A1: alche — Scenario Summary
A2: Base = current model. Bull/Bear use multipliers from Assumptions sheet.
A4: Metric | B4: BASE | C4: BULL (1.3x rev) | D4: BEAR (0.6x rev)
A5: Total Revenue (24-mo) | B5: ='P&L'!Z47 | C5: =ROUND('P&L'!Z47*Assumptions!B121,0) | D5: =ROUND('P&L'!Z47*Assumptions!B123,0)
A6: Total COGS (24-mo) | B6: ='P&L'!Z64 | C6: =ROUND('P&L'!Z64*Assumptions!B121,0) | D6: =ROUND('P&L'!Z64*Assumptions!B123,0)
A7: Gross Profit (24-mo) | B7: ='P&L'!Z66 | C7: =C5-C6 | D7: =ROUND('P&L'!Z66*Assumptions!B123,0)
A8: Total OpEx (24-mo) | B8: ='P&L'!Z124 | C8: =ROUND('P&L'!Z124*(0.85+0.15*Assumptions!B121),0) | D8: =ROUND('P&L'!Z124*(0.85+0.15*Assumptions!B123),0)
A9: Total CapEx (24-mo) | B9: ='P&L'!Z160 | C9: ='P&L'!Z160 | D9: ='P&L'!Z160
A10: EBITDA (24-mo) | B10: =B7-B8 | C10: =C7-C8 | D10: =D7-D8
A11: Net P&L (24-mo, pre-tax) | B11: =B10-B9 | C11: =C10-C9 | D11: =D10-D9
A12: Estimated Cash at M24 | B12: =Assumptions!B142+B11 | C12: =Assumptions!B142+C11 | D12: =Assumptions!B142+D11
A14: INTERPRETATION
A15: Bear case: shows if EUR 500K is sufficient
A16: If Bear cash < 0 → raise needs to increase or scope must be reduced
A17: Bull case: shows working capital stress at higher volume (P5)

Sheet Decisions
A1: alche — Decision Log (D1-D11) + Persona Audit
A2: All decisions from P&L sessions, 2026-02-22/23. 7 persona audits completed.
A4: # | B4: Decision | C4: Choice Made | D4: Old Value | E4: P&L Impact
A5: D1 | B5: Doctor Revenue | C5: C. SaaS EUR 99/mo × 20 clinics | D5: EUR 150/mo × 865 | E5: Revenue -75%; legally safe (StGB §299a)
A6: D2 | B6: Restaurant Revenue | C6: B. Phase 2 (500+ users) | D6: EUR 1.50/cover M6+ | E6: EUR 0 all 24 months
A7: D3 | B7: CGM Hardware | C7: Commission — Premium 3-mo gate or add-on | D7: EUR 130 × units (old) | E7: EUR 15/user/mo referral commission; starts M7; Premium gate 3-mo; COGS = 0
A8: D4 | B8: Physical Space | C8: A. Smoothie bar + space | D8: EUR 0 | E8: New rev + EUR 2,825/mo (rent+Nebenkosten) + CapEx
A9: D5 | B9: CapEx Section | C9: Yes, include | D9: All OpEx | E9: EUR ~148K total (v3.3: +EUR 50K Ablöse)
A10: D6 | B10: AI Cost Model | C10: Both internal + user-facing | D10: EUR 210 + EUR 499 Terra | E10: EUR 210 + EUR 0.35/sub (R9)
A11: D7 | B11: Product Waste | C11: Category-weighted | D11: Flat 5% | E11: 5.5% blended
A12: D8 | B12: Terra CGM API | C12: Defer — free HealthKit | D12: EUR 499/mo M6+ | E12: Saves EUR 9,481
A13: D9 | B13: SaaS Stack | C13: Itemized (R8) | D13: EUR 350→1800 | E13: EUR 338→500→750
A14: D10 | B14: Menu Analysis | C14: EUR 0 — founders do it | D14: EUR 500/mo | E14: Saves EUR 12,000
A15: D11 | B15: Retail Products | C15: EUR 49 validated; COGS EUR 23.50; 3PL from M4 | D15: EUR 11.50 COGS; 3PL from M6 | E15: Margin 76% → 52% (R10); 3PL start moved M6 → M4 (space opens M4)
A18: MODEL CORRECTIONS (v3.1 / v3.2)
A19: # | B19: Correction | C19: Change Made | D19: Previous | E19: Impact
A20: v3.1 | B20: Growth Marketer removed | C20: Timu IS the growth marketer | D20: EUR 4,500/mo from M12 | E20: Saves EUR 73K (M12-M24)
A21: v3.1 | B21: Subscribers gated to M4+ | C21: App launches with space | D21: 3 new subs/mo from M1 | E21: M1-M3: zero subs, zero sub revenue
A22: v3.1 | B22: UX/UI → CapEx | C22: EUR 15K one-off App Design (M1) | D22: EUR 800/mo OpEx | E22: Saves EUR 19.2K OpEx, adds EUR 15K CapEx
A23: v3.1 | B23: B19 note update | C23: 'Scaling phase' | D23: 'Growth marketer effect' | E23: Label only — no financial impact
A24: v3.2 | B24: LED therapy → free | C24: EUR 0 price, self-service | D24: EUR 45/session, EUR 25 practitioner | E24: Forgoes ~EUR 151K rev, saves ~EUR 84K COGS
A25: v3.3 | B25: Ablöse (key money) added | C25: EUR 50K M3 CapEx, amortized 36mo | D25: Not modeled | E25: CapEx EUR 98K → EUR 148K; tighter runway
A26: v3.3 | B26: Kaution (security deposit) | C26: EUR 7.5K M3 cash outflow | D26: Not modeled | E26: Cash Flow only — refundable, not P&L
A28: 7-PERSONA AUDIT RESULTS
A29: # | B29: Persona | C29: Key Finding | D29: EUR Impact | E29: Status in v3
A30: P1 | B30: Angel Investor | C30: EUR 113-236K missing costs; CAC EUR 40 too low | D30: EUR 175K midpoint gap | E30: All items added
A31: P2 | B31: Steuerberater | C31: GewSt 14.35% + KSt 15.825% = ~30% tax; IHK EUR 120/yr | D31: ~EUR 3K/mo when profitable | E31: Tax provision added
A32: P3 | B32: Operations Manager | C32: Rent is Kaltmiete; buildout EUR 25K+; utilities EUR 500 | D32: +EUR 665-1,600/mo | E32: Nebenkosten, buildout, utilities updated
A33: P4 | B33: Food Safety Inspector | C33: No Gaststättenerlaubnis needed; NMN NOT EU approved | D33: +EUR 2.6-5.8K one-off | E33: HACCP, hygiene, food safety added
A34: P5 | B34: Growth CFO | C34: EUR 218K P&L vs cash gap; ARPU EUR 38.44 not EUR 49 | D34: Working capital critical | E34: Cash flow sheet added
A35: P6 | B35: Compliance Legal | C35: DSB mandatory; DPIA mandatory; insurance EUR 650/mo | D35: +EUR 29.5-53K one-off | E35: DSB, DPIA, MDR, insurance split added
A36: P7 | B36: HR Manager | C36: CTO recruitment EUR 18K; employer multiplier 1.25x | D36: +EUR 16-27K one-off | E36: Recruitment, multiplier, onboarding added
